Workbook

Sheet M&A
C2: Netflix Warner Brothers M&A Model
C3: In millions, except per share data
C5: Date | D5: 46104
C6: Tax Structure | D6: Stock Sale
C8: TRANSACTION ASSUMPTIONS | F8: SOURCES & USES OF FUNDS | I8: ACCRETION/DILUTION ANALYSIS
C10: Acquirer | F10: Sources of Funds | I10: EPS Accounting: | J10: GAAP EPS | M10: 2026 | N10: 2027 | O10: 2028 | P10: 2029 | Q10: 2030
C11: Name | D11: Netflix | F11: New borrowing to acquire target | G11: =D50 -> 22983.534 | M11: =EOMONTH(L11,12) -> 397 | N11: =EOMONTH(M11,12) -> 762 | O11: =EOMONTH(N11,12) -> 1127 | P11: =EOMONTH(O11,12) -> 1492 | Q11: =EOMONTH(P11,12) -> 1858
C12: Ticker | D12: NASDAQ: NFLX | F12: New borrowing to refinance target debt | G12: =D55 -> 32428 | I12: Acquirer
C13: Latest Fiscal Year End Date | D13: 46022 | F13: Cash used to acquire target | G13: =D51 -> 5745.8835 | I13: Net income | M13: ='Acquirer Financials'!I27 -> 13536.447 | N13: ='Acquirer Financials'!J27 -> 15881.033 | O13: ='Acquirer Financials'!K27 -> 18161.911 | P13: ='Acquirer Financials'!L27 -> 20333.34 | Q13: ='Acquirer Financials'!M27 -> 22816.336
C14: Latest Filing Date | D14: 46045 | F14: Value of stock issued to acquire target | G14: =D31*D28 -> 43094.126 | I14: =J10 -> GAAP EPS | M14: =IF($J$10="GAAP EPS",'Acquirer Financials'!I227,'Acquirer Financials'!I234) -> 3.1926939 | N14: =IF($J$10="GAAP EPS",'Acquirer Financials'!J227,'Acquirer Financials'!J234) -> 3.7406187 | O14: =IF($J$10="GAAP EPS",'Acquirer Financials'!K227,'Acquirer Financials'!K234) -> 4.2736667 | P14: =IF($J$10="GAAP EPS",'Acquirer Financials'!L227,'Acquirer Financials'!L234) -> 4.7811343 | Q14: =IF($J$10="GAAP EPS",'Acquirer Financials'!M227,'Acquirer Financials'!M234) -> 5.3614511
C15: Filing Type | D15: 10-K | F15: Cash for fees | G15: =D39+D63 -> 636.17539 | I15: Diluted shares outstanding | M15: ='Acquirer Financials'!I226 -> 4239.8199 | N15: ='Acquirer Financials'!J226 -> 4245.5633 | O15: ='Acquirer Financials'!K226 -> 4249.7258 | P15: ='Acquirer Financials'!L226 -> 4252.8277 | Q15: ='Acquirer Financials'!M226 -> 4255.6269
C16: Current Share Price | D16: 93.38 | F16: Total sources | G16: =SUM(G11:G15) -> 104887.72
I17: Target
C18: Target | F18: Uses of Funds | I18: Net income | M18: ='Target Financials'!I31 -> -477.39566 | N18: ='Target Financials'!J31 -> 939.94184 | O18: ='Target Financials'!K31 -> 1277.1121 | P18: ='Target Financials'!L31 -> 1605.2706 | Q18: ='Target Financials'!M31 -> 1775.729
C19: Name | D19: Warner Brothers | F19: Stock to target | G19: =D16*D33 -> 43094.126 | I19: =J10 -> GAAP EPS | M19: =IF($J$10="GAAP EPS",'Target Financials'!I255,'Target Financials'!I261) -> -0.18315193 | N19: =IF($J$10="GAAP EPS",'Target Financials'!J255,'Target Financials'!J261) -> 0.3653954 | O19: =IF($J$10="GAAP EPS",'Target Financials'!K255,'Target Financials'!K261) -> 0.49046415 | P19: =IF($J$10="GAAP EPS",'Target Financials'!L255,'Target Financials'!L261) -> 0.61715748 | Q19: =IF($J$10="GAAP EPS",'Target Financials'!M255,'Target Financials'!M261) -> 0.68309406
C20: Ticker | D20: NASDAQ: WBD | F20: Cash to target | G20: =D32*D28 -> 28729.417 | I20: Diluted shares outstanding | M20: ='Target Financials'!I254 -> 2606.5554 | N20: ='Target Financials'!J254 -> 2572.3965 | O20: ='Target Financials'!K254 -> 2603.8847 | P20: ='Target Financials'!L254 -> 2601.0713 | Q20: ='Target Financials'!M254 -> 2599.538
C21: Latest Fiscal Year End Date | D21: 46022 | F21: Target debt refinanced | G21: =D55 -> 32428
C22: Latest Filing Date | D22: 46080 | F22: Deal fees | G22: =D39 -> 359.11772 | I22: Transaction related expenses/income
C23: Filing Type | D23: 10-K | F23: Financing fees | G23: =D63 -> 277.05767 | I23: Less: Interest expense from new deal debt | M23: =-$D$56*$D$65 -> -2864.15 | N23: =-$D$56*$D$65 -> -2864.15 | O23: =-$D$56*$D$65 -> -2864.15 | P23: =-$D$56*$D$65 -> -2864.15 | Q23: =-$D$56*$D$65 -> -2864.15
C24: Current Share Price | D24: 27.4 | F24: Total Uses | G24: =SUM(G19:G23) -> 104887.72 | I24: Less: Interest income on cash forgone | M24: =-($G$15+$G$13)*$D$66 -> -201.94116 | N24: =-($G$15+$G$13)*$D$66 -> -201.94116 | O24: =-($G$15+$G$13)*$D$66 -> -201.94116 | P24: =-($G$15+$G$13)*$D$66 -> -201.94116 | Q24: =-($G$15+$G$13)*$D$66 -> -201.94116
C25: % offer premium | D25: =D26/D24-1 -> 0.012773723 | I25: Plus: Synergies | M25: =$D$40 -> 3000 | N25: =$D$40 -> 3000 | O25: =$D$40 -> 3000 | P25: =$D$40 -> 3000 | Q25: =$D$40 -> 3000
C26: Offer Price per Share | D26: 27.75 | I26: Less: Incremental D&A expense | M26: =IF($J$10="GAAP EPS",-($G$34+$G$41),0) -> -5251.2725 | N26: =IF($J$10="GAAP EPS",-($G$34+$G$41),0) -> -5251.2725 | O26: =IF($J$10="GAAP EPS",-($G$34+$G$41),0) -> -5251.2725 | P26: =IF($J$10="GAAP EPS",-($G$34+$G$41),0) -> -5251.2725 | Q26: =IF($J$10="GAAP EPS",-($G$34+$G$41),0) -> -5251.2725
C27: Diluted Shares Outstanding | D27: =Shares!G31 -> 2588.2358 | F27: WRITE-UPS & PURCHASE PRICE ALLOCATION | I27: Taxes (assumed at acquirer's rate) | M27: =-SUM(M23:M26)*$D$44 -> 753.47044 | N27: =-SUM(N23:N26)*$D$44 -> 753.47044 | O27: =-SUM(O23:O26)*$D$44 -> 753.47044 | P27: =-SUM(P23:P26)*$D$44 -> 753.47044 | Q27: =-SUM(Q23:Q26)*$D$44 -> 753.47044
C28: Offer Value | D28: =D26*D27 -> 71823.543 | I28: Total after tax transaction related income/ (expenses) | M28: =SUM(M23:M27) -> -4563.8933 | N28: =SUM(N23:N27) -> -4563.8933 | O28: =SUM(O23:O27) -> -4563.8933 | P28: =SUM(P23:P27) -> -4563.8933 | Q28: =SUM(Q23:Q27) -> -4563.8933
F29: Asset Write-Ups
C30: Deal Structure | F30: Book value of target PP&E | G30: ='Target Financials'!I62 -> 6691.2317 | I30: ="Pro Forma "&LEFT(J10,FIND(" ",J10)-1)&" Net Income" -> Pro Forma GAAP Net Income | M30: ='Pro Forma Financials'!D31 -> 10986.366 | N30: ='Pro Forma Financials'!E31 -> 15216.943 | O30: ='Pro Forma Financials'!F31 -> 17923.85 | P30: ='Pro Forma Financials'!G31 -> 20473.027 | Q30: ='Pro Forma Financials'!H31 -> 23150.51
C31: % Stock | D31: 0.6 | F31: % Write-up | G31: 0.2 | I31: Pro Forma Shares Outstanding | M31: =M15+$D$33 -> 4701.3119 | N31: =N15+$D$33 -> 4707.0553 | O31: =O15+$D$33 -> 4711.2178 | P31: =P15+$D$33 -> 4714.3197 | Q31: =Q15+$D$33 -> 4717.1189
C32: % Cash | D32: =1-D31 -> 0.4 | F32: Asset write-up | G32: =G30*G31 -> 1338.2463
C33: Acquirer Shares Issued in Transaction | D33: =D31*D28/D16 -> 461.49203 | F33: Useful life | G33: ='Target Financials'!D188 -> 8 | I33: ="Pro forma "&J10 -> Pro forma GAAP EPS | M33: =M30/M31 -> 2.3368723 | N33: =N30/N31 -> 3.2327946 | O33: =O30/O31 -> 3.8045046 | P33: =P30/P31 -> 4.3427321 | Q33: =Q30/Q31 -> 4.9077648
C34: Nominal Exchange Ratio (offer price/acq share price) | D34: =D26/D16 -> 0.29717284 | F34: Incremental depreciation expense | G34: =G32/G33 -> 167.28079 | I34: Acquirer standalone EPS | M34: =M14 -> 3.1926939 | N34: =N14 -> 3.7406187 | O34: =O14 -> 4.2736667 | P34: =P14 -> 4.7811343 | Q34: =Q14 -> 5.3614511
C35: Actual exchange ratio (% stock x offer price/acq share price) | D35: =D31*D26/D16 -> 0.17830371 | F35: Incremental deferred tax liabilities | G35: =IF($D$6="Stock sale",G32*D44,0) -> 189.62951 | I35: Accretion / Dilution per share | M35: =M33-M34 -> -0.85582162 | N35: =N33-N34 -> -0.50782407 | O35: =O33-O34 -> -0.46916205 | P35: =P33-P34 -> -0.43840224 | Q35: =Q33-Q34 -> -0.4536863
I36: Accretion / Dilution % | M36: =M35/M34 -> -0.26805627 | N36: =N35/N34 -> -0.13575938 | O36: =O35/O34 -> -0.10977975 | P36: =P35/P34 -> -0.091694191 | Q36: =Q35/Q34 -> -0.084620058
C37: Other Assumptions | F37: Book value of target intangible assets | G37: ='Target Financials'!I64 -> 47049.129 | I37: Additional pretax synergies required to breakeven | M37: =MAX(0,-(M35*M31/(1-$D$44))) -> 4687.7367 | N37: =MAX(0,-(N35*N31/(1-$D$44))) -> 2784.9889 | O37: =MAX(0,-(O35*O31/(1-$D$44))) -> 2575.2355 | P37: =MAX(0,-(P35*P31/(1-$D$44))) -> 2407.979 | Q37: =MAX(0,-(Q35*Q31/(1-$D$44))) -> 2493.4082
C38: Deal Fees as % of offer value | D38: 0.005 | F38: % Write-up | G38: 1.1
C39: Deal Fees | D39: =D38*D28 -> 359.11772 | F39: Asset write-up | G39: =G37*G38 -> 51754.042
C40: Assumed annual pretax cost synergies | D40: 3000 | F40: Useful life | G40: ='Target Financials'!H64/-'Target Financials'!H206 -> 10.179805 | I40: SENSITIVITY ANALYSIS
C41: Assumed annual revenue synergies | D41: 2500 | F41: Incremental amortization expense | G41: =G39/G40 -> 5083.9917
C42: Netflix FY2026 EBITDA | D42: ='Acquirer Financials'!I36 -> 35249.954 | F42: Incremental deferred tax liabilities | G42: =IF($D$6="Stock sale",G39*D44,0) -> 7333.5478 | I42: Accretion/Dilution Year 1 | K42: % Stock | L42: Offer Price
C43: Warner Bros FY2026 EBITDA | D43: ='Target Financials'!I39 -> 5658.6058 | K43: =M35 -> -0.85582162 | L43: 18 | M43: =L43+4 -> 22 | N43: =M43+4 -> 26 | O43: =N43+4 -> 30 | P43: =O43+4 -> 34 | Q43: =P43+4 -> 38
C44: Acquirer Tax Rate (2026E) | D44: ='Acquirer Financials'!I48 -> 0.1417 | F44: Purchase Price Allocation | I44: Current share price | K44: 1 | L44: -0.63896017 | M44: -0.70674582 | N44: -0.77150138 | O44: -0.83342558 | P44: -0.89270014 | Q44: -0.94949158
C45: Target Tax Rate (2026E) | D45: ='Target Financials'!I52 -> 0.23 | F45: Target assets - book value | G45: ='Target Financials'!I66 -> 100731.75 | I45: =$D$16 -> 93.38 | K45: =K44-0.2 -> 0.8 | L45: -0.65421849 | M45: -0.72679362 | N45: -0.79669573 | O45: -0.86406984 | P45: -0.92905065 | Q45: -0.99176344
F46: Plus: PP&E write ups | G46: =G32 -> 1338.2463 | I46: Current % stock | K46: =K45-0.2 -> 0.6 | L46: -0.67014763 | M46: -0.74790312 | N46: -0.82344449 | O46: -0.896865 | P46: -0.96825271 | Q46: -1.0376909
C47: Transaction Financing | F47: Plus: Intangible asset write ups | G47: =G39 -> 51754.042 | I47: =$D$31 -> 0.6 | K47: =K46-0.2 -> 0.4 | L47: -0.68679284 | M47: -0.77016097 | N47: -0.85189609 | O47: -0.93204573 | P47: -1.0106556 | Q47: -1.0877696
C48: % Cash consideration financed with debt | D48: 0.8 | F48: Less: Write off of target goodwill | G48: =-'Target Financials'!I63 -> -25933 | I48: % Cash consideration financed with debt | K48: =K47-0.2 -> 0.2 | L48: -0.70420351 | M48: -0.79366348 | N48: -0.88221848 | O48: -0.96988217 | P48: -1.056668 | Q48: -1.1425889
C49: % Cash consideration financed with excess cash | D49: =1-D48 -> 0.2 | F49: Less: Write off of target deferred tax assets | G49: -4975 | I49: =$D$48 -> 0.8 | K49: =K48-0.2 -> 0 | L49: -0.72243369 | M49: -0.81851806 | N49: -0.91460244 | O49: -1.0106868 | P49: -1.1067712 | Q49: -1.2028556
C50: Acquirer new borrowing | D50: =D48*D32*D28 -> 22983.534 | F50: Target assets - fair market value | G50: =SUM(G45:G49) -> 122916.04
C51: Acquirer excess cash used | D51: =D49*D32*D28 -> 5745.8835 | I51: Accretion/Dilution Year 1 | K51: % Stock | L51: % Cash Consideration Financed with Debt
C52: % of total acquirer cash balance | D52: =D51/'Acquirer Financials'!I55 -> 0.62399819 | F52: Target liabilities - book value | G52: ='Target Financials'!I75 -> 63271.335 | K52: =M35 -> -0.85582162 | L52: 0 | M52: =L52+0.2 -> 0.2 | N52: =M52+0.2 -> 0.4 | O52: =N52+0.2 -> 0.6 | P52: =O52+0.2 -> 0.8 | Q52: =P52+0.2 -> 1
F53: Less: Write off of target deferred tax liabilities | G53: =IF($D$6="Stock sale", 0,-'Target Financials'!I73) -> 0 | I53: Current share price | K53: 1 | L53: -0.79893052 | M53: -0.79893052 | N53: -0.79893052 | O53: -0.79893052 | P53: -0.79893052 | Q53: -0.79893052
C54: Treatment of target debt | D54: Refinanced | F54: Plus: New deferred tax liabilities created | G54: =G42+G35 -> 7523.1773 | I54: =$D$16 -> 93.38 | K54: =K53-0.2 -> 0.8 | L54: -0.79017294 | M54: -0.7992484 | N54: -0.80832387 | O54: -0.81739933 | P54: -0.8264748 | Q54: -0.83555027
C55: Debt to be refinanced | D55: =IF($D$54="Assumed",0,D59) -> 32428 | F55: Target liabilities - fair market value | G55: =SUM(G52:G54) -> 70794.513 | I55: Current % stock | K55: =K54-0.2 -> 0.6 | L55: -0.78084224 | M55: -0.79958709 | N55: -0.81833193 | O55: -0.83707678 | P55: -0.85582162 | Q55: -0.87456647
C56: Total acquisition financing | D56: =D48*D32*D28+D55 -> 55411.534 | I56: =$D$31 -> 0.6 | K56: =K55-0.2 -> 0.4 | L56: -0.77088028 | M56: -0.79994869 | N56: -0.8290171 | O56: -0.85808551 | P56: -0.88715391 | Q56: -0.91622232
F57: Target net book value - fair market value | G57: =G50-G55 -> 52121.523 | I57: % Cash consideration financed with debt | K57: =K56-0.2 -> 0.2 | L57: -0.76022074 | M57: -0.80033561 | N57: -0.84045048 | O57: -0.88056535 | P57: -0.92068022 | Q57: -0.96079509
C58: Acquirer available cash | D58: ='Acquirer Financials'!I55 -> 9208.1732 | F58: Offer value | G58: =D28 -> 71823.543 | I58: =$D$48 -> 0.8 | K58: =K57-0.2 -> 0 | L58: -0.74878769 | M58: -0.80075061 | N58: -0.85271352 | O58: -0.90467644 | P58: -0.95663936 | Q58: -1.0086023
C59: Target debt outstanding | D59: ='Target Financials'!I71+'Target Financials'!I72 -> 32428 | F59: Goodwill created in transaction | G59: =G58-G57 -> 19702.02
I60: Accretion/Dilution Year 2 | K60: % Stock | L60: Offer Price
C61: Term of loan | D61: 5 | K61: =N35 -> -0.50782407 | L61: 18 | M61: =L61+4 -> 22 | N61: =M61+4 -> 26 | O61: =N61+4 -> 30 | P61: =O61+4 -> 34 | Q61: =P61+4 -> 38
C62: Financing fees as % of acquisition financing | D62: 0.005 | I62: Current share price | K62: 1 | L62: -0.32073329 | M62: -0.39906658 | N62: -0.47390236 | O62: -0.54546973 | P62: -0.61397824 | Q62: -0.6796199
C63: Financing fees | D63: =D62*D56 -> 277.05767 | I63: =$D$16 -> 93.38 | K63: =K62-0.2 -> 0.8 | L63: -0.31749193 | M63: -0.39719742 | N63: -0.47397078 | O63: -0.54797088 | P63: -0.61934533 | Q63: -0.68823142
I64: Current % stock | K64: =K63-0.2 -> 0.6 | L64: -0.31410825 | M64: -0.39522939 | N64: -0.47404342 | O64: -0.55064738 | P64: -0.62513294 | Q64: -0.69758677
C65: Interest rate on new debt | D65: ='Acquirer Financials'!I203 -> 0.051688698 | I65: =$D$31 -> 0.6 | K65: =K64-0.2 -> 0.4 | L65: -0.31057265 | M65: -0.39315444 | N65: -0.47412068 | O65: -0.55351832 | P65: -0.63139251 | Q65: -0.70778668
C66: Interest earned on cash | D66: ='Acquirer Financials'!I206 -> 0.031642009 | I66: % Cash consideration financed with debt | K66: =K65-0.2 -> 0.2 | L66: -0.30687469 | M66: -0.39096361 | N66: -0.47420301 | O66: -0.5566057 | P66: -0.63818423 | Q66: -0.71895091
I67: =$D$48 -> 0.8 | K67: =K66-0.2 -> 0 | L67: -0.30300289 | M67: -0.38864692 | N67: -0.47429094 | O67: -0.55993496 | P67: -0.64557898 | Q67: -0.731223
I69: Accretion/Dilution Year 3 | K69: % Stock | L69: Offer Price
K70: =O35 -> -0.46916205 | L70: 18 | M70: =L70+4 -> 22 | N70: =M70+4 -> 26 | O70: =N70+4 -> 30 | P70: =O70+4 -> 34 | Q70: =P70+4 -> 38
I71: Current share price | K71: 1 | L71: -0.28957134 | M71: -0.38070668 | N71: -0.4677763 | O71: -0.55104633 | P71: -0.63076017 | Q71: -0.70714087
I72: =$D$16 -> 93.38 | K72: =K71-0.2 -> 0.8 | L72: -0.27328756 | M72: -0.36352293 | N72: -0.45044167 | O72: -0.53422333 | P72: -0.61503474 | Q72: -0.6930311
I73: Current % stock | K73: =K72-0.2 -> 0.6 | L73: -0.25628943 | M73: -0.34543111 | N73: -0.43203982 | O73: -0.51622202 | P73: -0.59807826 | Q73: -0.67770363
I74: =$D$31 -> 0.6 | K74: =K73-0.2 -> 0.4 | L74: -0.23852887 | M74: -0.32635727 | N74: -0.41246906 | O74: -0.49691408 | P74: -0.57974025 | Q74: -0.6609937
I75: % Cash consideration financed with debt | K75: =K74-0.2 -> 0.2 | L75: -0.21995343 | M75: -0.30621924 | N75: -0.39161436 | O75: -0.47615191 | P75: -0.55984473 | Q75: -0.64270544
I76: =$D$48 -> 0.8 | K76: =K75-0.2 -> 0 | L76: -0.2005057 | M76: -0.28492539 | N76: -0.36934508 | O76: -0.45376477 | P76: -0.53818446 | Q76: -0.62260415

Sheet Target Financials
C2: Warner Bros Discovery Financial Statement Model
C3: In millions, except per share data
C5: Circ Break 1 = off, 0 = on | D5: 1
C6: Latest Fiscal Year End Date | D6: ='M&A'!D21 -> 46022
C7: Shares Outstanding | D7: 2479.9295
B9: x | C9: INCOME STATEMENT
C10: Fiscal Year | D10: 2021 | E10: 2022 | F10: 2023 | G10: 2024 | H10: 2025 | I10: 2026 | J10: 2027 | K10: 2028 | L10: 2029 | M10: 2030
C11: End Date | D11: 44561 | E11: =EOMONTH(D11,12) -> 44926 | F11: =EOMONTH(E11,12) -> 45291 | G11: =EOMONTH(F11,12) -> 45657 | H11: =EOMONTH(G11,12) -> 46022 | I11: =EOMONTH(H11,12) -> 46387 | J11: =EOMONTH(I11,12) -> 46752 | K11: =EOMONTH(J11,12) -> 47118 | L11: =EOMONTH(K11,12) -> 47483 | M11: =EOMONTH(L11,12) -> 47848
C13: Revenue | D13: 12191 | E13: 33817 | F13: 41321 | G13: 39321 | H13: 37296 | I13: 37432.15 | J13: 38125.5 | K13: 38743.39 | L13: 38824.97 | M13: 39336.82
C14: Cost of revenue | D14: -4620 | E14: -20442 | F14: -24526 | G14: -22970 | H14: -20885 | I14: =I15-I13 -> -21748.079 | J14: =J15-J13 -> -21617.159 | K14: =K15-K13 -> -22664.883 | L14: =L15-L13 -> -22906.732 | M14: =M15-M13 -> -23366.071
C15: Gross profit | D15: =SUM(D13:D14) -> 7571 | E15: =SUM(E13:E14) -> 13375 | F15: =SUM(F13:F14) -> 16795 | G15: =SUM(G13:G14) -> 16351 | H15: =SUM(H13:H14) -> 16411 | I15: =I13*I45 -> 15684.071 | J15: =J13*J45 -> 16508.341 | K15: =K13*K45 -> 16078.507 | L15: =L13*L45 -> 15918.238 | M15: =M13*M45 -> 15970.749
C16: SG&A | D16: -4016 | E16: -9678 | F16: -9696 | G16: -9296 | H16: -9418 | I16: =I13*-I47 -> -9452.3806 | J16: =J13*-J47 -> -9627.4657 | K16: =K13*-K47 -> -9783.4955 | L16: =L13*-L47 -> -9804.0961 | M16: =M13*-M47 -> -9933.3486
C17: Depreciation and amortization | D17: -1582 | E17: -7193 | F17: -7985 | G17: -7037 | H17: -5684 | I17: =-I197+I206 -> -5102.8902 | J17: =-J197+J206 -> -4150.5525 | K17: =-K197+K206 -> -3474.3439 | L17: =-L197+L206 -> -3246.3361 | M17: =-M197+M206 -> -3104.7617
C18: Restructuring charges | D18: -32 | E18: -3757 | F18: -585 | G18: -447 | H18: -399 | I18: =I13*-I49 -> -400.45656 | J18: =J13*-J49 -> -407.87416 | K18: =K13*-K49 -> -414.48447 | L18: =L13*-L49 -> -415.35722 | M18: =M13*-M49 -> -420.8331
C19: Impairments and loss on dispositions | D19: 71 | E19: -117 | F19: -77 | G19: -9603 | H19: -172 | I19: =I13*-I50 -> -172.62789 | J19: =J13*-J50 -> -175.82545 | K19: =K13*-K50 -> -178.67501 | L19: =L13*-L50 -> -179.05123 | M19: =M13*-M50 -> -181.41176
C20: Total operating expenses | D20: =SUM(D16:D19) -> -5559 | E20: =SUM(E16:E19) -> -20745 | F20: =SUM(F16:F19) -> -18343 | G20: =SUM(G16:G19) -> -26383 | H20: =SUM(H16:H19) -> -15673 | I20: =SUM(I16:I19) -> -15128.355 | J20: =SUM(J16:J19) -> -14361.718 | K20: =SUM(K16:K19) -> -13850.999 | ... M20: =SUM(M16:M19) -> -13640.355
C21: Operating income (EBIT) | D21: =D15+D20 -> 2012 | E21: =E15+E20 -> -7370 | F21: =F15+F20 -> -1548 | G21: =G15+G20 -> -10032 | H21: =H15+H20 -> 738 | I21: =I15+I20 -> 555.71551 | J21: =J15+J20 -> 2146.6237 | K21: =K15+K20 -> 2227.508 | ... M21: =M15+M20 -> 2330.3937
C22: Interest expense, net | D22: -633 | E22: -1777 | F22: -2221 | G22: -2017 | H22: -2085 | I22: =-I230 -> -1968.95 | J22: =-J230 -> -1708.19 | K22: =-K230 -> -1288.9 | L22: =-L230 -> -897 | M22: =-M230 -> -736
C23: Interest income | D23: 18 | E23: 67 | F23: 179 | G23: 210 | H23: 206 | I23: =I233 -> 199.01155 | J23: =J233 -> 188.04138 | K23: =K233 -> 170.74148 | L23: =L233 -> 170.49703 | M23: =M233 -> 179.7783
C24: Other income (expense), net | D24: 36 | E24: 120 | F24: -273 | G24: 451 | H24: 2780 | I24: =AVERAGE(D24:H24) -> 622.8 | J24: =I24 -> 622.8 | K24: =J24 -> 622.8 | L24: =K24 -> 622.8 | M24: =L24 -> 622.8
C25: Total other income/expense | D25: =SUM(D22:D24) -> -579 | E25: =SUM(E22:E24) -> -1590 | F25: =SUM(F22:F24) -> -2315 | G25: =SUM(G22:G24) -> -1356 | H25: =SUM(H22:H24) -> 901 | I25: =SUM(I22:I24) -> -1147.1384 | J25: =SUM(J22:J24) -> -897.34862 | K25: =SUM(K22:K24) -> -495.35852 | ... M25: =SUM(M22:M24) -> 66.578296
C26: Income (loss) before income taxes | D26: =D21+D25 -> 1433 | E26: =E21+E25 -> -8960 | F26: =F21+F25 -> -3863 | G26: =G21+G25 -> -11388 | H26: =H21+H25 -> 1639 | I26: =I21+I25 -> -591.42294 | J26: =J21+J25 -> 1249.2751 | K26: =K21+K25 -> 1732.1495 | ... M26: =M21+M25 -> 2396.972
C27: Income tax expense | D27: -236 | E27: 1663 | F27: 784 | G27: -94 | H27: -890 | I27: =-I52*I26 -> 136.02728 | J27: =-J52*J26 -> -287.33328 | K27: =-K52*K26 -> -433.03737 | L27: =-L52*L26 -> -542.42353 | M27: =-M52*M26 -> -599.243
C28: Net income | D28: =SUM(D26:D27) -> 1197 | E28: =SUM(E26:E27) -> -7297 | F28: =SUM(F26:F27) -> -3079 | G28: =SUM(G26:G27) -> -11482 | H28: =SUM(H26:H27) -> 749 | I28: =SUM(I26:I27) -> -455.39566 | J28: =SUM(J26:J27) -> 961.94184 | K28: =SUM(K26:K27) -> 1299.1121 | ... M28: =SUM(M26:M27) -> 1797.729
C29: Net income attributable to noncontrolling interests | D29: -138 | E29: -68 | F29: -38 | G29: 129 | H29: -24 | I29: =H29 -> -24 | J29: =I29 -> -24 | K29: =J29 -> -24 | L29: =K29 -> -24 | M29: =L29 -> -24
C30: Net income attributable to redeemable noncontrolling interests | D30: -53 | E30: -6 | F30: -9 | G30: 42 | H30: 2 | I30: =H30 -> 2 | J30: =I30 -> 2 | K30: =J30 -> 2 | L30: =K30 -> 2 | M30: =L30 -> 2
C31: Net income available to Warner Bros | D31: =SUM(D28:D30) -> 1006 | E31: =SUM(E28:E30) -> -7371 | F31: =SUM(F28:F30) -> -3126 | G31: =SUM(G28:G30) -> -11311 | H31: =SUM(H28:H30) -> 727 | I31: =SUM(I28:I30) -> -477.39566 | J31: =SUM(J28:J30) -> 939.94184 | K31: =SUM(K28:K30) -> 1277.1121 | ... M31: =SUM(M28:M30) -> 1775.729
C33: Basic EPS | D33: 1.55 | E33: -3.82 | F33: -1.28 | G33: -4.62 | H33: 0.29 | I33: =I252 -> -0.1914699 | J33: =J252 -> 0.38222058 | K33: =K252 -> 0.51276279 | L33: =L252 -> 0.64524788 | M33: =M252 -> 0.7142048
C34: Diluted EPS | D34: 1.54 | E34: -3.82 | F34: -1.28 | G34: -4.62 | H34: 0.29 | I34: =I255 -> -0.18315193 | J34: =J255 -> 0.3653954 | K34: =K255 -> 0.49046415 | L34: =L255 -> 0.61715748 | M34: =M255 -> 0.68309406
C36: Basic weighted average shares outstanding | D36: 588 | E36: 1940 | F36: 2436 | G36: 2450 | H36: 2475 | I36: =I251 -> 2493.3196 | J36: =J251 -> 2459.1607 | K36: =K251 -> 2490.6489 | L36: =L251 -> 2487.8355 | M36: =M251 -> 2486.3022
C37: Diluted weighted average shares outstanding | D37: 664 | E37: 1940 | F37: 2436 | G37: 2450 | H37: 2530 | I37: =I254 -> 2606.5554 | J37: =J254 -> 2572.3965 | K37: =K254 -> 2603.8847 | L37: =L254 -> 2601.0713 | M37: =M254 -> 2599.538
C39: EBITDA | D39: =D21-D17 -> 3594 | E39: =E21-E17 -> -177 | F39: =F21-F17 -> 6437 | G39: =G21-G17 -> -2995 | H39: =H21-H17 -> 6422 | I39: =I21-I17 -> 5658.6058 | J39: =J21-J17 -> 6297.1762 | K39: =K21-K17 -> 5701.8519 | ... M39: =M21-M17 -> 5435.1554
C40: Stock-based compensation | D40: 178 | E40: 412 | F40: 500 | G40: 557 | H40: 769 | I40: =H40*(1+I44) -> 771.80725 | J40: =I40*(1+J44) -> 786.10332 | K40: =J40*(1+K44) -> 798.84349 | L40: =K40*(1+L44) -> 800.52558 | M40: =L40*(1+M44) -> 811.07933
C41: Adjusted EBITDA | D41: =SUM(D39:D40) -> 3772 | E41: =SUM(E39:E40) -> 235 | F41: =SUM(F39:F40) -> 6937 | G41: =SUM(G39:G40) -> -2438 | H41: =SUM(H39:H40) -> 7191 | I41: =SUM(I39:I40) -> 6430.413 | J41: =SUM(J39:J40) -> 7083.2796 | K41: =SUM(K39:K40) -> 6500.6954 | ... M41: =SUM(M39:M40) -> 6246.2348
C43: Growth rate and margins
C44: Revenue growth % | E44: =E13/D13-1 -> 1.7739316 | F44: =F13/E13-1 -> 0.22190023 | G44: =G13/F13-1 -> -0.048401539 | H44: =H13/G13-1 -> -0.051499199 | I44: =I13/H13-1 -> 0.0036505255 | J44: =J13/I13-1 -> 0.018522847 | K44: =K13/J13-1 -> 0.016206738 | L44: =L13/K13-1 -> 0.0021056495 | M44: =M13/L13-1 -> 0.013183526
C45: Gross margin % | D45: =D15/D13 -> 0.62103191 | E45: =E15/E13 -> 0.39551113 | F45: =F15/F13 -> 0.40645193 | G45: =G15/G13 -> 0.41583378 | H45: =H15/H13 -> 0.44002038 | I45: 0.419 | J45: 0.433 | K45: 0.415 | L45: 0.41 | M45: 0.406
C47: SG&A % of sales | D47: =-D16/D13 -> 0.32942335 | E47: =-E16/E13 -> 0.28618742 | F47: =-F16/F13 -> 0.23465066 | G47: =-G16/G13 -> 0.23641311 | H47: =-H16/H13 -> 0.25252038 | I47: =H47 -> 0.25252038 | J47: =I47 -> 0.25252038 | K47: =J47 -> 0.25252038 | L47: =K47 -> 0.25252038 | M47: =L47 -> 0.25252038
C48: D&A % of sales | D48: =-D17/D13 -> 0.12976786 | E48: =-E17/E13 -> 0.21270367 | F48: =-F17/F13 -> 0.19324315 | G48: =-G17/G13 -> 0.1789629 | H48: =-H17/H13 -> 0.1524024 | I48: =H48 -> 0.1524024 | J48: =-J17/J13 -> 0.10886552 | K48: =-K17/K13 -> 0.089675785 | L48: =-L17/L13 -> 0.083614644 | M48: =-M17/M13 -> 0.078927623
C49: Restructuring charges % of sales | D49: =-D18/D13 -> 0.0026248872 | E49: =-E18/E13 -> 0.11109797 | F49: =-F18/F13 -> 0.01415745 | G49: =-G18/G13 -> 0.011367971 | H49: =-H18/H13 -> 0.010698198 | I49: =H49 -> 0.010698198 | J49: =I49 -> 0.010698198 | K49: =J49 -> 0.010698198 | L49: =K49 -> 0.010698198 | M49: =L49 -> 0.010698198
C50: Impairments and loss on dispositions % of sales | D50: =-D19/D13 -> -0.0058239685 | E50: =-E19/E13 -> 0.0034597983 | F50: =-F19/F13 -> 0.0018634593 | G50: =-G19/G13 -> 0.24422065 | H50: =-H19/H13 -> 0.0046117546 | I50: =H50 -> 0.0046117546 | J50: =I50 -> 0.0046117546 | K50: =J50 -> 0.0046117546 | L50: =K50 -> 0.0046117546 | M50: =L50 -> 0.0046117546
C52: Effective tax rate | D52: =-D27/D26 -> 0.16468946 | E52: =-E27/E26 -> 0.18560268 | F52: =-F27/F26 -> 0.20295107 | G52: =-G27/G26 -> -0.0082543028 | H52: =-H27/H26 -> 0.54301403 | I52: 0.23 | J52: 0.23 | K52: 0.25 | L52: 0.25 | M52: 0.25
B55: x | C55: BALANCE SHEET
C56: Fiscal Year | D56: 2021 | E56: 2022 | F56: 2023 | G56: 2024 | H56: 2025 | I56: 2026 | J56: 2027 | K56: 2028 | L56: 2029 | M56: 2030
C57: End Date | D57: 44561 | E57: =EOMONTH(D57,12) -> 44926 | F57: =EOMONTH(E57,12) -> 45291 | G57: =EOMONTH(F57,12) -> 45657 | H57: =EOMONTH(G57,12) -> 46022 | I57: =EOMONTH(H57,12) -> 46387 | J57: =EOMONTH(I57,12) -> 46752 | K57: =EOMONTH(J57,12) -> 47118 | L57: =EOMONTH(K57,12) -> 47483 | M57: =EOMONTH(L57,12) -> 47848
C59: Cash and cash equivalents | D59: 3905 | E59: 3731 | F59: 3780 | G59: 5312 | H59: 4566 | I59: =I116 -> 4976.8937 | J59: =J116 -> 4039.9644 | K59: =K116 -> 4147.3383 | L59: =L116 -> 4028.2425 | M59: =M116 -> 4592.3886
C60: Account receivables, net | D60: 2446 | E60: 6380 | F60: 6047 | G60: 4947 | H60: 5294 | I60: =I126 -> 5313.3259 | J60: =J126 -> 5411.7438 | K60: =K126 -> 5499.4505 | L60: =L126 -> 5511.0304 | M60: =M126 -> 5583.6852
C61: Prepaid expenses and other current assets | D61: 913 | E61: 3888 | F61: 4391 | G61: 3819 | H61: 3346 | I61: =I136 -> 3358.2147 | J61: =J136 -> 3420.4184 | K61: =K136 -> 3475.8522 | L61: =L136 -> 3483.1711 | M61: =M136 -> 3529.0916
C62: Property and equipment, net | D62: 1336 | E62: 5301 | F62: 5957 | G62: 6087 | H62: 6685 | I62: =I181 -> 6691.2317 | J62: =J181 -> 6880.9773 | K62: =K181 -> 7155.7147 | L62: =L181 -> 7422.1282 | M62: =M181 -> 7645.1312
C63: Goodwill | D63: 12912 | E63: 34438 | F63: 34969 | G63: 25667 | H63: 25933 | I63: =H63 -> 25933 | J63: =I63 -> 25933 | K63: =J63 -> 25933 | L63: =K63 -> 25933 | M63: =L63 -> 25933
C64: Intangible assets, net | D64: 10149 | E64: 71634 | F64: 59514 | G64: 51401 | H64: 46878 | I64: =I207 -> 47049.129 | J64: =J207 -> 47920.613 | K64: =K207 -> 48697.25 | L64: =L207 -> 48799.789 | M64: =M207 -> 49443.143
C65: Other assets | D65: 2766 | E65: 8629 | F65: 8099 | G65: 7327 | H65: 7383 | I65: =H65*(1+I44) -> 7409.9518 | J65: =I65*(1+J44) -> 7547.2052 | K65: =J65*(1+K44) -> 7669.5208 | L65: =K65*(1+L44) -> 7685.6701 | M65: =L65*(1+M44) -> 7786.9944
C66: Total Assets | D66: =SUM(D59:D65) -> 34427 | E66: =SUM(E59:E65) -> 134001 | F66: =SUM(F59:F65) -> 122757 | G66: =SUM(G59:G65) -> 104560 | H66: =SUM(H59:H65) -> 100085 | I66: =SUM(I59:I65) -> 100731.75 | J66: =SUM(J59:J65) -> 101153.92 | K66: =SUM(K59:K65) -> 102578.13 | ... M66: =SUM(M59:M65) -> 104513.43
C68: Accounts payable | D68: 412 | E68: 1454 | F68: 1260 | G68: 1055 | H68: 1093 | I68: =I146 -> 1138.1686 | J68: =J146 -> 1131.3169 | K68: =K146 -> 1186.1488 | L68: =L146 -> 1198.8058 | M68: =M146 -> 1222.8449
C69: Accrued liabilities | D69: 2230 | E69: 11504 | F69: 10368 | G69: 10438 | H69: 9626 | I69: =I156 -> 10023.797 | J69: =J156 -> 9963.4555 | K69: =K156 -> 10446.357 | L69: =L156 -> 10557.826 | M69: =M156 -> 10769.538
C70: Deferred revenue | D70: 478 | E70: 1694 | F70: 1924 | G70: 1569 | H70: 1642 | I70: =I166 -> 1647.9942 | J70: =J166 -> 1678.5197 | K70: =K166 -> 1705.723 | L70: =L166 -> 1709.3147 | M70: =M166 -> 1731.8495
C71: Current portion of debt | D71: 339 | E71: 365 | F71: 1780 | G71: 2748 | H71: 139 | I71: =I223 -> 16483 | J71: =J223 -> 1409 | K71: =K223 -> 2274 | L71: =L223 -> 1354 | M71: =M223 -> 0
C72: Long-term debt | D72: 14420 | E72: 48634 | F72: 41889 | G72: 36757 | H72: 32428 | I72: =I229 -> 15945 | J72: =J229 -> 29536 | K72: =K229 -> 27262 | L72: =L229 -> 25908 | M72: =M229 -> 25908
C73: Deferred income taxes | D73: 1225 | E73: 11014 | F73: 8736 | G73: 6985 | H73: 6383 | I73: =H73 -> 6383 | J73: =I73 -> 6383 | K73: =J73 -> 6383 | L73: =K73 -> 6383 | M73: =L73 -> 6383
C74: Other liabilities | D74: 1927 | E74: 10669 | F74: 10328 | G74: 10070 | H74: 11608 | I74: =H74*(1+I44) -> 11650.375 | J74: =I74*(1+J44) -> 11866.173 | K74: =J74*(1+K44) -> 12058.485 | L74: =K74*(1+L44) -> 12083.876 | M74: =L74*(1+M44) -> 12243.184
C75: Total Liabilities | D75: =SUM(D68:D74) -> 21031 | E75: =SUM(E68:E74) -> 85334 | F75: =SUM(F68:F74) -> 76285 | G75: =SUM(G68:G74) -> 69622 | H75: =SUM(H68:H74) -> 62919 | I75: =SUM(I68:I74) -> 63271.335 | J75: =SUM(J68:J74) -> 61967.466 | K75: =SUM(K68:K74) -> 61315.714 | ... M75: =SUM(M68:M74) -> 58258.417
C77: Redeemable noncontrolling interests | D77: 363 | E77: 318 | F77: 165 | G77: 109 | H77: 19 | I77: =H77 -> 19 | J77: =I77 -> 19 | K77: =J77 -> 19 | L77: =K77 -> 19 | M77: =L77 -> 19
C79: Common stock | D79: 11093 | E79: 54657 | F79: 55139 | G79: 55587 | H79: 56082 | I79: =H79+I40 -> 56853.807 | J79: =I79+J40 -> 57639.911 | K79: =J79+K40 -> 58438.754 | L79: =K79+L40 -> 59239.28 | M79: =L79+M40 -> 60050.359
C80: Treasury stock | D80: -8244 | E80: -8244 | F80: -8244 | G80: -8244 | H80: -8244 | I80: =H80 -> -8244 | J80: =I80 -> -8244 | K80: =J80 -> -8244 | L80: =K80 -> -8244 | M80: =L80 -> -8244
C81: Retained earnings | D81: 9580 | E81: 2205 | F81: -928 | G81: -12239 | H81: -11512 | I81: =I243 -> -11989.396 | J81: =J243 -> -11049.454 | K81: =K243 -> -9772.3417 | L81: =L243 -> -8167.0711 | M81: =M243 -> -6391.3421
C82: Accumulated other comprehensive loss | D82: -830 | E82: -1523 | F82: -741 | G82: -1067 | H82: -407 | I82: =H82 -> -407 | J82: =I82 -> -407 | K82: =J82 -> -407 | L82: =K82 -> -407 | M82: =L82 -> -407
C83: Total Warner Bros equity | D83: =SUM(D79:D82) -> 11599 | E83: =SUM(E79:E82) -> 47095 | F83: =SUM(F79:F82) -> 45226 | G83: =SUM(G79:G82) -> 34037 | H83: =SUM(H79:H82) -> 35919 | I83: =SUM(I79:I82) -> 36213.412 | J83: =SUM(J79:J82) -> 37939.457 | K83: =SUM(K79:K82) -> 40015.412 | ... M83: =SUM(M79:M82) -> 45008.017
C84: Noncontrolling interests | D84: 1434 | E84: 1254 | F84: 1081 | G84: 792 | H84: 1228 | I84: =H84 -> 1228 | J84: =I84 -> 1228 | K84: =J84 -> 1228 | L84: =K84 -> 1228 | M84: =L84 -> 1228
C85: Total Equity | D85: =SUM(D83:D84) -> 13033 | E85: =SUM(E83:E84) -> 48349 | F85: =SUM(F83:F84) -> 46307 | G85: =SUM(G83:G84) -> 34829 | H85: =SUM(H83:H84) -> 37147 | I85: =SUM(I83:I84) -> 37441.412 | J85: =SUM(J83:J84) -> 39167.457 | K85: =SUM(K83:K84) -> 41243.412 | ... M85: =SUM(M83:M84) -> 46236.017
C87: Balance check | D87: =D66-D75-D77-D85 -> 0 | E87: =E66-E75-E77-E85 -> 0 | F87: =F66-F75-F77-F85 -> 0 | G87: =G66-G75-G77-G85 -> 0 | H87: =H66-H75-H77-H85 -> 0 | I87: =I66-I75-I77-I85 -> 0 | J87: =J66-J75-J77-J85 -> 0 | K87: =K66-K75-K77-K85 -> 0 | ... M87: =M66-M75-M77-M85 -> 0
B90: x | C90: CASH FLOW STATEMENT
C91: Fiscal Year | D91: 2021 | E91: 2022 | F91: 2023 | G91: 2024 | H91: 2025 | I91: 2026 | J91: 2027 | K91: 2028 | L91: 2029 | M91: 2030
C92: End Date | D92: 44561 | E92: =EOMONTH(D92,12) -> 44926 | F92: =EOMONTH(E92,12) -> 45291 | G92: =EOMONTH(F92,12) -> 45657 | H92: =EOMONTH(G92,12) -> 46022 | I92: =EOMONTH(H92,12) -> 46387 | J92: =EOMONTH(I92,12) -> 46752 | K92: =EOMONTH(J92,12) -> 47118 | L92: =EOMONTH(K92,12) -> 47483 | M92: =EOMONTH(L92,12) -> 47848
C94: Net income | I94: =I31 -> -477.39566 | J94: =J31 -> 939.94184 | K94: =K31 -> 1277.1121 | L94: =L31 -> 1605.2706 | M94: =M31 -> 1775.729
C95: Depreciation and amortization | I95: =-I17 -> 5102.8902 | J95: =-J17 -> 4150.5525 | K95: =-K17 -> 3474.3439 | L95: =-L17 -> 3246.3361 | M95: =-M17 -> 3104.7617
C96: Stock-based compensation expense | I96: =I40 -> 771.80725 | J96: =J40 -> 786.10332 | K96: =K40 -> 798.84349 | L96: =L40 -> 800.52558 | M96: =M40 -> 811.07933
C97: Changes in accounts receivable | I97: =H60-I60 -> -19.325882 | J97: =I60-J60 -> -98.417924 | K97: =J60-K60 -> -87.706715 | L97: =K60-L60 -> -11.579915 | M97: =L60-M60 -> -72.654813
C98: Changes in prepaid expenses and other current assets | I98: =H61-I61 -> -12.214658 | J98: =I61-J61 -> -62.203697 | K98: =J61-K61 -> -55.433825 | L98: =K61-L61 -> -7.3189264 | M98: =L61-M61 -> -45.920477
C99: Changes in accounts payable | I99: =I68-H68 -> 45.168566 | J99: =J68-I68 -> -6.8516289 | K99: =K68-J68 -> 54.831843 | L99: =L68-K68 -> 12.656984 | M99: =M68-L68 -> 24.039133
C100: Changes in accrued liabilities | I100: =I69-H69 -> 397.79746 | J100: =J69-I69 -> -60.341976 | K100: =K69-J69 -> 482.90148 | L100: =L69-K69 -> 111.46947 | M100: =M69-L69 -> 211.71152
C101: Changes in deferred revenue | I101: =I70-H70 -> 5.9941629 | J101: =J70-I70 -> 30.525544 | K101: =K70-J70 -> 27.20333 | L101: =L70-K70 -> 3.5916549 | M101: =M70-L70 -> 22.534795
C102: Changes in other assets | I102: =H65-I65 -> -26.95183 | J102: =I65-J65 -> -137.25341 | K102: =J65-K65 -> -122.31558 | L102: =K65-L65 -> -16.149323 | M102: =L65-M65 -> -101.32423
C103: Changes in other liabilities | I103: =I74-H74 -> 42.3753 | J103: =J74-I74 -> 215.79812 | K103: =K74-J74 -> 192.31197 | L103: =L74-K74 -> 25.390944 | M103: =M74-L74 -> 159.3081
C104: Cash flows from operating activities | I104: =SUM(I94:I103) -> 5830.1449 | J104: =SUM(J94:J103) -> 5757.8527 | K104: =SUM(K94:K103) -> 6042.092 | L104: =SUM(L94:L103) -> 5770.1931 | M104: =SUM(M94:M103) -> 5889.2641
C106: Capital expenditures | I106: =-I179 -> -1683.1219 | J106: =-J179 -> -1714.2981 | K106: =-K179 -> -1742.0813 | L106: =-L179 -> -1745.7495 | M106: =-M179 -> -1768.7647
C107: Purchases of intangible assets | I107: =-I205 -> -3597.1293 | J107: =-J205 -> -3497.4838 | K107: =-K205 -> -2783.6368 | L107: =-L205 -> -1869.5393 | M107: =-M205 -> -2202.3533
C108: Cash flows from investing activities | I108: =SUM(I106:I107) -> -5280.2513 | J108: =SUM(J106:J107) -> -5211.782 | K108: =SUM(K106:K107) -> -4525.7182 | L108: =SUM(L106:L107) -> -3615.2889 | M108: =SUM(M106:M107) -> -3971.118
C110: Debt repayments | I110: =-I220 -> -139 | J110: =-J220 -> -16483 | K110: =-K220 -> -1409 | L110: =-L220 -> -2274 | M110: =-M220 -> -1354
C111: Debt borrowing | I111: =I228 -> 0 | J111: =J228 -> 15000 | K111: =K228 -> 0 | L111: =L228 -> 0 | M111: =M228 -> 0
C112: Cash flows from financing activities | I112: =SUM(I110:I111) -> -139 | J112: =SUM(J110:J111) -> -1483 | K112: =SUM(K110:K111) -> -1409 | L112: =SUM(L110:L111) -> -2274 | M112: =SUM(M110:M111) -> -1354
C114: Net change in cash | I114: =I104+I108+I112 -> 410.89368 | J114: =J104+J108+J112 -> -936.92928 | K114: =K104+K108+K112 -> 107.37386 | L114: =L104+L108+L112 -> -119.09575 | M114: =M104+M108+M112 -> 564.14611
C115: Beginning cash balance | I115: =H59 -> 4566 | J115: =I59 -> 4976.8937 | K115: =J59 -> 4039.9644 | L115: =K59 -> 4147.3383 | M115: =L59 -> 4028.2425
C116: Ending cash balance | I116: =SUM(I114:I115) -> 4976.8937 | J116: =SUM(J114:J115) -> 4039.9644 | K116: =SUM(K114:K115) -> 4147.3383 | L116: =SUM(L114:L115) -> 4028.2425 | M116: =SUM(M114:M115) -> 4592.3886
B119: x | C119: Working Capital
C120: Fiscal Year | D120: 2021 | E120: 2022 | F120: 2023 | G120: 2024 | H120: 2025 | I120: 2026 | J120: 2027 | K120: 2028 | L120: 2029 | M120: 2030
C121: End Date | D121: 44561 | E121: =EOMONTH(D121,12) -> 44926 | F121: =EOMONTH(E121,12) -> 45291 | G121: =EOMONTH(F121,12) -> 45657 | H121: =EOMONTH(G121,12) -> 46022 | I121: =EOMONTH(H121,12) -> 46387 | J121: =EOMONTH(I121,12) -> 46752 | K121: =EOMONTH(J121,12) -> 47118 | L121: =EOMONTH(K121,12) -> 47483 | M121: =EOMONTH(L121,12) -> 47848
C123: Accounts receivable, net
C124: Beginning of period | E124: =D126 -> 2446 | F124: =E126 -> 6380 | G124: =F126 -> 6047 | H124: =G126 -> 4947 | I124: =H126 -> 5294 | J124: =I126 -> 5313.3259 | K124: =J126 -> 5411.7438 | L124: =K126 -> 5499.4505 | M124: =L126 -> 5511.0304
C125: Increase/Decrease | E125: =E126-E124 -> 3934 | F125: =F126-F124 -> -333 | G125: =G126-G124 -> -1100 | H125: =H126-H124 -> 347 | I125: =I126-I124 -> 19.325882 | J125: =J126-J124 -> 98.417924 | K125: =K126-K124 -> 87.706715 | L125: =L126-L124 -> 11.579915 | M125: =M126-M124 -> 72.654813
C126: End of period | D126: =D60 -> 2446 | E126: =E60 -> 6380 | F126: =F60 -> 6047 | G126: =G60 -> 4947 | H126: =H60 -> 5294 | I126: =IF($D$128=1,H126*(1+I130),2*I13*I131/365-I124) -> 5313.3259 | J126: =IF($D$128=1,I126*(1+J130),2*J13*J131/365-J124) -> 5411.7438 | K126: =IF($D$128=1,J126*(1+K130),2*K13*K131/365-K124) -> 5499.4505 | L126: =IF($D$128=1,K126*(1+L130),2*L13*L131/365-L124) -> 5511.0304 | M126: =IF($D$128=1,L126*(1+M130),2*M13*M131/365-M124) -> 5583.6852
...

Sheet Acquirer Financials
C2: Netflix Financial Statement Model
C3: In millions, except per share data
C5: Circ Break 1 = off, 0 = on | D5: 1
C6: Latest Fiscal Year End Date | D6: ='M&A'!D13 -> 46022
C7: Shares Outstanding | D7: 4222.1622
B9: x | C9: INCOME STATEMENT
C10: Fiscal Year | D10: 2021 | E10: 2022 | F10: 2023 | G10: 2024 | H10: 2025 | I10: 2026 | J10: 2027 | K10: 2028 | L10: 2029 | M10: 2030
C11: End Date | D11: 44561 | E11: =EOMONTH(D11,12) -> 44926 | F11: =EOMONTH(E11,12) -> 45291 | G11: =EOMONTH(F11,12) -> 45657 | H11: =EOMONTH(G11,12) -> 46022 | I11: =EOMONTH(H11,12) -> 46387 | J11: =EOMONTH(I11,12) -> 46752 | K11: =EOMONTH(J11,12) -> 47118 | L11: =EOMONTH(K11,12) -> 47483 | M11: =EOMONTH(L11,12) -> 47848
C13: Revenue | D13: 29697.844 | E13: 31615.55 | F13: 33723.297 | G13: 39000.966 | H13: 45183.036 | I13: 51365.94 | J13: 57402.33 | K13: 63205.96 | L13: 69022.09 | M13: 74516.56
C14: Cost of revenue | D14: -17332.683 | E14: -19168.285 | F14: -19715.368 | G14: -21038.464 | H14: -23275.329 | I14: =I15-I13 -> -25421.004 | J14: =J15-J13 -> -27650.702 | K14: =K15-K13 -> -29580.389 | L14: =L15-L13 -> -31694.944 | M14: =M15-M13 -> -33249.289
C15: Gross profit | D15: =SUM(D13:D14) -> 12365.161 | E15: =SUM(E13:E14) -> 12447.265 | F15: =SUM(F13:F14) -> 14007.929 | G15: =SUM(G13:G14) -> 17962.502 | H15: =SUM(H13:H14) -> 21907.707 | I15: =I13*I42 -> 25944.936 | J15: =J13*J42 -> 29751.628 | K15: =K13*K42 -> 33625.571 | L15: =L13*L42 -> 37327.146 | M15: =M13*M42 -> 41267.271
C16: Sales and marketing | D16: -2545.146 | E16: -2530.502 | F16: -2657.883 | G16: -2917.554 | H16: -3301.306 | I16: =I$13*-I44 -> -3753.0609 | J16: =J$13*-J44 -> -4194.1107 | K16: =K$13*-K44 -> -4618.1539 | L16: =L$13*-L44 -> -5043.1104 | M16: =M$13*-M44 -> -5444.5648
C17: Tech and development | D17: -2273.885 | E17: -2711.041 | F17: -2675.758 | G17: -2925.295 | H17: -3391.39 | I17: =I$13*-I45 -> -3855.4721 | J17: =J$13*-J45 -> -4308.557 | K17: =K$13*-K45 -> -4744.1713 | L17: =L$13*-L45 -> -5180.7237 | M17: =M$13*-M45 -> -5593.1327
C18: General and administrative | D18: -1351.621 | E18: -1572.891 | F18: -1720.285 | G18: -1702.039 | H18: -1888.408 | I18: =I$13*-I46 -> -2146.8201 | J18: =J$13*-J46 -> -2399.1088 | K18: =K$13*-K46 -> -2641.6693 | L18: =L$13*-L46 -> -2884.7523 | M18: =M$13*-M46 -> -3114.3916
C19: Total operating expenses | D19: =SUM(D16:D18) -> -6170.652 | E19: =SUM(E16:E18) -> -6814.434 | F19: =SUM(F16:F18) -> -7053.926 | G19: =SUM(G16:G18) -> -7544.888 | H19: =SUM(H16:H18) -> -8581.104 | I19: =SUM(I16:I18) -> -9755.3532 | J19: =SUM(J16:J18) -> -10901.777 | K19: =SUM(K16:K18) -> -12003.995 | ... M19: =SUM(M16:M18) -> -14152.089
C20: Operating income (EBIT) | D20: =D15+D19 -> 6194.509 | E20: =E15+E19 -> 5632.831 | F20: =F15+F19 -> 6954.003 | G20: =G15+G19 -> 10417.614 | H20: =H15+H19 -> 13326.603 | I20: =I15+I19 -> 16189.583 | J20: =J15+J19 -> 18849.851 | K20: =K15+K19 -> 21621.576 | ... M20: =M15+M19 -> 27115.182
C21: Interest expense | D21: -765.62 | E21: -706.212 | F21: -699.826 | G21: -718.733 | H21: -776.51 | I21: =-I202 -> -747.56516 | J21: =-J202 -> -747.56516 | K21: =-K202 -> -747.56516 | L21: =-L202 -> -747.56516 | M21: =-M202 -> -747.56516
C22: Interest income | D22: 8.214 | E22: 60 | F22: 281 | G22: 294 | H22: 295 | I22: =I205 -> 289.05817 | J22: =J205 -> 332.47006 | K22: =K205 -> 452.78896 | L22: =L205 -> 646.31826 | M22: =M205 -> 917.18147
C23: Other income (expense), net | D23: 403 | E23: 277.31 | F23: -329.772 | G23: -27.224 | H23: -122.541 | I23: =AVERAGE(D23:H23) -> 40.1546 | J23: =I23 -> 40.1546 | K23: =J23 -> 40.1546 | L23: =K23 -> 40.1546 | M23: =L23 -> 40.1546
C24: Total other income/expense | D24: =SUM(D21:D23) -> -354.406 | E24: =SUM(E21:E23) -> -368.902 | F24: =SUM(F21:F23) -> -748.598 | G24: =SUM(G21:G23) -> -451.957 | H24: =SUM(H21:H23) -> -604.051 | I24: =SUM(I21:I23) -> -418.35238 | J24: =SUM(J21:J23) -> -374.9405 | K24: =SUM(K21:K23) -> -254.62159 | ... M24: =SUM(M21:M23) -> 209.77091
C25: Income (loss) before income taxes | D25: =D20+D24 -> 5840.103 | E25: =E20+E24 -> 5263.929 | F25: =F20+F24 -> 6205.405 | G25: =G20+G24 -> 9965.657 | H25: =H20+H24 -> 12722.552 | I25: =I20+I24 -> 15771.231 | J25: =J20+J24 -> 18474.911 | K25: =K20+K24 -> 21366.955 | ... M25: =M20+M24 -> 27324.953
C26: Income tax expense | D26: -723.875 | E26: -772.005 | F26: -797.415 | G26: -1254.026 | H26: -1741.351 | I26: =-I48*I25 -> -2234.7834 | J26: =-J48*J25 -> -2593.8774 | K26: =-K48*K25 -> -3205.0432 | L26: =-L48*L25 -> -3824.1271 | M26: =-M48*M25 -> -4508.6172
C27: Net income | D27: =SUM(D25:D26) -> 5116.228 | E27: =SUM(E25:E26) -> 4491.924 | F27: =SUM(F25:F26) -> 5407.99 | G27: =SUM(G25:G26) -> 8711.631 | H27: =SUM(H25:H26) -> 10981.201 | I27: =SUM(I25:I26) -> 13536.447 | J27: =SUM(J25:J26) -> 15881.033 | K27: =SUM(K25:K26) -> 18161.911 | ... M27: =SUM(M25:M26) -> 22816.336
C29: Basic EPS | D29: 11.55 | E29: 10.1 | F29: 1.22 | G29: 2.03 | H29: 2.58 | I29: =I224 -> 3.2349104 | J29: =J224 -> 3.7900125 | K29: =K224 -> 4.3300432 | L29: =L224 -> 4.8441586 | M29: =M224 -> 5.4320779
C30: Diluted EPS | D30: 11.24 | E30: 9.95 | F30: 1.2 | G30: 1.98 | H30: 2.53 | I30: =I227 -> 3.1926939 | J30: =J227 -> 3.7406187 | K30: =K227 -> 4.2736667 | L30: =L227 -> 4.7811343 | M30: =M227 -> 5.3614511
C32: Basic weighted average shares outstanding | D32: 443.155 | E32: 444.698 | F32: 4415.712 | G32: 4295.191 | H32: 4249.512 | I32: =I223 -> 4184.4891 | J32: =J223 -> 4190.2324 | K32: =K223 -> 4194.395 | L32: =L223 -> 4197.4968 | M32: =M223 -> 4200.2961
C33: Diluted weighted average shares outstanding | D33: 455.372 | E33: 451.29 | F33: 4494.966 | G33: 4392.608 | H33: 4343.863 | I33: =I226 -> 4239.8199 | J33: =J226 -> 4245.5633 | K33: =K226 -> 4249.7258 | L33: =L226 -> 4252.8277 | M33: =M226 -> 4255.6269
C35: Depreciation and amortization | D35: =-D151-D178 -> 12438.779 | E35: =-E151-E178 -> 14362.814 | F35: =-F151-F178 -> 14554.384 | G35: =-G151-G178 -> 15630.431 | H35: =-H151-H178 -> 16755.555 | I35: =-I151-I178 -> 19060.371 | J35: =-J151-J178 -> 21279.236 | K35: =-K151-K178 -> 23434.853 | ... M35: =-M151-M178 -> 27692.369
C36: EBITDA | D36: =D20+D35 -> 18633.288 | E36: =E20+E35 -> 19995.645 | F36: =F20+F35 -> 21508.387 | G36: =G20+G35 -> 26048.045 | H36: =H20+H35 -> 30082.158 | I36: =I20+I35 -> 35249.954 | J36: =J20+J35 -> 40129.087 | K36: =K20+K35 -> 45056.429 | ... M36: =M20+M35 -> 54807.551
C37: Stock-based compensation | D37: 403.22 | E37: 575.452 | F37: 339.368 | G37: 272.588 | H37: 368.449 | I37: =H37*(1+I41) -> 418.86803 | J37: =I37*(1+J41) -> 468.0923 | K37: =J37*(1+K41) -> 515.4185 | L37: =K37*(1+L41) -> 562.84664 | M37: =L37*(1+M41) -> 607.65177
C38: Adjusted EBITDA | D38: =SUM(D36:D37) -> 19036.508 | E38: =SUM(E36:E37) -> 20571.097 | F38: =SUM(F36:F37) -> 21847.755 | G38: =SUM(G36:G37) -> 26320.633 | H38: =SUM(H36:H37) -> 30450.607 | I38: =SUM(I36:I37) -> 35668.822 | J38: =SUM(J36:J37) -> 40597.18 | K38: =SUM(K36:K37) -> 45571.847 | ... M38: =SUM(M36:M37) -> 55415.203
C40: Growth rate and margins
C41: Revenue growth % | E41: =E13/D13-1 -> 0.064573913 | F41: =F13/E13-1 -> 0.066668048 | G41: =G13/F13-1 -> 0.1564992 | H41: =H13/G13-1 -> 0.15851069 | I41: =I13/H13-1 -> 0.13684127 | J41: =J13/I13-1 -> 0.11751737 | K41: =K13/J13-1 -> 0.10110443 | L41: =L13/K13-1 -> 0.092018696 | M41: =M13/L13-1 -> 0.079604515
C42: Gross margin % | D42: =D15/D13 -> 0.41636561 | E42: =E15/E13 -> 0.39370705 | F42: =F15/F13 -> 0.4153784 | G42: =G15/G13 -> 0.46056557 | H42: =H15/H13 -> 0.48486576 | I42: 0.5051 | J42: 0.5183 | K42: 0.532 | L42: 0.5408 | M42: 0.5538
C44: Sales and marketing % of sales | D44: =-D16/D13 -> 0.085701373 | E44: =-E16/E13 -> 0.080039791 | F44: =-F16/F13 -> 0.078814447 | G44: =-G16/G13 -> 0.074807224 | H44: =-H16/H13 -> 0.073065165 | I44: =H44 -> 0.073065165 | J44: =I44 -> 0.073065165 | K44: =J44 -> 0.073065165 | L44: =K44 -> 0.073065165 | M44: =L44 -> 0.073065165
C45: Tech and development % of sales | D45: =-D17/D13 -> 0.076567343 | E45: =-E17/E13 -> 0.08575024 | F45: =-F17/F13 -> 0.079344496 | G45: =-G17/G13 -> 0.075005706 | H45: =-H17/H13 -> 0.075058923 | I45: =H45 -> 0.075058923 | J45: =I45 -> 0.075058923 | K45: =J45 -> 0.075058923 | L45: =K45 -> 0.075058923 | M45: =L45 -> 0.075058923
C46: General and administrative % of sales | D46: =-D18/D13 -> 0.045512428 | E46: =-E18/E13 -> 0.04975055 | F46: =-F18/F13 -> 0.051011768 | G46: =-G18/G13 -> 0.043640945 | H46: =-H18/H13 -> 0.041794624 | I46: =H46 -> 0.041794624 | J46: =I46 -> 0.041794624 | K46: =J46 -> 0.041794624 | L46: =K46 -> 0.041794624 | M46: =L46 -> 0.041794624
C48: Effective tax rate | D48: =-D26/D25 -> 0.12394901 | E48: =-E26/E25 -> 0.14665946 | F48: =-F26/F25 -> 0.1285033 | G48: =-G26/G25 -> 0.12583475 | H48: =-H26/H25 -> 0.1368712 | I48: 0.1417 | J48: 0.1404 | K48: 0.15 | L48: 0.1583 | M48: 0.165
B51: x | C51: BALANCE SHEET
C52: Fiscal Year | D52: 2021 | E52: 2022 | F52: 2023 | G52: 2024 | H52: 2025 | I52: 2026 | J52: 2027 | K52: 2028 | L52: 2029 | M52: 2030
C53: End Date | D53: 44561 | E53: =EOMONTH(D53,12) -> 44926 | F53: =EOMONTH(E53,12) -> 45291 | G53: =EOMONTH(F53,12) -> 45657 | H53: =EOMONTH(G53,12) -> 46022 | I53: =EOMONTH(H53,12) -> 46387 | J53: =EOMONTH(I53,12) -> 46752 | K53: =EOMONTH(J53,12) -> 47118 | L53: =EOMONTH(K53,12) -> 47483 | M53: =EOMONTH(L53,12) -> 47848
C55: Cash and cash equivalents, and short-term investments | D55: 6027.804 | E55: 6058.452 | F55: 7137.886 | G55: 9583.739 | H55: 9062.359 | I55: =I107 -> 9208.1732 | J55: =J107 -> 11806.299 | K55: =K107 -> 16813.184 | L55: =L107 -> 24038.727 | M55: =M107 -> 33933.665
C56: Other current assets | D56: 2042.021 | E56: 3208.021 | F56: 2780.247 | G56: 3516.64 | H56: 3957.832 | I56: =H56*(1+I41) -> 4499.4268 | J56: =I56*(1+J41) -> 5028.1875 | K56: =J56*(1+K41) -> 5536.5596 | L56: =K56*(1+L41) -> 6046.0266 | M56: =L56*(1+M41) -> 6527.3176
C57: Content assets, net | D57: 30919.539 | E57: 32736.713 | F57: 31658.056 | G57: 32452.462 | H57: 32778.392 | I57: =I179 -> 37263.829 | J57: =J179 -> 41642.976 | K57: =K179 -> 45853.265 | L57: =L179 -> 50072.623 | M57: =M179 -> 54058.63
C58: Property and equipment, net | D58: 1323.453 | E58: 1398.257 | F58: 1491.444 | G58: 1593.756 | H58: 2004.35 | I58: =I152 -> 2395.772 | J58: =J152 -> 2854.2521 | K58: =K152 -> 3354.8954 | L58: =L152 -> 3879.0259 | M58: =M152 -> 4405.369
C59: Other assets | D59: 4271.846 | E59: 5193.325 | F59: 5664.359 | G59: 6483.777 | H59: 7794.06 | I59: =H59*(1+I41) -> 8860.6091 | J59: =I59*(1+J41) -> 9901.8845 | K59: =J59*(1+K41) -> 10903.009 | L59: =K59*(1+L41) -> 11906.29 | M59: =L59*(1+M41) -> 12854.084
C60: Total Assets | D60: =SUM(D55:D59) -> 44584.663 | E60: =SUM(E55:E59) -> 48594.768 | F60: =SUM(F55:F59) -> 48731.992 | G60: =SUM(G55:G59) -> 53630.374 | H60: =SUM(H55:H59) -> 55596.993 | I60: =SUM(I55:I59) -> 62227.81 | J60: =SUM(J55:J59) -> 71233.599 | K60: =SUM(K55:K59) -> 82460.913 | ... M60: =SUM(M55:M59) -> 111779.07
C62: Accounts payable | D62: 837.483 | E62: 671.513 | F62: 747.412 | G62: 899.909 | H62: 900.162 | I62: =I117 -> 983.14492 | J62: =J117 -> 1069.3774 | K62: =K117 -> 1144.0071 | L62: =L117 -> 1225.7865 | M62: =M117 -> 1285.9
C63: Accrued expenses and other liabilities | D63: 1449.351 | E63: 1514.65 | F63: 1803.96 | G63: 2156.544 | H63: 3220.869 | I63: =I127 -> 3517.7901 | J63: =J127 -> 3826.3386 | K63: =K127 -> 4093.3711 | L63: =L127 -> 4385.9858 | M63: =M127 -> 4601.078
C64: Deferred revenue | D64: 1209.342 | E64: 1264.661 | F64: 1442.969 | G64: 1520.813 | H64: 1775.73 | I64: =I137 -> 2018.7231 | J64: =J137 -> 2255.9582 | K64: =K137 -> 2484.0455 | L64: =L137 -> 2712.6242 | M64: =M137 -> 2928.5613
C65: Short-term debt | D65: 699.823 | E65: 0 | F65: 399.844 | G65: 1784.453 | H65: 998.865 | I65: =I195 -> 998.865 | J65: =J195 -> 998.865 | K65: =K195 -> 998.865 | L65: =L195 -> 998.865 | M65: =M195 -> 998.865
C66: Content liabilities | D66: 7387.18 | E66: 7561.427 | F66: 7044.643 | G66: 6174.487 | H66: 5664.33 | I66: =H66*(1+I41) -> 6439.4441 | J66: =I66*(1+J41) -> 7196.1906 | K66: =J66*(1+K41) -> 7923.7574 | L66: =K66*(1+L41) -> 8652.8912 | M66: =L66*(1+M41) -> 9341.7004
C67: Long-term debt | D67: 14693.072 | E67: 14353.076 | F67: 14143.417 | G67: 13798.351 | H67: 13463.971 | I67: =I201 -> 13463.971 | J67: =J201 -> 13463.971 | K67: =K201 -> 13463.971 | L67: =L201 -> 13463.971 | M67: =M201 -> 13463.971
C68: Other liabilities | D68: 2459.164 | E68: 2452.04 | F68: 2561.434 | G68: 2552.25 | H68: 2957.128 | I68: =H68*(1+I41) -> 3361.7851 | J68: =I68*(1+J41) -> 3756.8533 | K68: =J68*(1+K41) -> 4136.6878 | L68: =K68*(1+L41) -> 4517.3404 | M68: =L68*(1+M41) -> 4876.9411
C69: Total Liabilities | D69: =SUM(D62:D68) -> 28735.415 | E69: =SUM(E62:E68) -> 27817.367 | F69: =SUM(F62:F68) -> 28143.679 | G69: =SUM(G62:G68) -> 28886.807 | H69: =SUM(H62:H68) -> 28981.055 | I69: =SUM(I62:I68) -> 30783.723 | J69: =SUM(J62:J68) -> 32567.554 | K69: =SUM(K62:K68) -> 34244.705 | ... M69: =SUM(M62:M68) -> 37497.017
C71: Common stock | D71: 4024.561 | E71: 4637.601 | F71: 5145.172 | G71: 6252.126 | H71: 7286.41 | I71: =H71+I37 -> 7705.278 | J71: =I71+J37 -> 8173.3703 | K71: =J71+K37 -> 8688.7888 | L71: =K71+L37 -> 9251.6355 | M71: =L71+M37 -> 9859.2872
C72: Treasury stock | D72: -824.19 | E72: -824.19 | F72: -6922.2 | G72: -13171.638 | H72: -22372.658 | I72: =H72+I229 -> -31499.825 | J72: =I72+J229 -> -40626.992 | K72: =J72+K229 -> -49754.159 | L72: =K72+L229 -> -58881.326 | M72: =L72+M229 -> -68008.493
C73: Retained earnings | D73: 12689.372 | E73: 17181.296 | F73: 22589.286 | G73: 31300.917 | H73: 42282.118 | I73: =I215 -> 55818.565 | J73: =J215 -> 71699.598 | K73: =K215 -> 89861.51 | L73: =L215 -> 110194.85 | M73: =M215 -> 133011.19
C74: Accumulated other comprehensive loss | D74: -40.495 | E74: -217.306 | F74: -223.945 | G74: 362.162 | H74: -580.382 | I74: =H74 -> -580.382 | J74: =I74 -> -580.382 | K74: =J74 -> -580.382 | L74: =K74 -> -580.382 | M74: =L74 -> -580.382
C75: Total Equity | D75: =SUM(D71:D74) -> 15849.248 | E75: =SUM(E71:E74) -> 20777.401 | F75: =SUM(F71:F74) -> 20588.313 | G75: =SUM(G71:G74) -> 24743.567 | H75: =SUM(H71:H74) -> 26615.488 | I75: =SUM(I71:I74) -> 31443.636 | J75: =SUM(J71:J74) -> 38665.595 | K75: =SUM(K71:K74) -> 48215.758 | ... M75: =SUM(M71:M74) -> 74281.598
C77: Balance check | D77: =D60-D69-D75 -> 0 | E77: =E60-E69-E75 -> 0 | F77: =F60-F69-F75 -> 0 | G77: =G60-G69-G75 -> 0 | H77: =H60-H69-H75 -> 0.45 | I77: =I60-I69-I75 -> 0.45 | J77: =J60-J69-J75 -> 0.45 | K77: =K60-K69-K75 -> 0.45 | ... M77: =M60-M69-M75 -> 0.45
B80: x | C80: CASH FLOW STATEMENT
C81: Fiscal Year | D81: 2021 | E81: 2022 | F81: 2023 | G81: 2024 | H81: 2025 | I81: 2026 | J81: 2027 | K81: 2028 | L81: 2029 | M81: 2030
C82: End Date | D82: 44561 | E82: =EOMONTH(D82,12) -> 44926 | F82: =EOMONTH(E82,12) -> 45291 | G82: =EOMONTH(F82,12) -> 45657 | H82: =EOMONTH(G82,12) -> 46022 | I82: =EOMONTH(H82,12) -> 46387 | J82: =EOMONTH(I82,12) -> 46752 | K82: =EOMONTH(J82,12) -> 47118 | L82: =EOMONTH(K82,12) -> 47483 | M82: =EOMONTH(L82,12) -> 47848
C84: Net income | I84: =I27 -> 13536.447 | J84: =J27 -> 15881.033 | K84: =K27 -> 18161.911 | L84: =L27 -> 20333.34 | M84: =M27 -> 22816.336
C85: Depreciation and amortization | I85: =I169 -> 390.97489 | J85: =J169 -> 415.86206 | K85: =K169 -> 462.09863 | L85: =L169 -> 527.20175 | M85: =M169 -> 608.67997
C86: Stock-based compensation | I86: =I37 -> 418.86803 | J86: =J37 -> 468.0923 | K86: =K37 -> 515.4185 | L86: =L37 -> 562.84664 | M86: =M37 -> 607.65177
C87: Changes in other current assets | I87: =H56-I56 -> -541.59475 | J87: =I56-J56 -> -528.76078 | K87: =J56-K56 -> -508.37205 | L87: =K56-L56 -> -509.46699 | M87: =L56-M56 -> -481.29101
C88: Changes in content assets | I88: =H57-I57 -> -4485.4368 | J88: =I57-J57 -> -4379.147 | K88: =J57-K57 -> -4210.2894 | L88: =K57-L57 -> -4219.3577 | M88: =L57-M57 -> -3986.0069
C89: Changes in other assets | I89: =H59-I59 -> -1066.5491 | J89: =I59-J59 -> -1041.2754 | K89: =J59-K59 -> -1001.1244 | L89: =K59-L59 -> -1003.2807 | M89: =L59-M59 -> -947.79441
C90: Changes in content liabilities | I90: =I66-H66 -> 775.11411 | J90: =J66-I66 -> 756.74651 | K90: =K66-J66 -> 727.56677 | L90: =L66-K66 -> 729.13382 | M90: =M66-L66 -> 688.80921
C91: Changes in accounts payable | I91: =I62-H62 -> 82.982923 | J91: =J62-I62 -> 86.232508 | K91: =K62-J62 -> 74.629701 | L91: =L62-K62 -> 81.779362 | M91: =M62-L62 -> 60.113548
C92: Changes in accrued expenses and other liabilities | I92: =I63-H63 -> 296.92114 | J92: =J63-I63 -> 308.54848 | K92: =K63-J63 -> 267.03248 | L92: =L63-K63 -> 292.61468 | M92: =M63-L63 -> 215.09224
C93: Changes in deferred revenue | I93: =I64-H64 -> 242.99315 | J93: =J64-I64 -> 237.23503 | K93: =K64-J64 -> 228.08737 | L93: =L64-K64 -> 228.57863 | M93: =M64-L64 -> 215.93713
C94: Changes in other liabilities | I94: =I68-H68 -> 404.65715 | J94: =J68-I68 -> 395.06814 | K94: =K68-J68 -> 379.83452 | L94: =L68-K68 -> 380.65262 | M94: =M68-L68 -> 359.60069
C95: Cash flows from operating activities | I95: =SUM(I84:I94) -> 10055.378 | J95: =SUM(J84:J94) -> 12599.635 | K95: =SUM(K84:K94) -> 15096.793 | L95: =SUM(L84:L94) -> 17404.043 | M95: =SUM(M84:M94) -> 20157.128
C97: Capital expenditures | I97: =-I150 -> -782.3969 | J97: =-J150 -> -874.34212 | K97: =-K150 -> -962.74199 | L97: =-L150 -> -1051.3322 | M97: =-M150 -> -1135.023
C98: Cash flows from investing activities | I98: =I97 -> -782.3969 | J98: =J97 -> -874.34212 | K98: =K97 -> -962.74199 | L98: =L97 -> -1051.3322 | M98: =M97 -> -1135.023
C100: Debt repayment | I100: =I193+I199 -> -1998 | J100: =J193+J199 -> -1998 | K100: =K193+K199 -> -1998 | L100: =L193+L199 -> -1998 | M100: =M193+M199 -> -1998
C101: Debt borrowing | I101: =I194+I200 -> 1998 | J101: =J194+J200 -> 1998 | K101: =K194+K200 -> 1998 | L101: =L194+L200 -> 1998 | M101: =M194+M200 -> 1998
C102: Share repurchases | I102: =I229 -> -9127.167 | J102: =J229 -> -9127.167 | K102: =K229 -> -9127.167 | L102: =L229 -> -9127.167 | M102: =M229 -> -9127.167
C103: Cash flows from financing activities | I103: =SUM(I100:I102) -> -9127.167 | J103: =SUM(J100:J102) -> -9127.167 | K103: =SUM(K100:K102) -> -9127.167 | L103: =SUM(L100:L102) -> -9127.167 | M103: =SUM(M100:M102) -> -9127.167
C105: Net change in cash | I105: =I95+I98+I103 -> 145.81425 | J105: =J95+J98+J103 -> 2598.1258 | K105: =K95+K98+K103 -> 5006.8845 | L105: =L95+L98+L103 -> 7225.5434 | M105: =M95+M98+M103 -> 9894.9378
C106: Beginning cash balance | I106: =H55 -> 9062.359 | J106: =I55 -> 9208.1732 | K106: =J55 -> 11806.299 | L106: =K55 -> 16813.184 | M106: =L55 -> 24038.727
C107: Ending cash balance | I107: =SUM(I105:I106) -> 9208.1732 | J107: =SUM(J105:J106) -> 11806.299 | K107: =SUM(K105:K106) -> 16813.184 | L107: =SUM(L105:L106) -> 24038.727 | M107: =SUM(M105:M106) -> 33933.665
B110: x | C110: Working Capital
C111: Fiscal Year | D111: 2021 | E111: 2022 | F111: 2023 | G111: 2024 | H111: 2025 | I111: 2026 | J111: 2027 | K111: 2028 | L111: 2029 | M111: 2030
C112: End Date | D112: 44561 | E112: =EOMONTH(D112,12) -> 44926 | F112: =EOMONTH(E112,12) -> 45291 | G112: =EOMONTH(F112,12) -> 45657 | H112: =EOMONTH(G112,12) -> 46022 | I112: =EOMONTH(H112,12) -> 46387 | J112: =EOMONTH(I112,12) -> 46752 | K112: =EOMONTH(J112,12) -> 47118 | L112: =EOMONTH(K112,12) -> 47483 | M112: =EOMONTH(L112,12) -> 47848
C114: Accounts payable
C115: Beginning of period | E115: =D117 -> 837.483 | F115: =E117 -> 671.513 | G115: =F117 -> 747.412 | H115: =G117 -> 899.909 | I115: =H117 -> 900.162 | J115: =I117 -> 983.14492 | K115: =J117 -> 1069.3774 | L115: =K117 -> 1144.0071 | M115: =L117 -> 1225.7865
C116: Increase/Decrease | E116: =E117-E115 -> -165.97 | F116: =F117-F115 -> 75.899 | G116: =G117-G115 -> 152.497 | H116: =H117-H115 -> 0.253 | I116: =I117-I115 -> 82.982923 | J116: =J117-J115 -> 86.232508 | K116: =K117-K115 -> 74.629701 | L116: =L117-L115 -> 81.779362 | M116: =M117-M115 -> 60.113548
C117: End of period | D117: =D62 -> 837.483 | E117: =E62 -> 671.513 | F117: =F62 -> 747.412 | G117: =G62 -> 899.909 | H117: =H62 -> 900.162 | I117: =IF($D$119=1,H117*(1+I121),2*-I14*I122/365-I115) -> 983.14492 | J117: =IF($D$119=1,I117*(1+J121),2*-J14*J122/365-J115) -> 1069.3774 | K117: =IF($D$119=1,J117*(1+K121),2*-K14*K122/365-K115) -> 1144.0071 | L117: =IF($D$119=1,K117*(1+L121),2*-L14*L122/365-L115) -> 1225.7865 | M117: =IF($D$119=1,L117*(1+M121),2*-M14*M122/365-M115) -> 1285.9
C119: A/P forecasting approach (1=grow with rev, 2=DSO) | D119: 1
C121: Grow in line with cost of revenue (1) | E121: =E14/D14-1 -> 0.10590409 | F121: =F14/E14-1 -> 0.028541051 | G121: =G14/F14-1 -> 0.067109881 | H121: =H14/G14-1 -> 0.10632264 | I121: =I14/H14-1 -> 0.092186654 | J121: =J14/I14-1 -> 0.087710882 | K121: =K14/J14-1 -> 0.069787989 | L121: =L14/K14-1 -> 0.071485011 | M121: =M14/L14-1 -> 0.049040798
C122: DPO Assumption (2) | E122: =(AVERAGE(E62,D62)/-E14)*365 -> 14.367053 | F122: =(AVERAGE(F62,E62)/-F14)*365 -> 13.134617 | G122: =(AVERAGE(G62,F62)/-G14)*365 -> 14.28983 | H122: =(AVERAGE(H62,G62)/-H14)*365 -> 14.114213 | I122: =H122 -> 14.114213 | J122: =I122 -> 14.114213 | K122: =J122 -> 14.114213 | L122: =K122 -> 14.114213 | M122: =L122 -> 14.114213
C124: Accrued expenses and other liabilities
C125: Beginning of period | E125: =D127 -> 1449.351 | F125: =E127 -> 1514.65 | G125: =F127 -> 1803.96 | H125: =G127 -> 2156.544 | I125: =H127 -> 3220.869 | J125: =I127 -> 3517.7901 | K125: =J127 -> 3826.3386 | L125: =K127 -> 4093.3711 | M125: =L127 -> 4385.9858
C126: Increase/Decrease | E126: =E127-E125 -> 65.299 | F126: =F127-F125 -> 289.31 | G126: =G127-G125 -> 352.584 | H126: =H127-H125 -> 1064.325 | I126: =I127-I125 -> 296.92114 | J126: =J127-J125 -> 308.54848 | K126: =K127-K125 -> 267.03248 | L126: =L127-L125 -> 292.61468 | M126: =M127-M125 -> 215.09224
C127: End of period | D127: =D63 -> 1449.351 | E127: =E63 -> 1514.65 | F127: =F63 -> 1803.96 | G127: =G63 -> 2156.544 | H127: =H63 -> 3220.869 | I127: =IF($D$129=1,H127*(1+I131),2*-I14*I132/365-I125) -> 3517.7901 | J127: =IF($D$129=1,I127*(1+J131),2*-J14*J132/365-J125) -> 3826.3386 | K127: =IF($D$129=1,J127*(1+K131),2*-K14*K132/365-K125) -> 4093.3711 | L127: =IF($D$129=1,K127*(1+L131),2*-L14*L132/365-L125) -> 4385.9858 | M127: =IF($D$129=1,L127*(1+M131),2*-M14*M132/365-M125) -> 4601.078
C129: Accrued liabilities forecasting approach (1=grow with rev, 2=DSO) | D129: 1
...

Sheet Pro Forma Financials
C2: Pro Forma Financial Statements
C3: In millions, except per share data
B5: x | C5: INCOME STATEMENT
C6: Fiscal Year | D6: 2026 | E6: 2027 | F6: 2028 | G6: 2029 | H6: 2030
C7: End Date | D7: 46387 | E7: =EOMONTH(D7,12) -> 46752 | F7: =EOMONTH(E7,12) -> 47118 | G7: =EOMONTH(F7,12) -> 47483 | H7: =EOMONTH(G7,12) -> 47848
C9: Revenue | D9: ='Target Financials'!I13+'Acquirer Financials'!I13+'M&A'!$D$41 -> 91298.09 | E9: ='Target Financials'!J13+'Acquirer Financials'!J13+'M&A'!$D$41 -> 98027.83 | F9: ='Target Financials'!K13+'Acquirer Financials'!K13+'M&A'!$D$41 -> 104449.35 | G9: ='Target Financials'!L13+'Acquirer Financials'!L13+'M&A'!$D$41 -> 110347.06 | H9: ='Target Financials'!M13+'Acquirer Financials'!M13+'M&A'!$D$41 -> 116353.38
C10: Revenue growth % | D10: =D9/('Target Financials'!H13+'Acquirer Financials'!H13)-1 -> 0.10692479 | E10: =E9/D9-1 -> 0.073711728 | F10: =F9/E9-1 -> 0.065507112 | G10: =G9/F9-1 -> 0.056464784 | H10: =H9/G9-1 -> 0.054431174
C11: Cost of revenue | D11: ='Target Financials'!I14+'Acquirer Financials'!I14 -> -47169.083 | E11: ='Target Financials'!J14+'Acquirer Financials'!J14 -> -49267.861 | F11: ='Target Financials'!K14+'Acquirer Financials'!K14 -> -52245.272 | G11: ='Target Financials'!L14+'Acquirer Financials'!L14 -> -54601.676 | H11: ='Target Financials'!M14+'Acquirer Financials'!M14 -> -56615.36
C12: Cost of revenue as % of revenue | D12: =-D11/D9 -> 0.51664917 | E12: =-E11/E9 -> 0.50259055 | F12: =-F11/F9 -> 0.5001972 | G12: =-G11/G9 -> 0.49481768 | H12: =-H11/H9 -> 0.48658114
C13: Gross profit | D13: =D9+D11 -> 44129.007 | E13: =E9+E11 -> 48759.969 | F13: =F9+F11 -> 52204.078 | G13: =G9+G11 -> 55745.384 | H13: =H9+H11 -> 59738.02
C14: Gross profit margin | D14: =D13/D9 -> 0.48335083 | E14: =E13/E9 -> 0.49740945 | F14: =F13/F9 -> 0.4998028 | G14: =G13/G9 -> 0.50518232 | H14: =H13/H9 -> 0.51341886
C15: Operating expenses | D15: ='Target Financials'!I20+'Acquirer Financials'!I19-'M&A'!G22 -> -25242.826 | E15: ='Target Financials'!J20+'Acquirer Financials'!J19 -> -25263.494 | F15: ='Target Financials'!K20+'Acquirer Financials'!K19 -> -25854.993 | G15: ='Target Financials'!L20+'Acquirer Financials'!L19 -> -26753.427 | H15: ='Target Financials'!M20+'Acquirer Financials'!M19 -> -27792.444
C16: Operating expenses as % of revenue | D16: =-D15/D9 -> 0.276488 | E16: =-E15/E9 -> 0.25771757 | F16: =-F15/F9 -> 0.24753618 | G16: =-G15/G9 -> 0.24244803 | H16: =-H15/H9 -> 0.23886237
C17: Incremental Depreciation and Amortization | D17: =-('M&A'!$G$34+'M&A'!$G$41) -> -5251.2725 | E17: =-('M&A'!$G$34+'M&A'!$G$41) -> -5251.2725 | F17: =-('M&A'!$G$34+'M&A'!$G$41) -> -5251.2725 | G17: =-('M&A'!$G$34+'M&A'!$G$41) -> -5251.2725 | H17: =-('M&A'!$G$34+'M&A'!$G$41) -> -5251.2725
C18: Incremental D&A as % of OPEX | D18: =D17/D15 -> 0.20803029 | E18: =E17/E15 -> 0.2078601 | F18: =F17/F15 -> 0.20310477 | G18: =G17/G15 -> 0.19628411 | H18: =H17/H15 -> 0.18894605
C19: Cost synergies | D19: ='M&A'!$D$40 -> 3000 | E19: ='M&A'!$D$40 -> 3000 | F19: ='M&A'!$D$40 -> 3000 | G19: ='M&A'!$D$40 -> 3000 | H19: ='M&A'!$D$40 -> 3000
C20: Cost synergies as % of OPEX | D20: =-D19/D15 -> 0.11884565 | E20: =-E19/E15 -> 0.11874842 | F20: =-F19/F15 -> 0.11603175 | G20: =-G19/G15 -> 0.11213517 | H20: =-H19/H15 -> 0.10794301
C21: EBIT | D21: =SUM(D13,D15,D17,D19) -> 16634.908 | E21: =SUM(E13,E15,E17,E19) -> 21245.202 | F21: =SUM(F13,F15,F17,F19) -> 24097.812 | G21: =SUM(G13,G15,G17,G19) -> 26740.684 | H21: =SUM(H13,H15,H17,H19) -> 29694.303
C22: EBIT Margin | D22: =D21/D9 -> 0.18220434 | E22: =E21/E9 -> 0.21672623 | F22: =F21/F9 -> 0.23071289 | G22: =G21/G9 -> 0.24233255 | H22: =H21/H9 -> 0.25520791
C23: Interest expense | D23: ='Target Financials'!I22+'Acquirer Financials'!I21+'M&A'!M23+D37 -> -5636.0767 | E23: ='Target Financials'!J22+'Acquirer Financials'!J21+'M&A'!N23+E37 -> -5375.3167 | F23: ='Target Financials'!K22+'Acquirer Financials'!K21+'M&A'!O23+F37 -> -4956.0267 | G23: ='Target Financials'!L22+'Acquirer Financials'!L21+'M&A'!P23+G37 -> -4564.1267 | H23: ='Target Financials'!M22+'Acquirer Financials'!M21+'M&A'!Q23+H37 -> -4403.1267
C24: Interest income | D24: ='Target Financials'!I23+'Acquirer Financials'!I22+'M&A'!M24 -> 286.12856 | E24: ='Target Financials'!J23+'Acquirer Financials'!J22+'M&A'!N24 -> 318.57028 | F24: ='Target Financials'!K23+'Acquirer Financials'!K22+'M&A'!O24 -> 421.58928 | G24: ='Target Financials'!L23+'Acquirer Financials'!L22+'M&A'!P24 -> 614.87412 | H24: ='Target Financials'!M23+'Acquirer Financials'!M22+'M&A'!Q24 -> 895.0186
C25: Other income (expense) | D25: ='Target Financials'!I24+'Acquirer Financials'!I23 -> 662.9546 | E25: ='Target Financials'!J24+'Acquirer Financials'!J23 -> 662.9546 | F25: ='Target Financials'!K24+'Acquirer Financials'!K23 -> 662.9546 | G25: ='Target Financials'!L24+'Acquirer Financials'!L23 -> 662.9546 | H25: ='Target Financials'!M24+'Acquirer Financials'!M23 -> 662.9546
C26: EBT | D26: =D21+SUM(D23:D25) -> 11947.915 | E26: =E21+SUM(E23:E25) -> 16851.41 | F26: =F21+SUM(F23:F25) -> 20226.329 | G26: =G21+SUM(G23:G25) -> 23454.386 | H26: =H21+SUM(H23:H25) -> 26849.15
C27: EBT Margin | D27: =D26/D9 -> 0.13086708 | E27: =E26/E9 -> 0.17190435 | F27: =F26/F9 -> 0.19364724 | G27: =G26/G9 -> 0.21255108 | H27: =H26/H9 -> 0.23075522
C28: Income tax expense | D28: =D26*-D29+'M&A'!M27 -> -939.5491 | E28: =E26*-E29+'M&A'!N27 -> -1612.4676 | F28: =F26*-F29+'M&A'!O27 -> -2280.4789 | G28: =G26*-G29+'M&A'!P27 -> -2959.3589 | H28: =H26*-H29+'M&A'!Q27 -> -3676.6392
C29: Effective tax rate | D29: ='Acquirer Financials'!I48 -> 0.1417 | E29: ='Acquirer Financials'!J48 -> 0.1404 | F29: ='Acquirer Financials'!K48 -> 0.15 | G29: ='Acquirer Financials'!L48 -> 0.1583 | H29: ='Acquirer Financials'!M48 -> 0.165
C30: Net income attributable to noncontrolling interests | D30: ='Target Financials'!I29+'Target Financials'!I30 -> -22 | E30: ='Target Financials'!J29+'Target Financials'!J30 -> -22 | F30: ='Target Financials'!K29+'Target Financials'!K30 -> -22 | G30: ='Target Financials'!L29+'Target Financials'!L30 -> -22 | H30: ='Target Financials'!M29+'Target Financials'!M30 -> -22
C31: Net income | D31: =D26+D28+D30 -> 10986.366 | E31: =E26+E28+E30 -> 15216.943 | F31: =F26+F28+F30 -> 17923.85 | G31: =G26+G28+G30 -> 20473.027 | H31: =H26+H28+H30 -> 23150.51
C32: Net income margin | D32: =D31/D9 -> 0.12033511 | E32: =E31/E9 -> 0.15523084 | F32: =F31/F9 -> 0.17160327 | G32: =G31/G9 -> 0.18553306 | H32: =H31/H9 -> 0.19896723
C35: Financing Fee Amortization
C36: Beginning financing fees | D36: ='M&A'!D63 -> 277.05767 | E36: =D38 -> 221.64614 | F36: =E38 -> 166.2346 | G36: =F38 -> 110.82307 | H36: =G38 -> 55.411534
C37: Amortization | D37: ='M&A'!$D$63/-'M&A'!$D$61 -> -55.411534 | E37: ='M&A'!$D$63/-'M&A'!$D$61 -> -55.411534 | F37: ='M&A'!$D$63/-'M&A'!$D$61 -> -55.411534 | G37: ='M&A'!$D$63/-'M&A'!$D$61 -> -55.411534 | H37: ='M&A'!$D$63/-'M&A'!$D$61 -> -55.411534
C38: Ending financing fees | D38: =SUM(D36:D37) -> 221.64614 | E38: =SUM(E36:E37) -> 166.2346 | F38: =SUM(F36:F37) -> 110.82307 | G38: =SUM(G36:G37) -> 55.411534 | H38: =SUM(H36:H37) -> 0
B41: x | C41: BALANCE SHEET ADJUSTMENTS
D42: Standalone | F42: Adjustments | H42: Pro Forma
D43: Warner Bros | E43: Neflix | F43: Increase | G43: (Decrease) | H43: 46387
C45: Cash and cash equivalents | D45: ='Target Financials'!I59 -> 4976.8937 | E45: ='Acquirer Financials'!I55 -> 9208.1732 | G45: =-('M&A'!G13+'M&A'!G15) -> -6382.0588 | H45: =SUM(D45:G45) -> 7803.0081
C46: Account receivables, net | D46: ='Target Financials'!I60 -> 5313.3259 | E46: 0 | H46: =SUM(D46:G46) -> 5313.3259
C47: Prepaid expenses and other current assets | D47: ='Target Financials'!I61 -> 3358.2147 | E47: ='Acquirer Financials'!I56 -> 4499.4268 | H47: =SUM(D47:G47) -> 7857.6414
C48: Property and equipment, net | D48: ='Target Financials'!I62 -> 6691.2317 | E48: ='Acquirer Financials'!I58 -> 2395.772 | F48: ='M&A'!G32 -> 1338.2463 | H48: =SUM(D48:G48) -> 10425.25
C49: Content assets, net | D49: 0 | E49: ='Acquirer Financials'!I57 -> 37263.829 | H49: =SUM(D49:G49) -> 37263.829
C50: Goodwill | D50: ='Target Financials'!I63 -> 25933 | E50: 0 | F50: ='M&A'!G59 -> 19702.02 | G50: =-D50 -> -25933 | H50: =SUM(D50:G50) -> 19702.02
C51: Intangible assets, net | D51: ='Target Financials'!I64 -> 47049.129 | E51: 0 | F51: ='M&A'!G39 -> 51754.042 | H51: =SUM(D51:G51) -> 98803.172
C52: Other assets | D52: ='Target Financials'!I65 -> 7409.9518 | E52: ='Acquirer Financials'!I59 -> 8860.6091 | G52: ='M&A'!G49 -> -4975 | H52: =SUM(D52:G52) -> 11295.561
C53: Total Assets | D53: =SUM(D45:D52) -> 100731.75 | E53: =SUM(E45:E52) -> 62227.81 | H53: =SUM(H45:H52) -> 198463.81
C55: Accounts payable | D55: ='Target Financials'!I68 -> 1138.1686 | E55: ='Acquirer Financials'!I62 -> 983.14492 | H55: =SUM(D55:G55) -> 2121.3135
C56: Accrued liabilities | D56: ='Target Financials'!I69 -> 10023.797 | E56: ='Acquirer Financials'!I63 -> 3517.7901 | H56: =SUM(D56:G56) -> 13541.588
C57: Content liabilities | D57: 0 | E57: ='Acquirer Financials'!I66 -> 6439.4441 | H57: =SUM(D57:G57) -> 6439.4441
C58: Deferred revenue | D58: ='Target Financials'!I70 -> 1647.9942 | E58: ='Acquirer Financials'!I64 -> 2018.7231 | H58: =SUM(D58:G58) -> 3666.7173
C59: Short-term debt | D59: ='Target Financials'!I71 -> 16483 | E59: ='Acquirer Financials'!I65 -> 998.865 | G59: =IF('M&A'!$D$54="Refinanced",-'Pro Forma Financials'!D59,0) -> -16483 | H59: =SUM(D59:G59) -> 998.865
C60: Long-term debt | D60: ='Target Financials'!I72 -> 15945 | E60: ='Acquirer Financials'!I67 -> 13463.971 | F60: ='M&A'!G11+'M&A'!G12 -> 55411.534 | G60: =IF('M&A'!$D$54="Refinanced",-'Pro Forma Financials'!D60,0)-'M&A'!D63 -> -16222.058 | H60: =SUM(D60:G60) -> 68598.447
C61: Deferred income taxes | D61: ='Target Financials'!I73 -> 6383 | E61: 0 | F61: ='M&A'!G54 -> 7523.1773 | G61: ='M&A'!G53 -> 0 | H61: =SUM(D61:G61) -> 13906.177
C62: Other liabilities | D62: ='Target Financials'!I74 -> 11650.375 | E62: ='Acquirer Financials'!I68 -> 3361.7851 | H62: =SUM(D62:G62) -> 15012.16
C63: Total Liabilities | D63: =SUM(D55:D62) -> 63271.335 | E63: =SUM(E55:E62) -> 30783.723 | H63: =SUM(H55:H62) -> 124284.71
C65: Shareholder's equity | D65: ='Target Financials'!I85+'Target Financials'!I77 -> 37460.412 | E65: ='Acquirer Financials'!I75 -> 31443.636 | F65: ='M&A'!G14 -> 43094.126 | G65: =-(D65+'M&A'!D39) -> -37819.529 | H65: =SUM(D65:G65) -> 74178.645
C66: Total Equity and Liabilities | D66: =D65+D63 -> 100731.75 | E66: =E63+E65 -> 62227.36 | H66: =H63+H65 -> 198463.36
C67: Balance Check | D67: =D53-D66 -> 0 | E67: =E53-E66 -> 0.45 | H67: =H53-H66 -> 0.45
B70: x | C70: Credit Statistics
D71: Standalone | H71: Pro Forma
D72: Warner Bros | E72: Neflix | H72: 46387
C74: Total debt | D74: ='Target Financials'!H71+'Target Financials'!H72 -> 32567 | E74: ='Acquirer Financials'!H65+'Acquirer Financials'!H67 -> 14462.836 | H74: =H59+H60 -> 69597.312
C75: Plus: Noncontrolling interests | D75: ='Target Financials'!H84 -> 1228 | E75: 0 | H75: =SUM(D75:E75) -> 1228
C76: Less: Cash and cash equivalents | D76: =-'Target Financials'!H59 -> -4566 | E76: =-'Acquirer Financials'!H55 -> -9062.359 | H76: =-H45 -> -7803.0081
C77: Net debt | D77: =SUM(D74:D76) -> 29229 | E77: =SUM(E74:E76) -> 5400.477 | H77: =SUM(H74:H76) -> 63022.304
C79: Equity value | D79: ='M&A'!D24*Shares!G31 -> 70917.661 | E79: ='M&A'!D16*Shares!L31 -> 401986.22 | H79: ='M&A'!D16*'M&A'!M31 -> 439008.51
C80: Enterprise value | D80: =D79+D77 -> 100146.66 | E80: =E79+E77 -> 407386.7 | H80: =H79+H77 -> 502030.81
C81: EBITDA for 2025YE | D81: ='M&A'!D43 -> 5658.6058 | E81: ='M&A'!D42 -> 35249.954 | H81: =SUM('Pro Forma Financials'!D81:E81) -> 40908.56
C82: Gross debt/EBITDA | D82: =SUM(D74:D75)/D81 -> 5.9723192 | E82: =SUM(E74:E75)/E81 -> 0.41029375 | H82: =SUM(H74:H75)/H81 -> 1.7313079
C83: EV/EBITDA | D83: =D80/D81 -> 17.698116 | E83: =E80/E81 -> 11.557085 | H83: =H80/H81 -> 12.272024
C84: Debt/equity | D84: {=SUM(D74:D75/D79)} -> 0.47653856 | E84: =SUM(E74:E75)/E79 -> 0.035978437 | H84: =SUM(H74:H75)/H79 -> 0.16133016

Sheet Shares
C2: Shares
C3: In millions, except per share data
D4: Target | I4: Acquirer
D5: Warner Bros | I5: Netflix
C7: Basic share count | G7: ='Target Financials'!D7 -> 2479.9295 | L7: ='Acquirer Financials'!D7 -> 4222.1622
C8: RSUs/PSUs | G8: 97 | L8: 1.58526
C9: Total Basic Share Count | G9: =SUM(G7:G8) -> 2576.9295 | L9: =SUM(L7:L8) -> 4223.7474
C11: Options count | G11: 46.1 | L11: 127.6798
C12: Weighted average exercise price | G12: 20.68 | L12: 34.07
C13: # of options exercised | G13: =IF(G12<'M&A'!D24,Shares!G11,0) -> 46.1 | L13: =IF(L12<'M&A'!D16,Shares!L11,0) -> 127.6798
C14: Option proceeds | G14: =G12*G13 -> 953.348 | L14: =L12*L13 -> 4350.0509
C15: Shares repurchased | G15: =G14/'M&A'!D24 -> 34.793723 | L15: =L14/'M&A'!D16 -> 46.584396
C16: Net Dilution from Options | G16: =G13-G15 -> 11.306277 | L16: =L13-L15 -> 81.095408
C18: Convertible debt outstanding | G18: 0 | L18: 0
C19: Conversion ratio | G19: 0 | L19: 0
C20: Conversion price | G20: 0 | L20: 0
C21: Common shares convertible into | G21: 0 | L21: 0
C22: Dilution from convertible debt | G22: 0 | L22: 0
C24: Convertible preferred par value | G24: 0 | L24: 0
C25: Preferred shares oustanding | G25: 0 | L25: 0
C26: Conversion ratio | G26: 0 | L26: 0
C27: Common shares convertible into | G27: 0 | L27: 0
C28: Conversion price | G28: 0 | L28: 0
C29: Dilution from preferred stock | G29: 0 | L29: 0
C31: Fully Diluted Shares Outstanding | G31: =G9+G16+G22+G29 -> 2588.2358 | L31: =L9+L16+L22+L29 -> 4304.8428
