Workbook

Sheet Dashboard
C2: Palantir Technologies
C3: Dashboard
C4: $ USD thousands unless stated otherwise
C6: GENERAL
C8: Ticker | D8: PLTR | H8: Active Case: | I8: Base
C9: Date | D9: 46093
C10: Share Price | D10: 153.5
C12: VALUATION SUMMARY
C15: Valuation Methodology | D15: Low | E15: Difference | F15: High | J15: Summary | K15: Price | L15: Weighting
C16: Comps Value from FY1 mean-median range EV/EBITDA | D16: =(Valuation!Q15*FSM!R32+DCF!N60)/DCF!S60 -> 366.6819 | E16: =F16-D16 -> 115.4389 | F16: =(Valuation!Q14*FSM!R32+DCF!N60)/DCF!S60 -> 482.1208 | J16: Comps | K16: =(Valuation!Q15*FSM!R32+DCF!N60)/DCF!S60 -> 366.6819 | L16: 0.3
C17: DCF Value at 2%-4.5% Perpetuity Range at 10.16% WACC | D17: =DCF!E79 -> 76.147046 | E17: =F17-D17 -> 24.919789 | F17: =DCF!J79 -> 101.06683 | J17: DCF - Gordon Growth | K17: =DCF!D69 -> 88.873239 | L17: 0.35
C18: DCF Value at 30x-40x Exit EBITDA Range at 10.16% WACC | D18: =DCF!E90 -> 185.56646 | E18: =F18-D18 -> 53.886225 | F18: =DCF!J90 -> 239.45269 | J18: DCF - Exit Multiple | K18: =DCF!E69 -> 217.34229 | L18: 0.35
J19: Average | K19: =SUMPRODUCT(K16:K18,L16:L18) -> 217.18001
J20: Upside | K20: =K19/D10-1 -> 0.41485347

Sheet Rev Build
C2: Revenue Build
C3: $USD Thousand except per share data
B5: x | C5: Fiscal Year | D5: 2021 | E5: 2022 | F5: 2023 | G5: 2024 | H5: 2025 | I5: 2026 | J5: 2027 | K5: 2028 | L5: 2029 | M5: 2030 | N5: 2031 | O5: 2032 | P5: 2033 | Q5: 2034 | R5: 2035
C6: End Date | D6: 44561 | E6: =EOMONTH(D6,12) -> 44926 | F6: =EOMONTH(E6,12) -> 45291 | G6: =EOMONTH(F6,12) -> 45657 | H6: =EOMONTH(G6,12) -> 46022 | I6: =EOMONTH(H6,12) -> 46387 | J6: =EOMONTH(I6,12) -> 46752 | K6: =EOMONTH(J6,12) -> 47118 | L6: =EOMONTH(K6,12) -> 47483 | ... R6: =EOMONTH(Q6,12) -> 49674
C8: U.S Commercial | E8: 335100 | F8: 457100 | G8: 702300 | H8: 1500000 | I8: =H8*(1+I9) -> 2518167.6 | J8: =I8*(1+J9) -> 4101536.8 | K8: =J8*(1+K9) -> 6475417.6 | L8: =K8*(1+L9) -> 9899478.4 | M8: =L8*(1+M9) -> 14639134 | N8: =M8*(1+N9) -> 20916079 | O8: =N8*(1+O9) -> 28838637 | P8: =O8*(1+P9) -> 38320157 | ... R8: =Q8*(1+R9) -> 60213811
C9: U.S Commercial Growth % | F9: =F8/E8-1 -> 0.36407043 | G9: =G8/F8-1 -> 0.53642529 | H9: =H8/G8-1 -> 1.1358394 | I9: =I28 -> 0.67877837 | J9: =J28 -> 0.62877837 | K9: =K28 -> 0.57877837 | L9: =L28 -> 0.52877837 | M9: =M28 -> 0.47877837 | N9: =N28 -> 0.42877837 | O9: =O28 -> 0.37877837 | P9: =P28 -> 0.32877837 | ... R9: =R28 -> 0.22877837
C11: International Commercial | E11: 498995 | F11: 545697 | G11: 593602 | H11: 573159 | I11: =H11*(1+I12) -> 601232.33 | J11: =I11*(1+J12) -> 627674.54 | K11: =J11*(1+K12) -> 652141.3 | L11: =K11*(1+L12) -> 674301.07 | M11: =L11*(1+M12) -> 693842.32 | N11: =M11*(1+N12) -> 710480.67 | O11: =N11*(1+O12) -> 723965.6 | P11: =O11*(1+P12) -> 734086.64 | ... R11: =Q11*(1+R12) -> 743626.66
C12: International Commercial Growth % | F12: =F11/E11-1 -> 0.09359212 | G12: =G11/F11-1 -> 0.087786812 | H12: =H11/G11-1 -> -0.0344389 | I12: =I29 -> 0.048980011 | J12: =J29 -> 0.043980011 | K12: =K29 -> 0.038980011 | L12: =L29 -> 0.033980011 | M12: =M29 -> 0.028980011 | N12: =N29 -> 0.023980011 | O12: =O29 -> 0.018980011 | P12: =P29 -> 0.013980011 | ... R12: =R29 -> 0.0039800107
C14: U.S Government | E14: 826300 | F14: 921200 | G14: 1200000 | H14: 1900000 | I14: =H14*(1+I15) -> 2533859.9 | J14: =I14*(1+J15) -> 3303166.2 | K14: =J14*(1+K15) -> 4206947.1 | L14: =K14*(1+L15) -> 5231803.4 | M14: =L14*(1+M15) -> 6349371.3 | N14: =M14*(1+N15) -> 7515182.3 | O14: =N14*(1+O15) -> 8669592.9 | P14: =O14*(1+P15) -> 9741245.3 | ... R14: =Q14*(1+R15) -> 11330778
C15: U.S Government Growth % | F15: =F14/E14-1 -> 0.11484933 | G15: =G14/F14-1 -> 0.30264872 | H15: =H14/G14-1 -> 0.58333333 | I15: =I30 -> 0.33361046 | J15: =J30 -> 0.30361046 | K15: =K30 -> 0.27361046 | L15: =L30 -> 0.24361046 | M15: =M30 -> 0.21361046 | N15: =N30 -> 0.18361046 | O15: =O30 -> 0.15361046 | P15: =P30 -> 0.12361046 | ... R15: =R30 -> 0.06361046
C17: International Government | E17: 245476 | F17: 301015 | G17: 369605 | H17: 502287 | I17: =H17*(1+I18) -> 638422.83 | J17: =I17*(1+J18) -> 798687.36 | K17: =J17*(1+K18) -> 983209.66 | L17: =K17*(1+L18) -> 1190698.3 | M17: =L17*(1+M18) -> 1418159.7 | N17: =M17*(1+N18) -> 1660710.4 | O17: =N17*(1+O18) -> 1911530.7 | P17: =O17*(1+P18) -> 2162002.3 | ... R17: =Q17*(1+R18) -> 2620717.3
C18: International Government Growth % | F18: =F17/E17-1 -> 0.22625022 | G18: =G17/F17-1 -> 0.2278624 | H18: =H17/G17-1 -> 0.35898324 | I18: =I31 -> 0.27103195 | J18: =J31 -> 0.25103195 | K18: =K31 -> 0.23103195 | L18: =L31 -> 0.21103195 | M18: =M31 -> 0.19103195 | N18: =N31 -> 0.17103195 | O18: =O31 -> 0.15103195 | P18: =P31 -> 0.13103195 | ... R18: =R31 -> 0.091031954
C20: Total Revenue | D20: 1541889 | E20: =SUM(E8,E11,E14,E17) -> 1905871 | F20: =SUM(F8,F11,F14,F17) -> 2225012 | G20: =SUM(G8,G11,G14,G17) -> 2865507 | H20: =SUM(H8,H11,H14,H17) -> 4475446 | I20: =SUM(I8,I11,I14,I17) -> 6291682.6 | J20: =SUM(J8,J11,J14,J17) -> 8831065 | K20: =SUM(K8,K11,K14,K17) -> 12317716 | L20: =SUM(L8,L11,L14,L17) -> 16996281 | ... R20: =SUM(R8,R11,R14,R17) -> 74908933
C21: Total Revenue Growth % | E21: =E20/D20-1 -> 0.23606239 | F21: =F20/E20-1 -> 0.16745152 | G21: =G20/F20-1 -> 0.28786137 | H21: =H20/G20-1 -> 0.56183391 | I21: =I20/H20-1 -> 0.40582248 | J21: =J20/I20-1 -> 0.40360942 | K21: =K20/J20-1 -> 0.39481656 | L21: =L20/K20-1 -> 0.37982412 | ... R21: =R20/Q20-1 -> 0.19283929
B24: x | C24: Scenario Analysis
H25: Variance From | I25: 2026 | J25: 2027 | K25: 2028 | L25: 2029 | M25: 2030 | N25: 2031 | O25: 2032 | P25: 2033 | Q25: 2034 | R25: 2035
C26: Active Case: | D26: =Dashboard!I8 -> Base | H26: Base Case | I26: =I6 -> 46387 | J26: =EOMONTH(I26,12) -> 46752 | K26: =EOMONTH(J26,12) -> 47118 | L26: =EOMONTH(K26,12) -> 47483 | M26: =EOMONTH(L26,12) -> 47848 | N26: =EOMONTH(M26,12) -> 48213 | O26: =EOMONTH(N26,12) -> 48579 | P26: =EOMONTH(O26,12) -> 48944 | Q26: =EOMONTH(P26,12) -> 49309 | R26: =EOMONTH(Q26,12) -> 49674
C28: U.S Commercial Growth % | H28: =OFFSET(H$39,MATCH($C28,$C$39:$C$82,0)+MATCH($D$26,$C$40:$C$42,0)-1,0) -> NM | I28: =OFFSET(I$39,MATCH($C28,$C$39:$C$82,0)+MATCH($D$26,$C$40:$C$42,0)-1,0) -> 0.67877837 | J28: =OFFSET(J$39,MATCH($C28,$C$39:$C$82,0)+MATCH($D$26,$C$40:$C$42,0)-1,0) -> 0.62877837 | K28: =OFFSET(K$39,MATCH($C28,$C$39:$C$82,0)+MATCH($D$26,$C$40:$C$42,0)-1,0) -> 0.57877837 | L28: =OFFSET(L$39,MATCH($C28,$C$39:$C$82,0)+MATCH($D$26,$C$40:$C$42,0)-1,0) -> 0.52877837 | M28: =OFFSET(M$39,MATCH($C28,$C$39:$C$82,0)+MATCH($D$26,$C$40:$C$42,0)-1,0) -> 0.47877837 | N28: =OFFSET(N$39,MATCH($C28,$C$39:$C$82,0)+MATCH($D$26,$C$40:$C$42,0)-1,0) -> 0.42877837 | O28: =OFFSET(O$39,MATCH($C28,$C$39:$C$82,0)+MATCH($D$26,$C$40:$C$42,0)-1,0) -> 0.37877837 | ... R28: =OFFSET(R$39,MATCH($C28,$C$39:$C$82,0)+MATCH($D$26,$C$40:$C$42,0)-1,0) -> 0.22877837
C29: International Commercial Growth % | H29: =OFFSET(H$39,MATCH($C29,$C$39:$C$82,0)+MATCH($D$26,$C$40:$C$42,0)-1,0) -> NM | I29: =OFFSET(I$39,MATCH($C29,$C$39:$C$82,0)+MATCH($D$26,$C$40:$C$42,0)-1,0) -> 0.048980011 | J29: =OFFSET(J$39,MATCH($C29,$C$39:$C$82,0)+MATCH($D$26,$C$40:$C$42,0)-1,0) -> 0.043980011 | K29: =OFFSET(K$39,MATCH($C29,$C$39:$C$82,0)+MATCH($D$26,$C$40:$C$42,0)-1,0) -> 0.038980011 | L29: =OFFSET(L$39,MATCH($C29,$C$39:$C$82,0)+MATCH($D$26,$C$40:$C$42,0)-1,0) -> 0.033980011 | M29: =OFFSET(M$39,MATCH($C29,$C$39:$C$82,0)+MATCH($D$26,$C$40:$C$42,0)-1,0) -> 0.028980011 | N29: =OFFSET(N$39,MATCH($C29,$C$39:$C$82,0)+MATCH($D$26,$C$40:$C$42,0)-1,0) -> 0.023980011 | O29: =OFFSET(O$39,MATCH($C29,$C$39:$C$82,0)+MATCH($D$26,$C$40:$C$42,0)-1,0) -> 0.018980011 | ... R29: =OFFSET(R$39,MATCH($C29,$C$39:$C$82,0)+MATCH($D$26,$C$40:$C$42,0)-1,0) -> 0.0039800107
C30: U.S Government Growth % | H30: =OFFSET(H$39,MATCH($C30,$C$39:$C$82,0)+MATCH($D$26,$C$40:$C$42,0)-1,0) -> NM | I30: =OFFSET(I$39,MATCH($C30,$C$39:$C$82,0)+MATCH($D$26,$C$40:$C$42,0)-1,0) -> 0.33361046 | J30: =OFFSET(J$39,MATCH($C30,$C$39:$C$82,0)+MATCH($D$26,$C$40:$C$42,0)-1,0) -> 0.30361046 | K30: =OFFSET(K$39,MATCH($C30,$C$39:$C$82,0)+MATCH($D$26,$C$40:$C$42,0)-1,0) -> 0.27361046 | L30: =OFFSET(L$39,MATCH($C30,$C$39:$C$82,0)+MATCH($D$26,$C$40:$C$42,0)-1,0) -> 0.24361046 | M30: =OFFSET(M$39,MATCH($C30,$C$39:$C$82,0)+MATCH($D$26,$C$40:$C$42,0)-1,0) -> 0.21361046 | N30: =OFFSET(N$39,MATCH($C30,$C$39:$C$82,0)+MATCH($D$26,$C$40:$C$42,0)-1,0) -> 0.18361046 | O30: =OFFSET(O$39,MATCH($C30,$C$39:$C$82,0)+MATCH($D$26,$C$40:$C$42,0)-1,0) -> 0.15361046 | ... R30: =OFFSET(R$39,MATCH($C30,$C$39:$C$82,0)+MATCH($D$26,$C$40:$C$42,0)-1,0) -> 0.06361046
C31: International Government Growth % | H31: =OFFSET(H$39,MATCH($C31,$C$39:$C$82,0)+MATCH($D$26,$C$40:$C$42,0)-1,0) -> NM | I31: =OFFSET(I$39,MATCH($C31,$C$39:$C$82,0)+MATCH($D$26,$C$40:$C$42,0)-1,0) -> 0.27103195 | J31: =OFFSET(J$39,MATCH($C31,$C$39:$C$82,0)+MATCH($D$26,$C$40:$C$42,0)-1,0) -> 0.25103195 | K31: =OFFSET(K$39,MATCH($C31,$C$39:$C$82,0)+MATCH($D$26,$C$40:$C$42,0)-1,0) -> 0.23103195 | L31: =OFFSET(L$39,MATCH($C31,$C$39:$C$82,0)+MATCH($D$26,$C$40:$C$42,0)-1,0) -> 0.21103195 | M31: =OFFSET(M$39,MATCH($C31,$C$39:$C$82,0)+MATCH($D$26,$C$40:$C$42,0)-1,0) -> 0.19103195 | N31: =OFFSET(N$39,MATCH($C31,$C$39:$C$82,0)+MATCH($D$26,$C$40:$C$42,0)-1,0) -> 0.17103195 | O31: =OFFSET(O$39,MATCH($C31,$C$39:$C$82,0)+MATCH($D$26,$C$40:$C$42,0)-1,0) -> 0.15103195 | ... R31: =OFFSET(R$39,MATCH($C31,$C$39:$C$82,0)+MATCH($D$26,$C$40:$C$42,0)-1,0) -> 0.091031954
C33: Gross margin % | H33: =OFFSET(H$39,MATCH($C33,$C$39:$C$82,0)+MATCH($D$26,$C$40:$C$42,0)-1,0) -> NM | I33: =OFFSET(I$39,MATCH($C33,$C$39:$C$82,0)+MATCH($D$26,$C$40:$C$42,0)-1,0) -> 0.82366517 | J33: =OFFSET(J$39,MATCH($C33,$C$39:$C$82,0)+MATCH($D$26,$C$40:$C$42,0)-1,0) -> 0.82366517 | K33: =OFFSET(K$39,MATCH($C33,$C$39:$C$82,0)+MATCH($D$26,$C$40:$C$42,0)-1,0) -> 0.82366517 | L33: =OFFSET(L$39,MATCH($C33,$C$39:$C$82,0)+MATCH($D$26,$C$40:$C$42,0)-1,0) -> 0.82366517 | M33: =OFFSET(M$39,MATCH($C33,$C$39:$C$82,0)+MATCH($D$26,$C$40:$C$42,0)-1,0) -> 0.82366517 | N33: =OFFSET(N$39,MATCH($C33,$C$39:$C$82,0)+MATCH($D$26,$C$40:$C$42,0)-1,0) -> 0.82366517 | O33: =OFFSET(O$39,MATCH($C33,$C$39:$C$82,0)+MATCH($D$26,$C$40:$C$42,0)-1,0) -> 0.82366517 | ... R33: =OFFSET(R$39,MATCH($C33,$C$39:$C$82,0)+MATCH($D$26,$C$40:$C$42,0)-1,0) -> 0.82366517
C34: Sales & marketing % of sales | H34: =OFFSET(H$39,MATCH($C34,$C$39:$C$82,0)+MATCH($D$26,$C$40:$C$42,0)-1,0) -> NM | I34: =OFFSET(I$39,MATCH($C34,$C$39:$C$82,0)+MATCH($D$26,$C$40:$C$42,0)-1,0) -> 0.23614607 | J34: =OFFSET(J$39,MATCH($C34,$C$39:$C$82,0)+MATCH($D$26,$C$40:$C$42,0)-1,0) -> 0.23114607 | K34: =OFFSET(K$39,MATCH($C34,$C$39:$C$82,0)+MATCH($D$26,$C$40:$C$42,0)-1,0) -> 0.22614607 | L34: =OFFSET(L$39,MATCH($C34,$C$39:$C$82,0)+MATCH($D$26,$C$40:$C$42,0)-1,0) -> 0.22114607 | M34: =OFFSET(M$39,MATCH($C34,$C$39:$C$82,0)+MATCH($D$26,$C$40:$C$42,0)-1,0) -> 0.21614607 | N34: =OFFSET(N$39,MATCH($C34,$C$39:$C$82,0)+MATCH($D$26,$C$40:$C$42,0)-1,0) -> 0.21114607 | O34: =OFFSET(O$39,MATCH($C34,$C$39:$C$82,0)+MATCH($D$26,$C$40:$C$42,0)-1,0) -> 0.20614607 | ... R34: =OFFSET(R$39,MATCH($C34,$C$39:$C$82,0)+MATCH($D$26,$C$40:$C$42,0)-1,0) -> 0.19114607
C35: Research & development % of sales | H35: =OFFSET(H$39,MATCH($C35,$C$39:$C$82,0)+MATCH($D$26,$C$40:$C$42,0)-1,0) -> NM | I35: =OFFSET(I$39,MATCH($C35,$C$39:$C$82,0)+MATCH($D$26,$C$40:$C$42,0)-1,0) -> 0.12460814 | J35: =OFFSET(J$39,MATCH($C35,$C$39:$C$82,0)+MATCH($D$26,$C$40:$C$42,0)-1,0) -> 0.11960814 | K35: =OFFSET(K$39,MATCH($C35,$C$39:$C$82,0)+MATCH($D$26,$C$40:$C$42,0)-1,0) -> 0.11460814 | L35: =OFFSET(L$39,MATCH($C35,$C$39:$C$82,0)+MATCH($D$26,$C$40:$C$42,0)-1,0) -> 0.10960814 | M35: =OFFSET(M$39,MATCH($C35,$C$39:$C$82,0)+MATCH($D$26,$C$40:$C$42,0)-1,0) -> 0.10460814 | N35: =OFFSET(N$39,MATCH($C35,$C$39:$C$82,0)+MATCH($D$26,$C$40:$C$42,0)-1,0) -> 0.09960814 | O35: =OFFSET(O$39,MATCH($C35,$C$39:$C$82,0)+MATCH($D$26,$C$40:$C$42,0)-1,0) -> 0.09460814 | ... R35: =OFFSET(R$39,MATCH($C35,$C$39:$C$82,0)+MATCH($D$26,$C$40:$C$42,0)-1,0) -> 0.07960814
C36: General & administrative % of sales | H36: =OFFSET(H$39,MATCH($C36,$C$39:$C$82,0)+MATCH($D$26,$C$40:$C$42,0)-1,0) -> NM | I36: =OFFSET(I$39,MATCH($C36,$C$39:$C$82,0)+MATCH($D$26,$C$40:$C$42,0)-1,0) -> 0.14696144 | J36: =OFFSET(J$39,MATCH($C36,$C$39:$C$82,0)+MATCH($D$26,$C$40:$C$42,0)-1,0) -> 0.14196144 | K36: =OFFSET(K$39,MATCH($C36,$C$39:$C$82,0)+MATCH($D$26,$C$40:$C$42,0)-1,0) -> 0.13696144 | L36: =OFFSET(L$39,MATCH($C36,$C$39:$C$82,0)+MATCH($D$26,$C$40:$C$42,0)-1,0) -> 0.13196144 | M36: =OFFSET(M$39,MATCH($C36,$C$39:$C$82,0)+MATCH($D$26,$C$40:$C$42,0)-1,0) -> 0.12696144 | N36: =OFFSET(N$39,MATCH($C36,$C$39:$C$82,0)+MATCH($D$26,$C$40:$C$42,0)-1,0) -> 0.12196144 | O36: =OFFSET(O$39,MATCH($C36,$C$39:$C$82,0)+MATCH($D$26,$C$40:$C$42,0)-1,0) -> 0.11696144 | ... R36: =OFFSET(R$39,MATCH($C36,$C$39:$C$82,0)+MATCH($D$26,$C$40:$C$42,0)-1,0) -> 0.10196144
C37: Other income % of sales | H37: =OFFSET(H$39,MATCH($C37,$C$39:$C$82,0)+MATCH($D$26,$C$40:$C$42,0)-1,0) -> NM | I37: =OFFSET(I$39,MATCH($C37,$C$39:$C$82,0)+MATCH($D$26,$C$40:$C$42,0)-1,0) -> 0.0031666118 | J37: =OFFSET(J$39,MATCH($C37,$C$39:$C$82,0)+MATCH($D$26,$C$40:$C$42,0)-1,0) -> 0.0031666118 | K37: =OFFSET(K$39,MATCH($C37,$C$39:$C$82,0)+MATCH($D$26,$C$40:$C$42,0)-1,0) -> 0.0031666118 | L37: =OFFSET(L$39,MATCH($C37,$C$39:$C$82,0)+MATCH($D$26,$C$40:$C$42,0)-1,0) -> 0.0031666118 | M37: =OFFSET(M$39,MATCH($C37,$C$39:$C$82,0)+MATCH($D$26,$C$40:$C$42,0)-1,0) -> 0.0031666118 | N37: =OFFSET(N$39,MATCH($C37,$C$39:$C$82,0)+MATCH($D$26,$C$40:$C$42,0)-1,0) -> 0.0031666118 | O37: =OFFSET(O$39,MATCH($C37,$C$39:$C$82,0)+MATCH($D$26,$C$40:$C$42,0)-1,0) -> 0.0031666118 | ... R37: =OFFSET(R$39,MATCH($C37,$C$39:$C$82,0)+MATCH($D$26,$C$40:$C$42,0)-1,0) -> 0.0031666118
C39: U.S Commercial Growth %
C40: Bull | H40: 0.02 | I40: =I41+$H$40 -> 0.69877837 | J40: =J41+$H$40 -> 0.64877837 | K40: =K41+$H$40 -> 0.59877837 | L40: =L41+$H$40 -> 0.54877837 | M40: =M41+$H$40 -> 0.49877837 | N40: =N41+$H$40 -> 0.44877837 | O40: =O41+$H$40 -> 0.39877837 | P40: =P41+$H$40 -> 0.34877837 | ... R40: =R41+$H$40 -> 0.24877837 | T40: Step
C41: Base | H41: NM | I41: =AVERAGE(F9:H9) -> 0.67877837 | J41: =I41+$T$41 -> 0.62877837 | K41: =J41+$T$41 -> 0.57877837 | L41: =K41+$T$41 -> 0.52877837 | M41: =L41+$T$41 -> 0.47877837 | N41: =M41+$T$41 -> 0.42877837 | O41: =N41+$T$41 -> 0.37877837 | P41: =O41+$T$41 -> 0.32877837 | Q41: =P41+$T$41 -> 0.27877837 | R41: =Q41+$T$41 -> 0.22877837 | T41: -0.05
C42: Bear | H42: -0.02 | I42: =I41+$H$42 -> 0.65877837 | J42: =J41+$H$42 -> 0.60877837 | K42: =K41+$H$42 -> 0.55877837 | L42: =L41+$H$42 -> 0.50877837 | M42: =M41+$H$42 -> 0.45877837 | N42: =N41+$H$42 -> 0.40877837 | O42: =O41+$H$42 -> 0.35877837 | P42: =P41+$H$42 -> 0.30877837 | ... R42: =R41+$H$42 -> 0.20877837
C44: International Commercial Growth %
C45: Bull | H45: 0.01 | I45: =I46+$H$45 -> 0.058980011 | J45: =J46+$H$45 -> 0.053980011 | K45: =K46+$H$45 -> 0.048980011 | L45: =L46+$H$45 -> 0.043980011 | M45: =M46+$H$45 -> 0.038980011 | N45: =N46+$H$45 -> 0.033980011 | O45: =O46+$H$45 -> 0.028980011 | P45: =P46+$H$45 -> 0.023980011 | ... R45: =R46+$H$45 -> 0.013980011 | T45: Step
C46: Base | H46: NM | I46: =AVERAGE(F12:H12) -> 0.048980011 | J46: =I46+$T$46 -> 0.043980011 | K46: =J46+$T$46 -> 0.038980011 | L46: =K46+$T$46 -> 0.033980011 | M46: =L46+$T$46 -> 0.028980011 | N46: =M46+$T$46 -> 0.023980011 | O46: =N46+$T$46 -> 0.018980011 | P46: =O46+$T$46 -> 0.013980011 | Q46: =P46+$T$46 -> 0.0089800107 | R46: =Q46+$T$46 -> 0.0039800107 | T46: -0.005
C47: Bear | H47: -0.01 | I47: =I46+$H$47 -> 0.038980011 | J47: =J46+$H$47 -> 0.033980011 | K47: =K46+$H$47 -> 0.028980011 | L47: =L46+$H$47 -> 0.023980011 | M47: =M46+$H$47 -> 0.018980011 | N47: =N46+$H$47 -> 0.013980011 | O47: =O46+$H$47 -> 0.0089800107 | P47: =P46+$H$47 -> 0.0039800107 | ... R47: =R46+$H$47 -> -0.0060199893
C49: U.S Government Growth %
C50: Bull | H50: 0.02 | I50: =I51+$H$50 -> 0.35361046 | J50: =J51+$H$50 -> 0.32361046 | K50: =K51+$H$50 -> 0.29361046 | L50: =L51+$H$50 -> 0.26361046 | M50: =M51+$H$50 -> 0.23361046 | N50: =N51+$H$50 -> 0.20361046 | O50: =O51+$H$50 -> 0.17361046 | P50: =P51+$H$50 -> 0.14361046 | ... R50: =R51+$H$50 -> 0.08361046 | T50: Step
C51: Base | H51: NM | I51: =AVERAGE(F15:H15) -> 0.33361046 | J51: =I51+$T$51 -> 0.30361046 | K51: =J51+$T$51 -> 0.27361046 | L51: =K51+$T$51 -> 0.24361046 | M51: =L51+$T$51 -> 0.21361046 | N51: =M51+$T$51 -> 0.18361046 | O51: =N51+$T$51 -> 0.15361046 | P51: =O51+$T$51 -> 0.12361046 | Q51: =P51+$T$51 -> 0.09361046 | R51: =Q51+$T$51 -> 0.06361046 | T51: -0.03
C52: Bear | H52: -0.02 | I52: =I51+$H$52 -> 0.31361046 | J52: =J51+$H$52 -> 0.28361046 | K52: =K51+$H$52 -> 0.25361046 | L52: =L51+$H$52 -> 0.22361046 | M52: =M51+$H$52 -> 0.19361046 | N52: =N51+$H$52 -> 0.16361046 | O52: =O51+$H$52 -> 0.13361046 | P52: =P51+$H$52 -> 0.10361046 | ... R52: =R51+$H$52 -> 0.04361046
C54: International Government Growth %
C55: Bull | H55: 0.02 | I55: =I56+$H$55 -> 0.29103195 | J55: =J56+$H$55 -> 0.27103195 | K55: =K56+$H$55 -> 0.25103195 | L55: =L56+$H$55 -> 0.23103195 | M55: =M56+$H$55 -> 0.21103195 | N55: =N56+$H$55 -> 0.19103195 | O55: =O56+$H$55 -> 0.17103195 | P55: =P56+$H$55 -> 0.15103195 | ... R55: =R56+$H$55 -> 0.11103195 | T55: Step
C56: Base | H56: NM | I56: =AVERAGE(F18:H18) -> 0.27103195 | J56: =I56+$T$56 -> 0.25103195 | K56: =J56+$T$56 -> 0.23103195 | L56: =K56+$T$56 -> 0.21103195 | M56: =L56+$T$56 -> 0.19103195 | N56: =M56+$T$56 -> 0.17103195 | O56: =N56+$T$56 -> 0.15103195 | P56: =O56+$T$56 -> 0.13103195 | Q56: =P56+$T$56 -> 0.11103195 | R56: =Q56+$T$56 -> 0.091031954 | T56: -0.02
C57: Bear | H57: -0.02 | I57: =I56+$H$57 -> 0.25103195 | J57: =J56+$H$57 -> 0.23103195 | K57: =K56+$H$57 -> 0.21103195 | L57: =L56+$H$57 -> 0.19103195 | M57: =M56+$H$57 -> 0.17103195 | N57: =N56+$H$57 -> 0.15103195 | O57: =O56+$H$57 -> 0.13103195 | P57: =P56+$H$57 -> 0.11103195 | ... R57: =R56+$H$57 -> 0.071031954
C59: Gross margin %
C60: Bull | H60: 0.02 | I60: =I61+$H$60 -> 0.84366517 | J60: =J61+$H$60 -> 0.84366517 | K60: =K61+$H$60 -> 0.84366517 | L60: =L61+$H$60 -> 0.84366517 | M60: =M61+$H$60 -> 0.84366517 | N60: =N61+$H$60 -> 0.84366517 | O60: =O61+$H$60 -> 0.84366517 | P60: =P61+$H$60 -> 0.84366517 | ... R60: =R61+$H$60 -> 0.84366517
C61: Base | H61: NM | I61: =FSM!H38 -> 0.82366517 | J61: =I61 -> 0.82366517 | K61: =J61 -> 0.82366517 | L61: =K61 -> 0.82366517 | M61: =L61 -> 0.82366517 | N61: =M61 -> 0.82366517 | O61: =N61 -> 0.82366517 | P61: =O61 -> 0.82366517 | Q61: =P61 -> 0.82366517 | R61: =Q61 -> 0.82366517
C62: Bear | H62: -0.02 | I62: =I61+$H$62 -> 0.80366517 | J62: =J61+$H$62 -> 0.80366517 | K62: =K61+$H$62 -> 0.80366517 | L62: =L61+$H$62 -> 0.80366517 | M62: =M61+$H$62 -> 0.80366517 | N62: =N61+$H$62 -> 0.80366517 | O62: =O61+$H$62 -> 0.80366517 | P62: =P61+$H$62 -> 0.80366517 | ... R62: =R61+$H$62 -> 0.80366517
C64: Sales & marketing % of sales
C65: Bull | H65: 0.02 | I65: =I66+$H$65 -> 0.25614607 | J65: =J66+$H$65 -> 0.25114607 | K65: =K66+$H$65 -> 0.24614607 | L65: =L66+$H$65 -> 0.24114607 | M65: =M66+$H$65 -> 0.23614607 | N65: =N66+$H$65 -> 0.23114607 | O65: =O66+$H$65 -> 0.22614607 | P65: =P66+$H$65 -> 0.22114607 | ... R65: =R66+$H$65 -> 0.21114607 | T65: Step
C66: Base | H66: NM | I66: =FSM!H40 -> 0.23614607 | J66: =I66+$T$66 -> 0.23114607 | K66: =J66+$T$66 -> 0.22614607 | L66: =K66+$T$66 -> 0.22114607 | M66: =L66+$T$66 -> 0.21614607 | N66: =M66+$T$66 -> 0.21114607 | O66: =N66+$T$66 -> 0.20614607 | P66: =O66+$T$66 -> 0.20114607 | Q66: =P66+$T$66 -> 0.19614607 | R66: =Q66+$T$66 -> 0.19114607 | T66: -0.005
C67: Bear | H67: -0.02 | I67: =I66+$H$67 -> 0.21614607 | J67: =J66+$H$67 -> 0.21114607 | K67: =K66+$H$67 -> 0.20614607 | L67: =L66+$H$67 -> 0.20114607 | M67: =M66+$H$67 -> 0.19614607 | N67: =N66+$H$67 -> 0.19114607 | O67: =O66+$H$67 -> 0.18614607 | P67: =P66+$H$67 -> 0.18114607 | ... R67: =R66+$H$67 -> 0.17114607
C69: Research & development % of sales
C70: Bull | H70: 0.02 | I70: =I71+$H$70 -> 0.14460814 | J70: =J71+$H$70 -> 0.13960814 | K70: =K71+$H$70 -> 0.13460814 | L70: =L71+$H$70 -> 0.12960814 | M70: =M71+$H$70 -> 0.12460814 | N70: =N71+$H$70 -> 0.11960814 | O70: =O71+$H$70 -> 0.11460814 | P70: =P71+$H$70 -> 0.10960814 | ... R70: =R71+$H$70 -> 0.09960814 | T70: Step
C71: Base | H71: NM | I71: =FSM!H41 -> 0.12460814 | J71: =I71+$T$71 -> 0.11960814 | K71: =J71+$T$71 -> 0.11460814 | L71: =K71+$T$71 -> 0.10960814 | M71: =L71+$T$71 -> 0.10460814 | N71: =M71+$T$71 -> 0.09960814 | O71: =N71+$T$71 -> 0.09460814 | P71: =O71+$T$71 -> 0.08960814 | Q71: =P71+$T$71 -> 0.08460814 | R71: =Q71+$T$71 -> 0.07960814 | T71: -0.005
C72: Bear | H72: -0.02 | I72: =I71+$H$72 -> 0.10460814 | J72: =J71+$H$72 -> 0.09960814 | K72: =K71+$H$72 -> 0.09460814 | L72: =L71+$H$72 -> 0.08960814 | M72: =M71+$H$72 -> 0.08460814 | N72: =N71+$H$72 -> 0.07960814 | O72: =O71+$H$72 -> 0.07460814 | P72: =P71+$H$72 -> 0.06960814 | ... R72: =R71+$H$72 -> 0.05960814
C74: General & administrative % of sales
C75: Bull | H75: 0.02 | I75: =I76+$H$75 -> 0.16696144 | J75: =J76+$H$75 -> 0.16196144 | K75: =K76+$H$75 -> 0.15696144 | L75: =L76+$H$75 -> 0.15196144 | M75: =M76+$H$75 -> 0.14696144 | N75: =N76+$H$75 -> 0.14196144 | O75: =O76+$H$75 -> 0.13696144 | P75: =P76+$H$75 -> 0.13196144 | ... R75: =R76+$H$75 -> 0.12196144 | T75: Step
C76: Base | H76: NM | I76: =FSM!H42 -> 0.14696144 | J76: =I76+$T$76 -> 0.14196144 | K76: =J76+$T$76 -> 0.13696144 | L76: =K76+$T$76 -> 0.13196144 | M76: =L76+$T$76 -> 0.12696144 | N76: =M76+$T$76 -> 0.12196144 | O76: =N76+$T$76 -> 0.11696144 | P76: =O76+$T$76 -> 0.11196144 | Q76: =P76+$T$76 -> 0.10696144 | R76: =Q76+$T$76 -> 0.10196144 | T76: -0.005
C77: Bear | H77: -0.02 | I77: =I76+$H$77 -> 0.12696144 | J77: =J76+$H$77 -> 0.12196144 | K77: =K76+$H$77 -> 0.11696144 | L77: =L76+$H$77 -> 0.11196144 | M77: =M76+$H$77 -> 0.10696144 | N77: =N76+$H$77 -> 0.10196144 | O77: =O76+$H$77 -> 0.096961443 | P77: =P76+$H$77 -> 0.091961443 | ... R77: =R76+$H$77 -> 0.081961443
C79: Other income % of sales
C80: Bull | H80: 0.02 | I80: =I81+$H$80 -> 0.023166612 | J80: =J81+$H$80 -> 0.023166612 | K80: =K81+$H$80 -> 0.023166612 | L80: =L81+$H$80 -> 0.023166612 | M80: =M81+$H$80 -> 0.023166612 | N80: =N81+$H$80 -> 0.023166612 | O80: =O81+$H$80 -> 0.023166612 | P80: =P81+$H$80 -> 0.023166612 | ... R80: =R81+$H$80 -> 0.023166612
C81: Base | H81: NM | I81: =FSM!H44 -> 0.0031666118 | J81: =I81 -> 0.0031666118 | K81: =J81 -> 0.0031666118 | L81: =K81 -> 0.0031666118 | M81: =L81 -> 0.0031666118 | N81: =M81 -> 0.0031666118 | O81: =N81 -> 0.0031666118 | P81: =O81 -> 0.0031666118 | Q81: =P81 -> 0.0031666118 | R81: =Q81 -> 0.0031666118
C82: Bear | H82: -0.02 | I82: =I81+$H$82 -> -0.016833388 | J82: =J81+$H$82 -> -0.016833388 | K82: =K81+$H$82 -> -0.016833388 | L82: =L81+$H$82 -> -0.016833388 | M82: =M81+$H$82 -> -0.016833388 | N82: =N81+$H$82 -> -0.016833388 | O82: =O81+$H$82 -> -0.016833388 | P82: =P81+$H$82 -> -0.016833388 | ... R82: =R81+$H$82 -> -0.016833388
B85: x | C85: Sensitivity Analysis
C87: First year forecast net income sensitivity
D89: U.S Commercial Growth % | L89: International Commercial Growth %
D90: =FSM!I26 -> 1744867.7 | E90: 0.55 | F90: =E90+0.05 -> 0.6 | G90: =F90+0.05 -> 0.65 | H90: =G90+0.05 -> 0.7 | I90: =H90+0.05 -> 0.75 | J90: =I90+0.05 -> 0.8 | L90: =FSM!I26 -> 1744867.7 | M90: 0.035 | N90: =M90+0.005 -> 0.04 | O90: =N90+0.005 -> 0.045 | P90: =O90+0.005 -> 0.05 | Q90: =P90+0.005 -> 0.055 | R90: =Q90+0.005 -> 0.06
D91: 0.78 | E91: 1490277.3 | F91: 1506494.9 | G91: 1522712.5 | H91: 1538930.1 | I91: 1555147.7 | J91: 1571365.3 | L91: 0.78 | M91: 1530314.2 | N91: 1530933.9 | O91: 1531553.6 | P91: 1532173.2 | Q91: 1532792.9 | R91: 1533412.6
C92: Gross | D92: =D91+0.02 -> 0.8 | E92: 1584763 | F92: 1602142.6 | G92: 1619522.2 | H92: 1636901.9 | I92: 1654281.5 | J92: 1671661.1 | K92: Gross | L92: =L91+0.02 -> 0.8 | M92: 1627668.6 | N92: 1628332.7 | O92: 1628996.8 | P92: 1629660.9 | Q92: 1630324.9 | R92: 1630989
C93: margin | D93: =D92+0.02 -> 0.82 | E93: 1679248.8 | F93: 1697790.4 | G93: 1716332 | H93: 1734873.6 | I93: 1753415.2 | J93: 1771956.8 | K93: margin | L93: =L92+0.02 -> 0.82 | M93: 1725023 | N93: 1725731.5 | O93: 1726440 | P93: 1727148.5 | Q93: 1727857 | R93: 1728565.4
C94: % | D94: =D93+0.02 -> 0.84 | E94: 1773734.6 | F94: 1793438.2 | G94: 1813141.8 | H94: 1832845.4 | I94: 1852548.9 | J94: 1872252.5 | K94: % | L94: =L93+0.02 -> 0.84 | M94: 1822377.4 | N94: 1823130.3 | O94: 1823883.2 | P94: 1824636.1 | Q94: 1825389 | R94: 1826141.9
D95: =D94+0.02 -> 0.86 | E95: 1868220.3 | F95: 1889085.9 | G95: 1909951.5 | H95: 1930817.1 | I95: 1951682.7 | J95: 1972548.3 | L95: =L94+0.02 -> 0.86 | M95: 1919731.8 | N95: 1920529.1 | O95: 1921326.4 | P95: 1922123.7 | Q95: 1922921 | R95: 1923718.3
D96: =D95+0.02 -> 0.88 | E96: 1962706.1 | F96: 1984733.7 | G96: 2006761.3 | H96: 2028788.8 | I96: 2050816.4 | J96: 2072844 | L96: =L95+0.02 -> 0.88 | M96: 2017086.3 | N96: 2017927.9 | O96: 2018769.6 | P96: 2019611.3 | Q96: 2020453 | R96: 2021294.7
D99: U.S Government Growth % | L99: International Government Growth %
D100: =FSM!I26 -> 1744867.7 | E100: 0.25 | F100: =E100+0.04 -> 0.29 | G100: =F100+0.04 -> 0.33 | H100: =G100+0.04 -> 0.37 | I100: =H100+0.04 -> 0.41 | J100: =I100+0.04 -> 0.45 | L100: =FSM!I26 -> 1744867.7 | M100: 0.23 | N100: =M100+0.03 -> 0.26 | O100: =N100+0.03 -> 0.29 | P100: =O100+0.03 -> 0.32 | Q100: =P100+0.03 -> 0.35 | R100: =Q100+0.03 -> 0.38
D101: 0.78 | E101: 1497695.8 | F101: 1514129.6 | G101: 1530563.5 | H101: 1546997.3 | I101: 1563431.2 | J101: 1579865 | L101: 0.78 | M101: 1527590.3 | N101: 1530848.6 | O101: 1534107 | P101: 1537365.3 | Q101: 1540623.7 | R101: 1543882.1
C102: Gross | D102: =D101+0.02 -> 0.8 | E102: 1592713.1 | F102: 1610324.4 | G102: 1627935.8 | H102: 1645547.1 | I102: 1663158.4 | J102: 1680769.8 | K102: Gross | L102: =L101+0.02 -> 0.8 | M102: 1624749.5 | N102: 1628241.3 | O102: 1631733.2 | P102: 1635225 | Q102: 1638716.8 | R102: 1642208.6
C103: margin | D103: =D102+0.02 -> 0.82 | E103: 1687730.4 | F103: 1706519.2 | G103: 1725308 | H103: 1744096.9 | I103: 1762885.7 | J103: 1781674.5 | K103: margin | L103: =L102+0.02 -> 0.82 | M103: 1721908.8 | N103: 1725634 | O103: 1729359.3 | P103: 1733084.6 | Q103: 1736809.9 | R103: 1740535.2
C104: % | D104: =D103+0.02 -> 0.84 | E104: 1782747.7 | F104: 1802714 | G104: 1822680.3 | H104: 1842646.6 | I104: 1862612.9 | J104: 1882579.2 | K104: % | L104: =L103+0.02 -> 0.84 | M104: 1819068 | N104: 1823026.7 | O104: 1826985.5 | P104: 1830944.2 | Q104: 1834903 | R104: 1838861.7
D105: =D104+0.02 -> 0.86 | E105: 1877765 | F105: 1898908.8 | G105: 1920052.6 | H105: 1941196.4 | I105: 1962340.2 | J105: 1983484 | L105: =L104+0.02 -> 0.86 | M105: 1916227.2 | N105: 1920419.5 | O105: 1924611.7 | P105: 1928803.9 | Q105: 1932996.1 | R105: 1937188.3
D106: =D105+0.02 -> 0.88 | E106: 1972782.3 | F106: 1995103.6 | G106: 2017424.9 | H106: 2039746.2 | I106: 2062067.4 | J106: 2084388.7 | L106: =L105+0.02 -> 0.88 | M106: 2013386.5 | N106: 2017812.2 | O106: 2022237.8 | P106: 2026663.5 | Q106: 2031089.2 | R106: 2035514.8

Sheet FSM
C2: Financial Statement Model
C3: $USD Thousand except per share data
C5: Circ Break 1 = off, 0 = on | D5: 1
C6: Latest Fiscal Year End Date | D6: 46022
C7: Shares Outstanding (thousands) | D7: 2391675.7
B9: x | C9: INCOME STATEMENT
C10: Fiscal Year | D10: 2021 | E10: 2022 | F10: 2023 | G10: 2024 | H10: 2025 | I10: 2026 | J10: 2027 | K10: 2028 | L10: 2029 | M10: 2030 | N10: 2031 | O10: 2032 | P10: 2033 | Q10: 2034 | R10: 2035
C11: End Date | D11: 44561 | E11: =EOMONTH(D11,12) -> 44926 | F11: =EOMONTH(E11,12) -> 45291 | G11: =EOMONTH(F11,12) -> 45657 | H11: =EOMONTH(G11,12) -> 46022 | I11: =EOMONTH(H11,12) -> 46387 | J11: =EOMONTH(I11,12) -> 46752 | K11: =EOMONTH(J11,12) -> 47118 | L11: =EOMONTH(K11,12) -> 47483 | ... R11: =EOMONTH(Q11,12) -> 49674
C13: Revenue | D13: 1541889 | E13: 1905871 | F13: 2225012 | G13: 2865507 | H13: 4475446 | I13: ='Rev Build'!I20 -> 6291682.6 | J13: ='Rev Build'!J20 -> 8831065 | K13: ='Rev Build'!K20 -> 12317716 | L13: ='Rev Build'!L20 -> 16996281 | M13: ='Rev Build'!M20 -> 23100508 | N13: ='Rev Build'!N20 -> 30802452 | O13: ='Rev Build'!O20 -> 40143726 | P13: ='Rev Build'!P20 -> 50957491 | ... R13: ='Rev Build'!R20 -> 74908933
C14: Cost of revenue | D14: -339404 | E14: -408549 | F14: -431105 | G14: -565990 | H14: -789177 | I14: =I15-I13 -> -1109442.8 | J14: =J15-J13 -> -1557224.3 | K14: =K15-K13 -> -2172042.3 | L14: =L15-L13 -> -2997036.3 | M14: =M15-M13 -> -4073424.1 | N14: =N15-N13 -> -5431545.1 | O14: =O15-O13 -> -7078737 | P14: =P15-P13 -> -8985580.4 | ... R14: =R15-R13 -> -13209054
C15: Gross profit | D15: =SUM(D13:D14) -> 1202485 | E15: =SUM(E13:E14) -> 1497322 | F15: =SUM(F13:F14) -> 1793907 | G15: =SUM(G13:G14) -> 2299517 | H15: =SUM(H13:H14) -> 3686269 | I15: =I13*I38 -> 5182239.8 | J15: =J13*J38 -> 7273840.6 | K15: =K13*K38 -> 10145673 | L15: =L13*L38 -> 13999245 | M15: =M13*M38 -> 19027084 | N15: =N13*N38 -> 25370907 | O15: =O13*O38 -> 33064989 | P15: =P13*P38 -> 41971911 | ... R15: =R13*R38 -> 61699879
C16: Sales and marketing | D16: -614512 | E16: -702511 | F16: -744992 | G16: -887755 | H16: -1056859 | I16: =I13*-I40 -> -1485756.1 | J16: =J13*-J40 -> -2041266 | K16: =K13*-K40 -> -2785603 | L16: =L13*-L40 -> -3758660.8 | M16: =M13*-M40 -> -4993084.1 | N16: =N13*-N40 -> -6503816.8 | O16: =O13*-O40 -> -8275471.5 | P16: =P13*-P40 -> -10249899 | ... R16: =R13*-R40 -> -14318548
C17: Research and development | D17: -387487 | E17: -359679 | F17: -404624 | G17: -507878 | H17: -557677 | I17: =I13*-I41 -> -783994.86 | J17: =J13*-J41 -> -1056267.3 | K17: =K13*-K41 -> -1411710.5 | L17: =L13*-L41 -> -1862930.8 | M17: =M13*-M41 -> -2416501.1 | N17: =N13*-N41 -> -3068174.9 | O17: =O13*-O41 -> -3797923.2 | P17: =P13*-P41 -> -4566206 | ... R17: =R13*-R41 -> -5963360.8
C18: General and administrative | D18: -611532 | E18: -596333 | F18: -524325 | G18: -593481 | H18: -657718 | I18: =I13*-I42 -> -924634.75 | J18: =J13*-J42 -> -1253670.7 | K18: =K13*-K42 -> -1687052.1 | L18: =L13*-L42 -> -2242853.8 | M18: =M13*-M42 -> -2932873.8 | N18: =N13*-N42 -> -3756711.5 | O18: =O13*-O42 -> -4695268.1 | P18: =P13*-P42 -> -5705274.2 | ... R18: =R13*-R42 -> -7637822.8
C19: Operating income (EBIT) | D19: =SUM(D15:D18) -> -411046 | E19: =SUM(E15:E18) -> -161201 | F19: =SUM(F15:F18) -> 119966 | G19: =SUM(G15:G18) -> 310403 | H19: =SUM(H15:H18) -> 1414015 | I19: =SUM(I15:I18) -> 1987854.1 | J19: =SUM(J15:J18) -> 2922636.7 | K19: =SUM(K15:K18) -> 4261307.8 | ... R19: =SUM(R15:R18) -> 33780147
C20: Interest income | D20: 1607 | E20: 20309 | F20: 132572 | G20: 196792 | H20: 229181 | I20: =I247 -> 268401.55 | J20: =J247 -> 365371.2 | K20: =K247 -> 506754.02 | L20: =L247 -> 710403.03 | M20: =M247 -> 999095.58 | N20: =N247 -> 1402492.8 | O20: =O247 -> 1953579.4 | P20: =P247 -> 2685409.1 | ... R20: =R247 -> 4816021.1
C21: Other income (expense), net | D21: =-75415-3640 -> -79055 | E21: =-216077-4058 -> -220135 | F21: =-11977-3470 -> -15447 | G21: -18022 | H21: 14172 | I21: =I13*I44 -> 19923.316 | J21: =J13*J44 -> 27964.554 | K21: =K13*K44 -> 39005.423 | L21: =L13*L44 -> 53820.624 | M21: =M13*M44 -> 73150.34 | N21: =N13*N44 -> 97539.407 | O21: =O13*O44 -> 127119.6 | P21: =P13*P44 -> 161362.59 | ... R21: =R13*R44 -> 237207.51
C22: Income before provision for income taxes | D22: =SUM(D19:D21) -> -488494 | E22: =SUM(E19:E21) -> -361027 | F22: =SUM(F19:F21) -> 237091 | G22: =SUM(G19:G21) -> 489173 | H22: =SUM(H19:H21) -> 1657368 | I22: =SUM(I19:I21) -> 2276178.9 | J22: =SUM(J19:J21) -> 3315972.4 | K22: =SUM(K19:K21) -> 4807067.2 | ... R22: =SUM(R19:R21) -> 38833376
C23: Provision for income taxes | D23: -31885 | E23: -10067 | F23: -19716 | G23: -21255 | H23: -22724 | I23: =I22*-I45 -> -521700.21 | J23: =J22*-J45 -> -758694.49 | K23: =K22*-K45 -> -1084955.1 | L23: =L22*-L45 -> -1517785.1 | M23: =M22*-M45 -> -2146511.5 | N23: =N22*-N45 -> -2843869.6 | O23: =O22*-O45 -> -3859175.3 | P23: =P22*-P45 -> -5102433.6 | ... R23: =R22*-R45 -> -8155008.9
C24: Net income | D24: =SUM(D22:D23) -> -520379 | E24: =SUM(E22:E23) -> -371094 | F24: =SUM(F22:F23) -> 217375 | G24: =SUM(G22:G23) -> 467918 | H24: =SUM(H22:H23) -> 1634644 | I24: =SUM(I22:I23) -> 1754478.7 | J24: =SUM(J22:J23) -> 2557277.9 | K24: =SUM(K22:K23) -> 3722112.1 | ... R24: =SUM(R22:R23) -> 30678367
C25: Less: Net income attributable to noncontrolling interests | D25: 0 | E25: -2611 | F25: -7550 | G25: -5728 | H25: -9611 | I25: =H25 -> -9611 | J25: =I25 -> -9611 | K25: =J25 -> -9611 | L25: =K25 -> -9611 | M25: =L25 -> -9611 | N25: =M25 -> -9611 | O25: =N25 -> -9611 | P25: =O25 -> -9611 | ... R25: =Q25 -> -9611
C26: Net income attributable to common stockholders | D26: =SUM(D24:D25) -> -520379 | E26: =SUM(E24:E25) -> -373705 | F26: =SUM(F24:F25) -> 209825 | G26: =SUM(G24:G25) -> 462190 | H26: =SUM(H24:H25) -> 1625033 | I26: =SUM(I24:I25) -> 1744867.7 | J26: =SUM(J24:J25) -> 2547666.9 | K26: =SUM(K24:K25) -> 3712501.1 | ... R26: =SUM(R24:R25) -> 30668756
C28: Basic EPS | D28: -0.27 | E28: -0.18 | F28: 0.1 | G28: 0.21 | H28: 0.69 | I28: =I266 -> 0.72879866 | J28: =J266 -> 1.0636408 | K28: =K266 -> 1.5490193 | L28: =L266 -> 2.2394824 | M28: =M266 -> 3.1655402 | N28: =N266 -> 4.4458652 | O28: =O266 -> 6.0251609 | P28: =P266 -> 7.9533215 | ... R28: =R266 -> 12.664744
C29: Diluted EPS | D29: -0.27 | E29: -0.18 | F29: 0.09 | G29: 0.19 | H29: 0.63 | I29: =I269 -> 0.67375789 | J29: =J269 -> 0.98334487 | K29: =K269 -> 1.4321465 | L29: =L269 -> 2.0706399 | M29: =M269 -> 2.9271076 | N29: =N269 -> 4.1113975 | O29: =O269 -> 5.5725322 | P29: =P269 -> 7.3568263 | ... R29: =R269 -> 11.718289
C31: Depreciation and amortization | D31: 14897 | E31: 22522 | F31: 33354 | G31: 31587 | H31: 26145 | I31: =I210 -> 25239.136 | J31: =J210 -> 33966.268 | K31: =K210 -> 48413.422 | L31: =L210 -> 69840.69 | M31: =M210 -> 99829.69 | N31: =N210 -> 140141.99 | O31: =O210 -> 192491.29 | P31: =P210 -> 257089.08 | ... R31: =R210 -> 414205.03
C32: EBITDA | D32: =D19+D31 -> -396149 | E32: =E19+E31 -> -138679 | F32: =F19+F31 -> 153320 | G32: =G19+G31 -> 341990 | H32: =H19+H31 -> 1440160 | I32: =I19+I31 -> 2013093.2 | J32: =J19+J31 -> 2956602.9 | K32: =K19+K31 -> 4309721.2 | ... R32: =R19+R31 -> 34194352
C33: Stock-based compensation | D33: 778215 | E33: 564798 | F33: 475903 | G33: 691638 | H33: 684033 | I33: =H33*(1+I37) -> 961628.97 | J33: =I33*(1+J37) -> 1349751.5 | K33: =J33*(1+K37) -> 1882655.7 | L33: =K33*(1+L37) -> 2597733.8 | M33: =L33*(1+M37) -> 3530711.7 | N33: =M33*(1+N37) -> 4707886.9 | O33: =N33*(1+O37) -> 6135619.4 | P33: =O33*(1+P37) -> 7788409.3 | ... R33: =Q33*(1+R37) -> 11449179
C34: Adjusted EBITDA | D34: =D32+D33 -> 382066 | E34: =E32+E33 -> 426119 | F34: =F32+F33 -> 629223 | G34: =G32+G33 -> 1033628 | H34: =H32+H33 -> 2124193 | I34: =I32+I33 -> 2974722.2 | J34: =J32+J33 -> 4306354.4 | K34: =K32+K33 -> 6192376.9 | ... R34: =R32+R33 -> 45643531
C36: Growth rates and margins
C37: Revenue growth % | E37: ='Rev Build'!E21 -> 0.23606239 | F37: ='Rev Build'!F21 -> 0.16745152 | G37: ='Rev Build'!G21 -> 0.28786137 | H37: ='Rev Build'!H21 -> 0.56183391 | I37: ='Rev Build'!I21 -> 0.40582248 | J37: ='Rev Build'!J21 -> 0.40360942 | K37: ='Rev Build'!K21 -> 0.39481656 | L37: ='Rev Build'!L21 -> 0.37982412 | ... R37: ='Rev Build'!R21 -> 0.19283929
C38: Gross margin % | D38: =D15/D13 -> 0.7798778 | E38: =E15/E13 -> 0.78563659 | F38: =F15/F13 -> 0.80624599 | G38: =G15/G13 -> 0.80248172 | H38: =H15/H13 -> 0.82366517 | I38: ='Rev Build'!I33 -> 0.82366517 | J38: ='Rev Build'!J33 -> 0.82366517 | K38: ='Rev Build'!K33 -> 0.82366517 | L38: ='Rev Build'!L33 -> 0.82366517 | M38: ='Rev Build'!M33 -> 0.82366517 | N38: ='Rev Build'!N33 -> 0.82366517 | O38: ='Rev Build'!O33 -> 0.82366517 | P38: ='Rev Build'!P33 -> 0.82366517 | ... R38: ='Rev Build'!R33 -> 0.82366517
C40: Sales & marketing % of sales | D40: =-D16/D13 -> 0.3985449 | E40: =-E16/E13 -> 0.36860365 | F40: =-F16/F13 -> 0.33482606 | G40: =-G16/G13 -> 0.3098073 | H40: =-H16/H13 -> 0.23614607 | I40: ='Rev Build'!I34 -> 0.23614607 | J40: ='Rev Build'!J34 -> 0.23114607 | K40: ='Rev Build'!K34 -> 0.22614607 | L40: ='Rev Build'!L34 -> 0.22114607 | M40: ='Rev Build'!M34 -> 0.21614607 | N40: ='Rev Build'!N34 -> 0.21114607 | O40: ='Rev Build'!O34 -> 0.20614607 | P40: ='Rev Build'!P34 -> 0.20114607 | ... R40: ='Rev Build'!R34 -> 0.19114607
C41: Research & development % of sales | D41: =-D17/D13 -> 0.25130668 | E41: =-E17/E13 -> 0.18872159 | F41: =-F17/F13 -> 0.1818525 | G41: =-G17/G13 -> 0.17723844 | H41: =-H17/H13 -> 0.12460814 | I41: ='Rev Build'!I35 -> 0.12460814 | J41: ='Rev Build'!J35 -> 0.11960814 | K41: ='Rev Build'!K35 -> 0.11460814 | L41: ='Rev Build'!L35 -> 0.10960814 | M41: ='Rev Build'!M35 -> 0.10460814 | N41: ='Rev Build'!N35 -> 0.09960814 | O41: ='Rev Build'!O35 -> 0.09460814 | P41: ='Rev Build'!P35 -> 0.08960814 | ... R41: ='Rev Build'!R35 -> 0.07960814
C42: General & administrative % of sales | D42: =-D18/D13 -> 0.39661221 | E42: =-E18/E13 -> 0.31289264 | F42: =-F18/F13 -> 0.23565041 | G42: =-G18/G13 -> 0.20711204 | H42: =-H18/H13 -> 0.14696144 | I42: ='Rev Build'!I36 -> 0.14696144 | J42: ='Rev Build'!J36 -> 0.14196144 | K42: ='Rev Build'!K36 -> 0.13696144 | L42: ='Rev Build'!L36 -> 0.13196144 | M42: ='Rev Build'!M36 -> 0.12696144 | N42: ='Rev Build'!N36 -> 0.12196144 | O42: ='Rev Build'!O36 -> 0.11696144 | P42: ='Rev Build'!P36 -> 0.11196144 | ... R42: ='Rev Build'!R36 -> 0.10196144
C44: Other income % of sales | D44: =D21/D13 -> -0.051271525 | E44: =E21/E13 -> -0.11550362 | F44: =F21/F13 -> -0.0069424345 | G44: =G21/G13 -> -0.0062892884 | H44: =H21/H13 -> 0.0031666118 | I44: ='Rev Build'!I37 -> 0.0031666118 | J44: ='Rev Build'!J37 -> 0.0031666118 | K44: ='Rev Build'!K37 -> 0.0031666118 | L44: ='Rev Build'!L37 -> 0.0031666118 | M44: ='Rev Build'!M37 -> 0.0031666118 | N44: ='Rev Build'!N37 -> 0.0031666118 | O44: ='Rev Build'!O37 -> 0.0031666118 | P44: ='Rev Build'!P37 -> 0.0031666118 | ... R44: ='Rev Build'!R37 -> 0.0031666118
C45: Effective Tax Rate | D45: =-D23/D22 -> -0.06527204 | E45: =-E23/E22 -> -0.027884341 | F45: =-F23/F22 -> 0.083157944 | G45: =-G23/G22 -> 0.043450885 | H45: =-H23/H22 -> 0.013710896 | I45: 0.2292 | J45: 0.2288 | K45: 0.2257 | L45: 0.22 | M45: 0.22 | N45: 0.21 | O45: 0.21 | P45: 0.21 | Q45: 0.21 | R45: 0.21
B48: x | C48: BALANCE SHEET
C49: Fiscal Year | D49: 2021 | E49: 2022 | F49: 2023 | G49: 2024 | H49: 2025 | I49: 2026 | J49: 2027 | K49: 2028 | L49: 2029 | M49: 2030 | N49: 2031 | O49: 2032 | P49: 2033 | Q49: 2034 | R49: 2035
C50: End Date | D50: 44561 | E50: =EOMONTH(D50,12) -> 44926 | F50: =EOMONTH(E50,12) -> 45291 | G50: =EOMONTH(F50,12) -> 45657 | H50: =EOMONTH(G50,12) -> 46022 | I50: =EOMONTH(H50,12) -> 46387 | J50: =EOMONTH(I50,12) -> 46752 | K50: =EOMONTH(J50,12) -> 47118 | L50: =EOMONTH(K50,12) -> 47483 | ... R50: =EOMONTH(Q50,12) -> 49674
C52: Cash & cash equivalents and marketable securities | D52: 2601067 | E52: 2633675 | F52: 3674179 | G52: 5229987 | H52: 7177043 | I52: =I108 -> 9633508.4 | J52: =J108 -> 13250455 | K52: =K108 -> 18488610 | L52: =L108 -> 26005419 | M52: =M108 -> 36570029 | N52: =N108 -> 51271034 | O52: =O108 -> 71085734 | P52: =P108 -> 97107060 | ... R52: =R108 -> 1.7133542e+08
C53: Accounts receivable, net | D53: 190923 | E53: 258346 | F53: 364784 | G53: 575048 | H53: 1042065 | I53: =I118 -> 1464958.4 | J53: =J118 -> 2056229.4 | K53: =K118 -> 2868062.8 | L53: =L118 -> 3957422.3 | M53: =M118 -> 5378733.4 | N53: =N118 -> 7172057.7 | O53: =O118 -> 9347084.5 | P53: =P118 -> 11864967 | ... R53: =R118 -> 17441832
C54: Prepaid expenses and other current assets | D54: 110872 | E54: 149556 | F54: 99655 | G54: 129254 | H54: 139066 | I54: =I128 -> 195502.11 | J54: =J128 -> 274408.6 | K54: =K128 -> 382749.66 | L54: =L128 -> 528127.22 | M54: =M128 -> 717804.49 | N54: =N128 -> 957127.8 | O54: =O128 -> 1247390.2 | P54: =P128 -> 1583407.4 | ... R54: =R128 -> 2327653.1
C55: Property and equipment, net | D55: 31304 | E55: 69170 | F55: 47758 | G55: 39638 | H55: 51960 | I55: =I183 -> 80798.638 | J55: =J183 -> 122736.44 | K55: =K183 -> 180195.28 | L55: =L183 -> 256439.68 | M55: =M183 -> 355161.65 | N55: =N183 -> 479770.46 | O55: =O183 -> 632319.36 | P55: =P183 -> 813216.09 | ... R55: =R183 -> 1252292.2
C56: Operating lease ROU assets | D56: 216898 | E56: 200240 | F56: 182863 | G56: 200740 | H56: 200105 | I56: =I64 -> 167259 | J56: =J64 -> 116831 | K56: =K64 -> 87276 | L56: =L64 -> 62333 | M56: =M64 -> 29014 | N56: =N64 -> 0 | O56: =O64 -> 0 | P56: =P64 -> 0 | ... R56: =R64 -> 0
C57: Other assets | D57: 96386 | E57: 150252 | F57: 153186 | G57: 166217 | H57: 290153 | I57: =H57*(1+I37) -> 407903.61 | J57: =I57*(1+J37) -> 572537.35 | K57: =J57*(1+K37) -> 798584.58 | L57: =K57*(1+L37) -> 1101906.3 | M57: =L57*(1+M37) -> 1497656.7 | N57: =M57*(1+N37) -> 1996990.7 | O57: =N57*(1+O37) -> 2602606 | P57: =O57*(1+P37) -> 3303686.1 | ... R57: =Q57*(1+R37) -> 4856510.7
C58: Total assets | D58: =SUM(D52:D57) -> 3247450 | E58: =SUM(E52:E57) -> 3461239 | F58: =SUM(F52:F57) -> 4522425 | G58: =SUM(G52:G57) -> 6340884 | H58: =SUM(H52:H57) -> 8900392 | I58: =SUM(I52:I57) -> 11949930 | J58: =SUM(J52:J57) -> 16393198 | K58: =SUM(K52:K57) -> 22805479 | ... R58: =SUM(R52:R57) -> 1.9721371e+08
C60: Accounts payable | D60: 74907 | E60: 44788 | F60: 12122 | G60: 103 | H60: 8064 | I60: =I138 -> 11336.552 | J60: =J138 -> 15912.092 | K60: =K138 -> 22194.449 | L60: =L138 -> 30624.436 | M60: =M138 -> 41623.225 | N60: =N138 -> 55500.831 | O60: =O138 -> 72332.234 | P60: =P138 -> 91816.817 | ... R60: =R138 -> 134973.28
C61: Accrued liabilities | D61: 155806 | E61: 172715 | F61: 222991 | G61: 427046 | H61: 355624 | I61: =I148 -> 499944.21 | J61: =J148 -> 701726.41 | K61: =K148 -> 978779.61 | L61: =L148 -> 1350543.7 | M61: =M148 -> 1835592.5 | N61: =N148 -> 2447597.7 | O61: =O148 -> 3189865.9 | P61: =P148 -> 4049139.8 | ... R61: =R148 -> 5952348.5
C62: Deferred revenue | D62: 268033 | E62: 193315 | F62: 274948 | G62: 299509 | H62: 455179 | I62: =I158 -> 639900.87 | J62: =J158 -> 898170.89 | K62: =K158 -> 1252783.6 | L62: =L158 -> 1728621.1 | M62: =M158 -> 2349456.6 | N62: =N158 -> 3132789.3 | O62: =O158 -> 4082851.4 | P62: =P158 -> 5182674.5 | ... R62: =R158 -> 7618676
C63: Customer deposits | D63: 195304 | E63: 145925 | F63: 211305 | G63: 266915 | H63: 357084 | I63: =I168 -> 501996.71 | J63: =J168 -> 704607.32 | K63: =K168 -> 982797.95 | L63: =L168 -> 1356088.3 | M63: =M168 -> 1843128.4 | N63: =N168 -> 2457646.2 | O63: =O168 -> 3202961.7 | P63: =P168 -> 4065763.4 | ... R63: =R168 -> 5976785.6
C64: Operating lease liabilities | D64: 260073 | E64: 249404 | F64: 229392 | G64: 239219 | H64: 229338 | I64: 167259 | J64: 116831 | K64: 87276 | L64: 62333 | M64: 29014 | N64: 0 | O64: 0 | P64: 0 | Q64: 0 | R64: 0
C65: Debt revolver | D65: 0 | E65: 0 | F65: 0 | G65: 0 | H65: 0 | I65: =I236 -> 0 | J65: =J236 -> 0 | K65: =K236 -> 0 | L65: =L236 -> 0 | M65: =M236 -> 0 | N65: =N236 -> 0 | O65: =O236 -> 0 | P65: =P236 -> 0 | ... R65: =R236 -> 0
C66: Other non-current liabilities | D66: 2297 | E66: 12655 | F66: 10702 | G66: 13685 | H66: 7092 | I66: =H66*(1+I37) -> 9970.093 | J66: =I66*(1+J37) -> 13994.117 | K66: =J66*(1+K37) -> 19519.225 | L66: =K66*(1+L37) -> 26933.098 | M66: =L66*(1+M37) -> 36606.14 | N66: =M66*(1+N37) -> 48810.999 | O66: =N66*(1+O37) -> 63613.616 | P66: =O66*(1+P37) -> 80749.611 | ... R66: =Q66*(1+R37) -> 118704.18
C67: Total liabilities | D67: =SUM(D60:D66) -> 956420 | E67: =SUM(E60:E66) -> 818802 | F67: =SUM(F60:F66) -> 961460 | G67: =SUM(G60:G66) -> 1246477 | H67: =SUM(H60:H66) -> 1412381 | I67: =SUM(I60:I66) -> 1830407.4 | J67: =SUM(J60:J66) -> 2451241.8 | K67: =SUM(K60:K66) -> 3343350.9 | ... R67: =SUM(R60:R66) -> 19801488
C69: Common stock | D69: 7779112 | E69: 8430097 | F69: 9124373 | G69: 10196309 | H69: 10935716 | I69: =H69+I33 -> 11897345 | J69: =I69+J33 -> 13247096 | K69: =J69+K33 -> 15129752 | L69: =K69+L33 -> 17727486 | M69: =L69+M33 -> 21258198 | N69: =M69+N33 -> 25966085 | O69: =N69+O33 -> 32101704 | P69: =O69+P33 -> 39890113 | ... R69: =Q69+R33 -> 60937550
C70: Accumulated other comprehensive income | D70: -2349 | E70: -5333 | F70: 801 | G70: -5611 | H70: 13942 | I70: =H70 -> 13942 | J70: =I70 -> 13942 | K70: =J70 -> 13942 | L70: =K70 -> 13942 | M70: =L70 -> 13942 | N70: =M70 -> 13942 | O70: =N70 -> 13942 | P70: =O70 -> 13942 | ... R70: =Q70 -> 13942
C71: Retained earnings | D71: -5485733 | E71: -5859438 | F71: -5649613 | G71: -5187423 | H71: -3562390 | I71: =I257 -> -1892507.3 | J71: =J257 -> 580174.67 | K71: =K257 -> 4217690.8 | L71: =L257 -> 9514332.8 | M71: =M257 -> 17040096 | N71: =N257 -> 27653866 | O71: =O257 -> 42087120 | P71: =P257 -> 61197393 | ... R71: =R257 -> 1.1635999e+08
C72: Total Palantir's equity | D72: =SUM(D69:D71) -> 2291030 | E72: =SUM(E69:E71) -> 2565326 | F72: =SUM(F69:F71) -> 3475561 | G72: =SUM(G69:G71) -> 5003275 | H72: =SUM(H69:H71) -> 7387268 | I72: =SUM(I69:I71) -> 10018780 | J72: =SUM(J69:J71) -> 13841213 | K72: =SUM(K69:K71) -> 19361385 | ... R72: =SUM(R69:R71) -> 1.7731148e+08
C73: Noncontrolling interests | D73: 0 | E73: 77111 | F73: 85404 | G73: 91132 | H73: 100743 | I73: =H73 -> 100743 | J73: =I73 -> 100743 | K73: =J73 -> 100743 | L73: =K73 -> 100743 | M73: =L73 -> 100743 | N73: =M73 -> 100743 | O73: =N73 -> 100743 | P73: =O73 -> 100743 | ... R73: =Q73 -> 100743
C74: Total equity | D74: =SUM(D72:D73) -> 2291030 | E74: =SUM(E72:E73) -> 2642437 | F74: =SUM(F72:F73) -> 3560965 | G74: =SUM(G72:G73) -> 5094407 | H74: =SUM(H72:H73) -> 7488011 | I74: =SUM(I72:I73) -> 10119523 | J74: =SUM(J72:J73) -> 13941956 | K74: =SUM(K72:K73) -> 19462128 | ... R74: =SUM(R72:R73) -> 1.7741222e+08
C76: Balance check | D76: =D58-D67-D74 -> 0 | E76: =E58-E67-E74 -> 0 | F76: =F58-F67-F74 -> 0 | G76: =G58-G67-G74 -> 0 | H76: =H58-H67-H74 -> 0 | I76: =I58-I67-I74 -> 0 | J76: =J58-J67-J74 -> 0 | K76: =K58-K67-K74 -> 0 | ... R76: =R58-R67-R74 -> 0
B79: x | C79: CASH FLOW STATEMENT
C80: Fiscal Year | D80: 2021 | E80: 2022 | F80: 2023 | G80: 2024 | H80: 2025 | I80: 2026 | J80: 2027 | K80: 2028 | L80: 2029 | M80: 2030 | N80: 2031 | O80: 2032 | P80: 2033 | Q80: 2034 | R80: 2035
C81: End Date | D81: 44561 | E81: =EOMONTH(D81,12) -> 44926 | F81: =EOMONTH(E81,12) -> 45291 | G81: =EOMONTH(F81,12) -> 45657 | H81: =EOMONTH(G81,12) -> 46022 | I81: =EOMONTH(H81,12) -> 46387 | J81: =EOMONTH(I81,12) -> 46752 | K81: =EOMONTH(J81,12) -> 47118 | L81: =EOMONTH(K81,12) -> 47483 | ... R81: =EOMONTH(Q81,12) -> 49674
C83: Net income | I83: =I26 -> 1744867.7 | J83: =J26 -> 2547666.9 | K83: =K26 -> 3712501.1 | L83: =L26 -> 5371627 | M83: =M26 -> 7600748.1 | N83: =N26 -> 10688755 | O83: =O26 -> 14508239 | P83: =P26 -> 19185258 | ... R83: =R26 -> 30668756
C84: Depreciation and amortization | I84: =I210 -> 25239.136 | J84: =J210 -> 33966.268 | K84: =K210 -> 48413.422 | L84: =L210 -> 69840.69 | M84: =M210 -> 99829.69 | N84: =N210 -> 140141.99 | O84: =O210 -> 192491.29 | P84: =P210 -> 257089.08 | ... R84: =R210 -> 414205.03
C85: Stock-based compensation | I85: =I33 -> 961628.97 | J85: =J33 -> 1349751.5 | K85: =K33 -> 1882655.7 | L85: =L33 -> 2597733.8 | M85: =M33 -> 3530711.7 | N85: =N33 -> 4707886.9 | O85: =O33 -> 6135619.4 | P85: =P33 -> 7788409.3 | ... R85: =R33 -> 11449179
C86: Changes in working capital:
C87: Accounts receivable, net | I87: =H53-I53 -> -422893.4 | J87: =I53-J53 -> -591271.01 | K87: =J53-K53 -> -811833.42 | L87: =K53-L53 -> -1089359.4 | M87: =L53-M53 -> -1421311.1 | N87: =M53-N53 -> -1793324.4 | O87: =N53-O53 -> -2175026.7 | P87: =O53-P53 -> -2517882.2 | ... R87: =Q53-R53 -> -2819718.1
C88: Prepaid expenses and other current assets | I88: =H54-I54 -> -56436.109 | J88: =I54-J54 -> -78906.493 | K88: =J54-K54 -> -108341.06 | L88: =K54-L54 -> -145377.55 | M88: =L54-M54 -> -189677.27 | N88: =M54-N54 -> -239323.31 | O88: =N54-O54 -> -290262.38 | P88: =O54-P54 -> -336017.24 | ... R88: =Q54-R54 -> -376297.94
C89: Accounts payable | I89: =I60-H60 -> 3272.5525 | J89: =J60-I60 -> 4575.5394 | K89: =K60-J60 -> 6282.3574 | L89: =L60-K60 -> 8429.9871 | M89: =M60-L60 -> 10998.789 | N89: =N60-M60 -> 13877.606 | O89: =O60-N60 -> 16831.403 | P89: =P60-O60 -> 19484.583 | ... R89: =R60-Q60 -> 21820.334
C90: Accrued liabilities | I90: =I61-H61 -> 144320.21 | J90: =J61-I61 -> 201782.2 | K90: =K61-J61 -> 277053.21 | L90: =L61-K61 -> 371764.1 | M90: =M61-L61 -> 485048.76 | N90: =N61-M61 -> 612005.19 | O90: =O61-N61 -> 742268.19 | P90: =P61-O61 -> 859273.99 | ... R90: =R61-Q61 -> 962281.08
C91: Deferred Revenue | I91: =I62-H62 -> 184721.87 | J91: =J62-I62 -> 258270.02 | K91: =K62-J62 -> 354612.74 | L91: =L62-K62 -> 475837.44 | M91: =M62-L62 -> 620835.51 | N91: =N62-M62 -> 783332.71 | O91: =O62-N62 -> 950062.13 | P91: =P62-O62 -> 1099823.1 | ... R91: =R62-Q62 -> 1231666.4
C92: Customer Deposits | I92: =I63-H63 -> 144912.71 | J92: =J63-I63 -> 202610.6 | K92: =K63-J63 -> 278190.64 | L92: =L63-K63 -> 373290.37 | M92: =M63-L63 -> 487040.1 | N92: =N63-M63 -> 614517.75 | O92: =O63-N63 -> 745315.55 | P92: =P63-O63 -> 862801.7 | ... R92: =R63-Q63 -> 966231.68
C93: Operating ROU assets | I93: =H56-I56 -> 32846 | J93: =I56-J56 -> 50428 | K93: =J56-K56 -> 29555 | L93: =K56-L56 -> 24943 | M93: =L56-M56 -> 33319 | N93: =M56-N56 -> 29014 | O93: =N56-O56 -> 0 | P93: =O56-P56 -> 0 | ... R93: =Q56-R56 -> 0
C94: Other assets | I94: =-I219 -> -124196.31 | J94: =-J219 -> -173680.98 | K94: =-K219 -> -238666.47 | L94: =-L219 -> -320734.01 | M94: =-M219 -> -419416.42 | N94: =-N219 -> -530890.43 | O94: =-O219 -> -646741.72 | P94: =-P219 -> -753285.02 | ... R94: =-R219 -> -861866.07
C95: Operating lease liabilities | I95: =I64-H64 -> -62079 | J95: =J64-I64 -> -50428 | K95: =K64-J64 -> -29555 | L95: =L64-K64 -> -24943 | M95: =M64-L64 -> -33319 | N95: =N64-M64 -> -29014 | O95: =O64-N64 -> 0 | P95: =P64-O64 -> 0 | ... R95: =R64-Q64 -> 0
C96: Other non-current liabilities | I96: =I66-H66 -> 2878.093 | J96: =J66-I66 -> 4024.0235 | K96: =K66-J66 -> 5525.1089 | L96: =L66-K66 -> 7413.8726 | M96: =M66-L66 -> 9673.0417 | N96: =N66-M66 -> 12204.859 | O96: =O66-N66 -> 14802.617 | P96: =P66-O66 -> 17135.995 | ... R96: =R66-Q66 -> 19190.205
C97: Cash flows from operating activities | I97: =SUM(I83:I96) -> 2579082.5 | J97: =SUM(J83:J96) -> 3758788.6 | K97: =SUM(K83:K96) -> 5406393.4 | L97: =SUM(L83:L96) -> 7720466.2 | M97: =SUM(M83:M96) -> 10814481 | N97: =SUM(N83:N96) -> 15009184 | O97: =SUM(O83:O96) -> 20193599 | P97: =SUM(P83:P96) -> 26482091 | ... R97: =SUM(R83:R96) -> 41675447
C99: Capital Expenditures | I99: =-I181 -> -47632.077 | J99: =-J181 -> -66856.832 | K99: =-K181 -> -93253.017 | L99: =-L181 -> -128672.76 | M99: =-M181 -> -174885.68 | N99: =-N181 -> -233194.34 | O99: =-O181 -> -303913.78 | P99: =-P181 -> -385780.93 | ... R99: =-R181 -> -567108.72
C100: Cash flows from investing activities | I100: =SUM(I99) -> -47632.077 | J100: =SUM(J99) -> -66856.832 | K100: =SUM(K99) -> -93253.017 | L100: =SUM(L99) -> -128672.76 | M100: =SUM(M99) -> -174885.68 | N100: =SUM(N99) -> -233194.34 | O100: =SUM(O99) -> -303913.78 | P100: =SUM(P99) -> -385780.93 | ... R100: =SUM(R99) -> -567108.72
C102: Debt revolver | I102: =I236 -> 0 | J102: =J236 -> 0 | K102: =K236 -> 0 | L102: =L236 -> 0 | M102: =M236 -> 0 | N102: =N236 -> 0 | O102: =O236 -> 0 | P102: =P236 -> 0 | ... R102: =R236 -> 0
C103: Share repurchases | I103: =I256 -> -74985 | J103: =J256 -> -74985 | K103: =K256 -> -74985 | L103: =L256 -> -74985 | M103: =M256 -> -74985 | N103: =N256 -> -74985 | O103: =O256 -> -74985 | P103: =P256 -> -74985 | ... R103: =R256 -> -74985
C104: Cash flows from financing activities | I104: =SUM(I102:I103) -> -74985 | J104: =SUM(J102:J103) -> -74985 | K104: =SUM(K102:K103) -> -74985 | L104: =SUM(L102:L103) -> -74985 | M104: =SUM(M102:M103) -> -74985 | N104: =SUM(N102:N103) -> -74985 | O104: =SUM(O102:O103) -> -74985 | P104: =SUM(P102:P103) -> -74985 | ... R104: =SUM(R102:R103) -> -74985
C106: Net change in cash | I106: =I97+I100+I104 -> 2456465.4 | J106: =J97+J100+J104 -> 3616946.8 | K106: =K97+K100+K104 -> 5238155.4 | L106: =L97+L100+L104 -> 7516808.5 | M106: =M97+M100+M104 -> 10564610 | N106: =N97+N100+N104 -> 14701005 | O106: =O97+O100+O104 -> 19814700 | P106: =P97+P100+P104 -> 26021326 | ... R106: =R97+R100+R104 -> 41033354
C107: Beginning of period cash | I107: =H52 -> 7177043 | J107: =I52 -> 9633508.4 | K107: =J52 -> 13250455 | L107: =K52 -> 18488610 | M107: =L52 -> 26005419 | N107: =M52 -> 36570029 | O107: =N52 -> 51271034 | P107: =O52 -> 71085734 | ... R107: =Q52 -> 1.3030207e+08
C108: Ending of period cash | I108: =SUM(I106:I107) -> 9633508.4 | J108: =SUM(J106:J107) -> 13250455 | K108: =SUM(K106:K107) -> 18488610 | L108: =SUM(L106:L107) -> 26005419 | M108: =SUM(M106:M107) -> 36570029 | N108: =SUM(N106:N107) -> 51271034 | O108: =SUM(O106:O107) -> 71085734 | P108: =SUM(P106:P107) -> 97107060 | ... R108: =SUM(R106:R107) -> 1.7133542e+08
B111: x | C111: Working Capital
C112: Fiscal Year | D112: 2021 | E112: 2022 | F112: 2023 | G112: 2024 | H112: 2025 | I112: 2026 | J112: 2027 | K112: 2028 | L112: 2029 | M112: 2030 | N112: 2031 | O112: 2032 | P112: 2033 | Q112: 2034 | R112: 2035
C113: End Date | D113: 44561 | E113: =EOMONTH(D113,12) -> 44926 | F113: =EOMONTH(E113,12) -> 45291 | G113: =EOMONTH(F113,12) -> 45657 | H113: =EOMONTH(G113,12) -> 46022 | I113: =EOMONTH(H113,12) -> 46387 | J113: =EOMONTH(I113,12) -> 46752 | K113: =EOMONTH(J113,12) -> 47118 | L113: =EOMONTH(K113,12) -> 47483 | ... R113: =EOMONTH(Q113,12) -> 49674
C115: Accounts receivable, net
C116: Beginning of period | E116: =D118 -> 190923 | F116: =E118 -> 258346 | G116: =F118 -> 364784 | H116: =G118 -> 575048 | I116: =H118 -> 1042065 | J116: =I118 -> 1464958.4 | K116: =J118 -> 2056229.4 | L116: =K118 -> 2868062.8 | ... R116: =Q118 -> 14622114
C117: Increase/Decrease | E117: =E118-E116 -> 67423 | F117: =F118-F116 -> 106438 | G117: =G118-G116 -> 210264 | H117: =H118-H116 -> 467017 | I117: =I118-I116 -> 422893.4 | J117: =J118-J116 -> 591271.01 | K117: =K118-K116 -> 811833.42 | L117: =L118-L116 -> 1089359.4 | ... R117: =R118-R116 -> 2819718.1
C118: End of period | D118: =D53 -> 190923 | E118: =E53 -> 258346 | F118: =F53 -> 364784 | G118: =G53 -> 575048 | H118: =H53 -> 1042065 | I118: =IF($D$120=1,H118*(1+I122),2*I13*I123/365-I116) -> 1464958.4 | J118: =IF($D$120=1,I118*(1+J122),2*J13*J123/365-J116) -> 2056229.4 | K118: =IF($D$120=1,J118*(1+K122),2*K13*K123/365-K116) -> 2868062.8 | L118: =IF($D$120=1,K118*(1+L122),2*L13*L123/365-L116) -> 3957422.3 | M118: =IF($D$120=1,L118*(1+M122),2*M13*M123/365-M116) -> 5378733.4 | N118: =IF($D$120=1,M118*(1+N122),2*N13*N123/365-N116) -> 7172057.7 | O118: =IF($D$120=1,N118*(1+O122),2*O13*O123/365-O116) -> 9347084.5 | P118: =IF($D$120=1,O118*(1+P122),2*P13*P123/365-P116) -> 11864967 | ... R118: =IF($D$120=1,Q118*(1+R122),2*R13*R123/365-R116) -> 17441832
C120: A/R forecasting approach (1=grow with rev, 2=DSO) | D120: 1
C122: Grow in line with revenue (1) | E122: =E37 -> 0.23606239 | F122: =F37 -> 0.16745152 | G122: =G37 -> 0.28786137 | H122: =H37 -> 0.56183391 | I122: =I37 -> 0.40582248 | J122: =J37 -> 0.40360942 | K122: =K37 -> 0.39481656 | L122: =L37 -> 0.37982412 | ... R122: =R37 -> 0.19283929
C123: DSO Assumption (2) | E123: =(AVERAGE(E53,D53)/E13)*365 -> 43.020536 | F123: =(AVERAGE(F53,E53)/F13)*365 -> 51.110387 | G123: =(AVERAGE(G53,F53)/G13)*365 -> 59.856542 | H123: =(AVERAGE(H53,G53)/H13)*365 -> 65.942729 | I123: =H123 -> 65.942729 | J123: =I123 -> 65.942729 | K123: =J123 -> 65.942729 | L123: =K123 -> 65.942729 | M123: =L123 -> 65.942729 | N123: =M123 -> 65.942729 | O123: =N123 -> 65.942729 | P123: =O123 -> 65.942729 | ... R123: =Q123 -> 65.942729
C125: Prepaid expenses and other current assets
C126: Beginning of period | E126: =D128 -> 110872 | F126: =E128 -> 149556 | G126: =F128 -> 99655 | H126: =G128 -> 129254 | I126: =H128 -> 139066 | J126: =I128 -> 195502.11 | K126: =J128 -> 274408.6 | L126: =K128 -> 382749.66 | ... R126: =Q128 -> 1951355.1
C127: Increase/Decrease | E127: =E128-E126 -> 38684 | F127: =F128-F126 -> -49901 | G127: =G128-G126 -> 29599 | H127: =H128-H126 -> 9812 | I127: =I128-I126 -> 56436.109 | J127: =J128-J126 -> 78906.493 | K127: =K128-K126 -> 108341.06 | L127: =L128-L126 -> 145377.55 | ... R127: =R128-R126 -> 376297.94
...

Sheet Intrinsic>>>

Sheet WACC
C2: WACC Analysis
C3: $USD Thousand except per share data
C5: INPUTS | H5: BETA CALCULATION
J6: 5-year
C7: Tax rate (5-year average) | F7: =SUM(FSM!D45:H45)/5 -> 0.0094326687 | H7: Company Name | I7: Ticker | J7: average tax rate | K7: Levered Beta | L7: Total Debt | M7: Market cap | N7: Unlevered Beta
C8: Risk-free rate | F8: 0.04731 | H8: Datadog | I8: NASDAQ: DDOG | J8: 0.13168 | K8: 1.36 | L8: =SUM(Inputs!D79:D82) -> 1279005 | M8: =Inputs!D77 -> 47373805 | N8: =K8/(1+(1-J8)*(L8/M8)) -> 1.3288478
C9: Market risk premium | F9: 0.0446 | H9: Snowflake | I9: NYSE: SNOW | J9: 0.25646667 | K9: 1.21 | L9: =SUM(Inputs!F79:F82) -> 407866 | M9: =Inputs!F77 -> 69648794 | N9: =K9/(1+(1-J9)*(L9/M9)) -> 1.2047543
H10: Hubspot | I10: NYSE: HUBS | J10: 0.20154 | K10: 1.45 | L10: =SUM(Inputs!H79:H82) -> 262305 | M10: =Inputs!H77 -> 13966518 | N10: =K10/(1+(1-J10)*(L10/M10)) -> 1.4285772
C11: WACC | H11: Salesforce | I11: NYSE: CRM | J11: 0.22202 | K11: 1.31 | L11: =SUM(Inputs!J79:J82) -> 17176000 | M11: =Inputs!J77 -> 188319600 | N11: =K11/(1+(1-J11)*(L11/M11)) -> 1.2232051
H12: Oracle | I12: NYSE: ORCL | J12: 0.1748 | K12: 1.65 | L12: =SUM(Inputs!L79:L82) -> 161425000 | M12: =Inputs!L77 -> 4.8122046e+08 | N12: =K12/(1+(1-J12)*(L12/M12)) -> 1.2922804
C13: Market risk premium | F13: =F9 -> 0.0446 | H13: Palo Alto Networks | I13: NASDAQ: PANW | J13: 0.21998 | K13: 0.82 | L13: =SUM(Inputs!N79:N82) -> 372000 | M13: =Inputs!N77 -> 140892940 | N13: =K13/(1+(1-J13)*(L13/M13)) -> 0.81831469
C14: Levered Beta | F14: =N18 -> 1.2170015 | H14: Average | N14: =AVERAGE(N8:N13) -> 1.2159966
C15: Adjusted market risk premium | F15: =F13*F14 -> 0.054278268 | H15: Palantir Avg tax rate | N15: =F7 -> 0.0094326687
C16: Add: risk-free rate | F16: =F8 -> 0.04731 | H16: Total Debt | N16: =SUM(DCF!N55:N56) -> 330081
C17: Cost of Equity | F17: =F15+F16 -> 0.10158827 | H17: Market cap | N17: =DCF!S60*DCF!D8 -> 3.9564159e+08
C18: Equity to total capitalization | F18: 1 | H18: PLTR Levered Beta | N18: =N14*(1+(1-F7)*(N16/N17)) -> 1.2170015
C19: Cost of equity portion | F19: =F17*F18 -> 0.10158827
H20: WACC Sensitivity
C21: Cost of debt | F21: 0
C22: Tax rate | F22: =F7 -> 0.0094326687 | H22: Pre-tax cost of debt
C23: After-tax cost of debt | F23: =F21*F22 -> 0 | H23: =F27 -> 0.10158827 | I23: 0.01 | J23: =I23+$P$25 -> 0.02 | K23: =J23+$P$25 -> 0.03 | L23: =K23+$P$25 -> 0.04 | M23: =L23+$P$25 -> 0.05 | N23: =M23+$P$25 -> 0.06
C24: Debt to total capitalization | F24: 0 | H24: 0.05 | I24: 0.10159298 | J24: 0.1015977 | K24: 0.10160242 | L24: 0.10160713 | M24: 0.10161185 | N24: 0.10161657
C25: Cost of debt portion | F25: =F23*F24 -> 0 | H25: =H24+$P$26 -> 0.1 | I25: 0.1015977 | J25: 0.10160713 | K25: 0.10161657 | L25: 0.101626 | M25: 0.10163543 | N25: 0.10164486 | P25: 0.01 | Q25: Pre-tax cost of debt step
H26: =H25+$P$26 -> 0.15 | I26: 0.10160242 | J26: 0.10161657 | K26: 0.10163071 | L26: 0.10164486 | M26: 0.10165901 | N26: 0.10167316 | P26: 0.05 | Q26: Debt to total cap/Equity to total cap step
C27: WACC | F27: =F19+F25 -> 0.10158827 | H27: =H26+$P$26 -> 0.2 | I27: 0.10160713 | J27: 0.101626 | K27: 0.10164486 | L27: 0.10166373 | M27: 0.10168259 | N27: 0.10170146 | P27: 0.02 | Q27: Cost of equity step
H28: =H27+$P$26 -> 0.25 | I28: 0.10161185 | J28: 0.10163543 | K28: 0.10165901 | L28: 0.10168259 | M28: 0.10170618 | N28: 0.10172976
H29: =H28+$P$26 -> 0.3 | I29: 0.10161657 | J29: 0.10164486 | K29: 0.10167316 | L29: 0.10170146 | M29: 0.10172976 | N29: 0.10175806
H31: Cost of Equity
H32: =F27 -> 0.10158827 | I32: 0.06 | J32: =I32+$P$27 -> 0.08 | K32: =J32+$P$27 -> 0.1 | L32: =K32+$P$27 -> 0.12 | M32: =L32+$P$27 -> 0.14 | N32: =M32+$P$27 -> 0.16
H33: 0.6 | I33: 0.036 | J33: 0.048 | K33: 0.06 | L33: 0.072 | M33: 0.084 | N33: 0.096
H34: =H33+$P$26 -> 0.65 | I34: 0.039 | J34: 0.052 | K34: 0.065 | L34: 0.078 | M34: 0.091 | N34: 0.104
H35: =H34+$P$26 -> 0.7 | I35: 0.042 | J35: 0.056 | K35: 0.07 | L35: 0.084 | M35: 0.098 | N35: 0.112
H36: =H35+$P$26 -> 0.75 | I36: 0.045 | J36: 0.06 | K36: 0.075 | L36: 0.09 | M36: 0.105 | N36: 0.12
H37: =H36+$P$26 -> 0.8 | I37: 0.048 | J37: 0.064 | K37: 0.08 | L37: 0.096 | M37: 0.112 | N37: 0.128
H38: =H37+$P$26 -> 0.85 | I38: 0.051 | J38: 0.068 | K38: 0.085 | L38: 0.102 | M38: 0.119 | N38: 0.136

Sheet DCF
C2: Discounted Cash Flows
C3: $USD Thousand except per share data
C5: Most recent fiscal year end | D5: 46022 | I5: Discount rate (WACC) | K5: =WACC!F27 -> 0.10158827
C6: End of first fiscal year | D6: 46387 | I6: Midyear convention | K6: 1
C7: Valuation date | D7: 46093
C8: Share price | D8: =Dashboard!D10 -> 153.5
C9: Share price date | D9: 46093 | I9: Active Case: | K9: =Dashboard!I8 -> Base
C10: Potion of first year cash flows | D10: =YEARFRAC(D7,D6) -> 0.80277778
B12: x | C12: Fiscal Year | J12: 2026 | K12: 2027 | L12: 2028 | M12: 2029 | N12: 2030 | O12: 2031 | P12: 2032 | Q12: 2033 | R12: 2034 | S12: 2035
C13: End Date | J13: 46387 | K13: =EOMONTH(J13,12) -> 46752 | L13: =EOMONTH(K13,12) -> 47118 | M13: =EOMONTH(L13,12) -> 47483 | N13: =EOMONTH(M13,12) -> 47848 | O13: =EOMONTH(N13,12) -> 48213 | P13: =EOMONTH(O13,12) -> 48579 | Q13: =EOMONTH(P13,12) -> 48944 | R13: =EOMONTH(Q13,12) -> 49309 | S13: =EOMONTH(R13,12) -> 49674
C15: Revenue | J15: =FSM!I13 -> 6291682.6 | K15: =FSM!J13 -> 8831065 | L15: =FSM!K13 -> 12317716 | M15: =FSM!L13 -> 16996281 | N15: =FSM!M13 -> 23100508 | O15: =FSM!N13 -> 30802452 | P15: =FSM!O13 -> 40143726 | Q15: =FSM!P13 -> 50957491 | ... S15: =FSM!R13 -> 74908933
C16: Cost of revenue | J16: =FSM!I14 -> -1109442.8 | K16: =FSM!J14 -> -1557224.3 | L16: =FSM!K14 -> -2172042.3 | M16: =FSM!L14 -> -2997036.3 | N16: =FSM!M14 -> -4073424.1 | O16: =FSM!N14 -> -5431545.1 | P16: =FSM!O14 -> -7078737 | Q16: =FSM!P14 -> -8985580.4 | ... S16: =FSM!R14 -> -13209054
C17: Gross profit | J17: =J15+J16 -> 5182239.8 | K17: =K15+K16 -> 7273840.6 | L17: =L15+L16 -> 10145673 | M17: =M15+M16 -> 13999245 | N17: =N15+N16 -> 19027084 | O17: =O15+O16 -> 25370907 | P17: =P15+P16 -> 33064989 | Q17: =Q15+Q16 -> 41971911 | ... S17: =S15+S16 -> 61699879
C18: Operating expenses
C19: Sales and marketing | J19: =FSM!I16 -> -1485756.1 | K19: =FSM!J16 -> -2041266 | L19: =FSM!K16 -> -2785603 | M19: =FSM!L16 -> -3758660.8 | N19: =FSM!M16 -> -4993084.1 | O19: =FSM!N16 -> -6503816.8 | P19: =FSM!O16 -> -8275471.5 | Q19: =FSM!P16 -> -10249899 | ... S19: =FSM!R16 -> -14318548
C20: Research and development | J20: =FSM!I17 -> -783994.86 | K20: =FSM!J17 -> -1056267.3 | L20: =FSM!K17 -> -1411710.5 | M20: =FSM!L17 -> -1862930.8 | N20: =FSM!M17 -> -2416501.1 | O20: =FSM!N17 -> -3068174.9 | P20: =FSM!O17 -> -3797923.2 | Q20: =FSM!P17 -> -4566206 | ... S20: =FSM!R17 -> -5963360.8
C21: General and administrative | J21: =FSM!I18 -> -924634.75 | K21: =FSM!J18 -> -1253670.7 | L21: =FSM!K18 -> -1687052.1 | M21: =FSM!L18 -> -2242853.8 | N21: =FSM!M18 -> -2932873.8 | O21: =FSM!N18 -> -3756711.5 | P21: =FSM!O18 -> -4695268.1 | Q21: =FSM!P18 -> -5705274.2 | ... S21: =FSM!R18 -> -7637822.8
C22: Operating income | J22: =J17+SUM(J19:J21) -> 1987854.1 | K22: =K17+SUM(K19:K21) -> 2922636.7 | L22: =L17+SUM(L19:L21) -> 4261307.8 | M22: =M17+SUM(M19:M21) -> 6134799.5 | N22: =N17+SUM(N19:N21) -> 8684624.8 | O22: =O17+SUM(O19:O21) -> 12042204 | P22: =P17+SUM(P19:P21) -> 16296326 | Q22: =Q17+SUM(Q19:Q21) -> 21450531 | ... S22: =S17+SUM(S19:S21) -> 33780147
C23: Tax expense | J23: =J22*-FSM!I45 -> -455616.15 | K23: =K22*-FSM!J45 -> -668699.27 | L23: =L22*-FSM!K45 -> -961777.16 | M23: =M22*-FSM!L45 -> -1349655.9 | N23: =N22*-FSM!M45 -> -1910617.4 | O23: =O22*-FSM!N45 -> -2528862.8 | P23: =P22*-FSM!O45 -> -3422228.5 | Q23: =Q22*-FSM!P45 -> -4504611.5 | ... S23: =S22*-FSM!R45 -> -7093830.9
C24: NOPAT | J24: =J22+J23 -> 1532237.9 | K24: =K22+K23 -> 2253937.4 | L24: =L22+L23 -> 3299530.6 | M24: =M22+M23 -> 4785143.6 | N24: =N22+N23 -> 6774007.3 | O24: =O22+O23 -> 9513340.9 | P24: =P22+P23 -> 12874098 | Q24: =Q22+Q23 -> 16945920 | ... S24: =S22+S23 -> 26686316
C26: Non-cash add back
C27: Depreciation and amortization | J27: =FSM!I210 -> 25239.136 | K27: =FSM!J210 -> 33966.268 | L27: =FSM!K210 -> 48413.422 | M27: =FSM!L210 -> 69840.69 | N27: =FSM!M210 -> 99829.69 | O27: =FSM!N210 -> 140141.99 | P27: =FSM!O210 -> 192491.29 | Q27: =FSM!P210 -> 257089.08 | ... S27: =FSM!R210 -> 414205.03
C29: Net working capital adjustments
C30: (Increase)/Decrease in accounts receivable | J30: =FSM!I87 -> -422893.4 | K30: =FSM!J87 -> -591271.01 | L30: =FSM!K87 -> -811833.42 | M30: =FSM!L87 -> -1089359.4 | N30: =FSM!M87 -> -1421311.1 | O30: =FSM!N87 -> -1793324.4 | P30: =FSM!O87 -> -2175026.7 | Q30: =FSM!P87 -> -2517882.2 | ... S30: =FSM!R87 -> -2819718.1
C31: (Increase)/Decrease in prepaid expenses and other current assets | J31: =FSM!I88 -> -56436.109 | K31: =FSM!J88 -> -78906.493 | L31: =FSM!K88 -> -108341.06 | M31: =FSM!L88 -> -145377.55 | N31: =FSM!M88 -> -189677.27 | O31: =FSM!N88 -> -239323.31 | P31: =FSM!O88 -> -290262.38 | Q31: =FSM!P88 -> -336017.24 | ... S31: =FSM!R88 -> -376297.94
C32: Increase/(Decrease) in accounts payable | J32: =FSM!I89 -> 3272.5525 | K32: =FSM!J89 -> 4575.5394 | L32: =FSM!K89 -> 6282.3574 | M32: =FSM!L89 -> 8429.9871 | N32: =FSM!M89 -> 10998.789 | O32: =FSM!N89 -> 13877.606 | P32: =FSM!O89 -> 16831.403 | Q32: =FSM!P89 -> 19484.583 | ... S32: =FSM!R89 -> 21820.334
C33: Increase/(Decrease) in accrued liabilities | J33: =FSM!I90 -> 144320.21 | K33: =FSM!J90 -> 201782.2 | L33: =FSM!K90 -> 277053.21 | M33: =FSM!L90 -> 371764.1 | N33: =FSM!M90 -> 485048.76 | O33: =FSM!N90 -> 612005.19 | P33: =FSM!O90 -> 742268.19 | Q33: =FSM!P90 -> 859273.99 | ... S33: =FSM!R90 -> 962281.08
C34: Increase/(Decrease in deferred revenue | J34: =FSM!I91 -> 184721.87 | K34: =FSM!J91 -> 258270.02 | L34: =FSM!K91 -> 354612.74 | M34: =FSM!L91 -> 475837.44 | N34: =FSM!M91 -> 620835.51 | O34: =FSM!N91 -> 783332.71 | P34: =FSM!O91 -> 950062.13 | Q34: =FSM!P91 -> 1099823.1 | ... S34: =FSM!R91 -> 1231666.4
C35: Increase/(Decrease) in customer deposits | J35: =FSM!I92 -> 144912.71 | K35: =FSM!J92 -> 202610.6 | L35: =FSM!K92 -> 278190.64 | M35: =FSM!L92 -> 373290.37 | N35: =FSM!M92 -> 487040.1 | O35: =FSM!N92 -> 614517.75 | P35: =FSM!O92 -> 745315.55 | Q35: =FSM!P92 -> 862801.7 | ... S35: =FSM!R92 -> 966231.68
C37: Capital expenditures
C38: Capital expenditures | J38: =-FSM!I181 -> -47632.077 | K38: =-FSM!J181 -> -66856.832 | L38: =-FSM!K181 -> -93253.017 | M38: =-FSM!L181 -> -128672.76 | N38: =-FSM!M181 -> -174885.68 | O38: =-FSM!N181 -> -233194.34 | P38: =-FSM!O181 -> -303913.78 | Q38: =-FSM!P181 -> -385780.93 | ... S38: =-FSM!R181 -> -567108.72
C39: Unlevered Free Cash Flow | J39: =J24+SUM(J27:J38) -> 1507742.8 | K39: =K24+SUM(K27:K38) -> 2218107.7 | L39: =L24+SUM(L27:L38) -> 3250655.5 | M39: =M24+SUM(M27:M38) -> 4720896.4 | N39: =N24+SUM(N27:N38) -> 6691886.1 | O39: =O24+SUM(O27:O38) -> 9411374.1 | P39: =P24+SUM(P27:P38) -> 12751863 | Q39: =Q24+SUM(Q27:Q38) -> 16804712 | ... S39: =S24+SUM(S27:S38) -> 26519396
C42: Fiscal Year | I42: Val Date | J42: 1 | K42: 2 | L42: 3 | M42: 4 | N42: 5 | O42: 6 | P42: 7 | Q42: 8 | R42: 9 | S42: 10
C43: End Date | I43: =D7 -> 46093 | J43: =IF($K$6=0,J13,AVERAGE(J13,I43)) -> 46240 | K43: =IF($K$6=0,K13,AVERAGE(K13,J13)) -> 46569.5 | L43: =IF($K$6=0,L13,AVERAGE(L13,K13)) -> 46935 | M43: =IF($K$6=0,M13,AVERAGE(M13,L13)) -> 47300.5 | N43: =IF($K$6=0,N13,AVERAGE(N13,M13)) -> 47665.5 | O43: =IF($K$6=0,O13,AVERAGE(O13,N13)) -> 48030.5 | P43: =IF($K$6=0,P13,AVERAGE(P13,O13)) -> 48396 | Q43: =IF($K$6=0,Q13,AVERAGE(Q13,P13)) -> 48761.5 | R43: =IF($K$6=0,R13,AVERAGE(R13,Q13)) -> 49126.5 | S43: =IF($K$6=0,S13,AVERAGE(S13,R13)) -> 49491.5
C45: Unlevered Free Cash Flow stub adjusted | J45: =J39*D10 -> 1210382.4 | K45: =K39 -> 2218107.7 | L45: =L39 -> 3250655.5 | M45: =M39 -> 4720896.4 | N45: =N39 -> 6691886.1 | O45: =O39 -> 9411374.1 | P45: =P39 -> 12751863 | Q45: =Q39 -> 16804712 | R45: =R39 -> 21469131 | S45: =S39 -> 26519396
C46: PV Factor | J46: =1/(1+$K$5)^((J43-$I$43)/365) -> 0.96178314 | K46: =1/(1+$K$5)^((K43-$I$43)/365) -> 0.8813424 | L46: =1/(1+$K$5)^((L43-$I$43)/365) -> 0.79995914 | M46: =1/(1+$K$5)^((M43-$I$43)/365) -> 0.72609081 | N46: =1/(1+$K$5)^((N43-$I$43)/365) -> 0.65913085 | O46: =1/(1+$K$5)^((O43-$I$43)/365) -> 0.59834592 | P46: =1/(1+$K$5)^((P43-$I$43)/365) -> 0.54309459 | Q46: =1/(1+$K$5)^((Q43-$I$43)/365) -> 0.49294516 | ... S46: =1/(1+$K$5)^((S43-$I$43)/365) -> 0.40621879
C47: PV of Unlevered Free Cash Flows | J47: =J45*J46 -> 1164125.4 | K47: =K45*K46 -> 1954912.4 | L47: =L45*L46 -> 2600391.5 | M47: =M45*M46 -> 3427799.5 | N47: =N45*N46 -> 4410828.6 | O47: =O45*O46 -> 5631257.3 | P47: =P45*P46 -> 6925467.9 | Q47: =Q45*Q46 -> 8283801.3 | ... S47: =S45*S46 -> 10772677
B50: x | C50: Terminal Value - Gordon Growth | F50: Terminal Value - Exit Multiple | K50: Net Debt | P50: Shares Outstanding
C51: Long-term growth rate | D51: 0.035 | F51: Terminal year EBITDA | I51: =FSM!R32 -> 34194352 | K51: Gross debt and equivalents | P51: Basic shares | S51: =FSM!D7 -> 2391675.7
C52: 2035 FCF x (1+g) | D52: =S39*(1+D51) -> 27447575 | F52: EBITDA multiple | I52: =Valuation!P14 -> 35.893007 | K52: Debt | N52: 0 | P52: Restricted stock/RSUs | S52: 41762
C53: Terminal value | D53: =D52/(K5-D51) -> 4.1219836e+08 | F53: Terminal value | I53: =I51*I52 -> 1.2273381e+09 | K53: Convertible debt | N53: 0 | P53: SARs/Options | S53: 163473
C54: PV of terminal value | D54: =D53/(1+K5)^((S43-I43)/365) -> 1.6744272e+08 | F54: PV of terminal value | I54: =I53/(1+K5)^((S43-I43)/365) -> 4.9856781e+08 | K54: Preferred stock | N54: 0 | P54: Total proceeds | S54: =152202*9.98+11271*130 -> 2984206
C55: PV of stage 1 cash flows | D55: =SUM(J47:S47) -> 54778393 | F55: PV of stage 1 cash flows | I55: =SUM(J47:S47) -> 54778393 | K55: Operating lease liabilities | N55: =FSM!H64 -> 229338 | P55: Shares repurchased | S55: =-S54/D8 -> -19441.081
C56: Total Enterprise Value | D56: =D54+D55 -> 2.2222111e+08 | F56: Total Enterprise Value | I56: =I54+I55 -> 5.533462e+08 | K56: Noncontrolling interests | N56: =FSM!H73 -> 100743 | P56: Net dilutive impact of SARs/Options | S56: =S53+S55 -> 144031.92
K57: Nonoperating assets | P57: Convertible debt | S57: 0
C58: Terminal value as % of TEV | D58: =D54/$D$56 -> 0.753496 | F58: Terminal value as % of TEV | I58: =I54/I56 -> 0.90100521 | K58: Cash and marketable securities | N58: =FSM!H52 -> 7177043 | P58: Convertible preferred stock | S58: 0
C59: Stage 1 cash flows as % of TEV | D59: =D55/$D$56 -> 0.246504 | F59: Stage 1 cash flows as % of TEV | I59: =I55/I56 -> 0.098994795
C60: Implied TV exit EBITDA multiple | D60: =D53/FSM!R32 -> 12.054574 | F60: Implied terminal growth rate | I60: =(K5-S45/I53)/(1+S45/I53) -> 0.078289404 | K60: Net Debt | N60: =SUM(N52:N56)-N58 -> -6846962 | P60: Net Diluted Shares Outstanding | S60: =S51+S52+S56 -> 2577469.6
C63: Valuation
D64: Perpetuity | E64: EBITDA | I64: Last twelve months (LTM) | K64: Year 1 Forecast
C65: Enterprise value | D65: =D56 -> 2.2222111e+08 | E65: =I56 -> 5.533462e+08 | I65: Perpetuity | J65: EBITDA | K65: Perpetuity | L65: EBITDA
C66: Net debt | D66: =$N$60 -> -6846962 | E66: =$N$60 -> -6846962 | H66: EV / Revenue | I66: =D65/((1-$D$10)*J15+$D$10*FSM!H13) -> 45.973787 | J66: =E65/((1-D10)*J15+D10*FSM!H13) -> 114.47796 | K66: =D65/$J$15 -> 35.319822 | L66: =E65/$J$15 -> 87.948842
C67: Equity value | D67: =D65-D66 -> 2.2906807e+08 | E67: =E65-E66 -> 5.6019316e+08 | H67: EV / EBITDA | I67: =D65/((1-D10)*FSM!I32+D10*FSM!H32) -> 143.07721 | J67: =E65/((1-D10)*FSM!I32+D10*FSM!H32) -> 356.27232 | K67: =D65/FSM!$I$32 -> 110.38789 | L67: =E65/FSM!$I$32 -> 274.87361
C68: Shares outstanding | D68: =$S$60 -> 2577469.6 | E68: =$S$60 -> 2577469.6 | H68: EV / EBIT | I68: =D65/((1-D10)*J22+D10*FSM!H19) -> 145.50991 | J68: =E65/((1-D10)*J22+D10*FSM!H19) -> 362.32992 | K68: =D65/$J$22 -> 111.78945 | L68: =E65/$J$22 -> 278.36359
C69: Equity value per share | D69: =D67/D68 -> 88.873239 | E69: =E67/E68 -> 217.34229
B72: x | C72: Sensitivity Analysis
D74: Equity value per share | M74: Year 1 EBITDA Multiple
D75: Long-term growth rate | M75: Long-term growth rate
D76: =D69 -> 88.873239 | E76: 0.02 | F76: =E76+0.005 -> 0.025 | G76: =F76+0.005 -> 0.03 | H76: =G76+0.005 -> 0.035 | I76: =H76+0.005 -> 0.04 | J76: =I76+0.005 -> 0.045 | M76: =K67 -> 110.38789 | N76: 0.02 | O76: =N76+0.005 -> 0.025 | P76: =O76+0.005 -> 0.03 | Q76: =P76+0.005 -> 0.035 | R76: =Q76+0.005 -> 0.04 | S76: =R76+0.005 -> 0.045
D77: 0.1116 | E77: 65.489217 | F77: 68.181063 | G77: 71.202793 | H77: 74.619004 | I77: 78.51234 | J77: 82.990261 | M77: 0.1116 | N77: 80.448091 | O77: 83.894604 | P77: 87.763485 | Q77: 92.137441 | R77: 97.122284 | S77: 102.8556
D78: =D77-0.005 -> 0.1066 | E78: 70.48749 | F78: 73.624583 | G78: 77.171218 | H78: 81.213194 | I78: 85.862072 | J78: 91.265639 | M78: =M77-0.005 -> 0.1066 | N78: 86.847644 | O78: 90.86423 | P78: 95.405175 | Q78: 100.58033 | R78: 106.53253 | S78: 113.45101
C79: WACC | D79: =D78-0.005 -> 0.1016 | E79: 76.147046 | F79: 79.829709 | G79: 84.026711 | H79: 88.853893 | I79: 94.464709 | J79: 101.06683 | L79: WACC | M79: =M78-0.005 -> 0.1016 | N79: 94.093873 | O79: 98.808981 | P79: 104.18262 | Q79: 110.36312 | R79: 117.54694 | S79: 126
D80: =D79-0.005 -> 0.0966 | E80: 82.599465 | F80: 86.958185 | G80: 91.971368 | H80: 97.798379 | I80: 104.6549 | J80: 112.8402 | M80: =M79-0.005 -> 0.0966 | N80: 102.35525 | O80: 107.93595 | P80: 114.35459 | Q80: 121.81522 | R80: 130.59398 | S80: 141.07406
D81: =D80-0.005 -> 0.0916 | E81: 90.013186 | F81: 95.220436 | G81: 101.27302 | H81: 108.39496 | I81: 116.89713 | J81: 127.22379 | M81: =M80-0.005 -> 0.0916 | N81: 111.84743 | O81: 118.51454 | P81: 126.26398 | Q81: 135.38258 | R81: 146.26836 | S81: 159.49013
D82: =D81-0.005 -> 0.0866 | E82: 98.607348 | F82: 104.89533 | G82: 112.29426 | H82: 121.1271 | I82: 131.85539 | J82: 145.1626 | M82: =M81-0.005 -> 0.0866 | N82: 122.85099 | O82: 130.90182 | P82: 140.37507 | Q82: 151.68421 | R82: 165.42021 | S82: 182.45814
D85: Equity value per share | M85: Year 1 EBITDA Multiple
D86: Exit EBITDA Multiple | M86: Exit EBITDA Multiple
D87: =E69 -> 217.34229 | E87: 30 | F87: =E87+2 -> 32 | G87: =F87+2 -> 34 | H87: =G87+2 -> 36 | I87: =H87+2 -> 38 | J87: =I87+2 -> 40 | M87: =L67 -> 274.87361 | N87: 30 | O87: =N87+2 -> 32 | P87: =O87+2 -> 34 | Q87: =P87+2 -> 36 | R87: =Q87+2 -> 38 | S87: =R87+2 -> 40
D88: 0.1116 | E88: 171.32144 | F88: 181.22898 | G88: 191.13652 | H88: 201.04406 | I88: 210.9516 | J88: 220.85914 | M88: 0.1116 | N88: 215.95068 | O88: 228.63583 | P88: 241.32097 | Q88: 254.00612 | R88: 266.69127 | S88: 279.37642
D89: =D88-0.005 -> 0.1066 | E89: 178.28069 | F89: 188.61296 | G89: 198.94522 | H89: 209.27749 | I89: 219.60975 | J89: 229.94202 | M89: =M88-0.005 -> 0.1066 | N89: 224.86098 | O89: 238.08993 | P89: 251.31887 | Q89: 264.54782 | R89: 277.77676 | S89: 291.00571
C90: WACC | D90: =D89-0.005 -> 0.1016 | E90: 185.56646 | F90: 196.34371 | G90: 207.12095 | H90: 217.8982 | I90: 228.67544 | J90: 239.45269 | L90: WACC | M90: =M89-0.005 -> 0.1016 | N90: 234.18933 | O90: 247.98801 | P90: 261.78669 | Q90: 275.58536 | R90: 289.38404 | S90: 303.18271
D91: =D90-0.005 -> 0.0966 | E91: 193.19574 | F91: 204.43928 | G91: 215.68283 | H91: 226.92637 | I91: 238.16992 | J91: 249.41346 | M91: =M90-0.005 -> 0.0966 | N91: 243.9575 | O91: 258.3532 | P91: 272.74891 | Q91: 287.14461 | R91: 301.54032 | S91: 315.93603
D92: =D91-0.005 -> 0.0916 | E92: 201.18649 | F92: 212.91878 | G92: 224.65108 | H92: 236.38337 | I92: 248.11566 | J92: 259.84795 | M92: =M91-0.005 -> 0.0916 | N92: 254.18848 | O92: 269.20996 | P92: 284.23143 | Q92: 299.2529 | R92: 314.27438 | S92: 329.29585
D93: =D92-0.005 -> 0.0866 | E93: 209.55772 | F93: 221.8024 | G93: 234.04708 | H93: 246.29175 | I93: 258.53643 | J93: 270.78111 | M93: =M92-0.005 -> 0.0866 | N93: 264.90661 | O93: 280.58412 | P93: 296.26163 | Q93: 311.93913 | R93: 327.61664 | S93: 343.29415

Sheet Comps>>>

Sheet Inputs
C2: Comparable Company Inputs
C3: $USD Thousand except per share data
C5: Refresh Date | D5: 46093
C6: Recent Calendarized Date | D6: 46022
B8: x | C8: General Inputs
C10: Ticker | D10: NASDAQ: DDOG | F10: NYSE: SNOW | H10: NYSE: HUBS | J10: NYSE: CRM | L10: NYSE: ORCL | N10: NASDAQ: PANW
C11: Company name | D11: Datadog | F11: Snowflake | H11: Hubspot | J11: Salesforce | L11: Oracle | N11: Palo Alto Networks
C12: Lastest closing price | D12: 127.16 | F12: 177.25 | H12: 257.63 | J12: 199.28 | L12: 159.16 | N12: 168.13
C13: Latest fiscal year end | D13: 46022 | F13: 45688 | H13: 46022 | J13: 46053 | L13: 45808 | N13: 45869
C14: Latest quarter year end | D14: 46022 | F14: 45961 | H14: 46022 | J14: 46053 | L14: 46081 | N14: 46053
B17: x | C17: Share Counts
C19: Basic share count | D19: 352576.08 | F19: 342200 | H19: 52740.536 | J19: 923000 | L19: 2876046 | N19: 816000
C20: RSUs/PSUs | D20: 16700.403 | F20: 24039 | H20: 1471 | J20: 22000 | L20: 120000 | N20: 22000
C21: Total Basic Share Count | D21: =SUM(D19:D20) -> 369276.48 | F21: =SUM(F19:F20) -> 366239 | H21: =SUM(H19:H20) -> 54211.536 | J21: =SUM(J19:J20) -> 945000 | L21: =SUM(L19:L20) -> 2996046 | N21: =SUM(N19:N20) -> 838000
C23: Options count | D23: 3474.619 | F23: 13695 | H23: 174 | J23: 6000 | L23: 41000 | N23: 0
C24: Weighted average exercise price | D24: 7.26 | F24: 18.83 | H24: 286.89 | J24: 207.54 | L24: 52.58 | N24: 0
C25: # of options exercised | D25: =IF(D24<D12,D23,0) -> 3474.619 | F25: =IF(F24<F12,F23,0) -> 13695 | H25: =IF(H24<H12,H23,0) -> 0 | J25: =IF(J24<J12,J23,0) -> 0 | L25: =IF(L24<L12,L23,0) -> 41000 | N25: =IF(N24<N12,N23,0) -> 0
C26: Option proceeds | D26: =D25*D24 -> 25225.734 | F26: =F25*F24 -> 257876.85 | H26: =H25*H24 -> 0 | J26: =J25*J24 -> 0 | L26: =L25*L24 -> 2155780 | N26: =N25*N24 -> 0
C27: Shares repurchased | D27: =D26/D12 -> 198.3779 | F27: =F26/F12 -> 1454.8764 | H27: =H26/H12 -> 0 | J27: =J26/J12 -> 0 | L27: =L26/L12 -> 13544.735 | N27: =N26/N12 -> 0
C28: Net Dilution from Options | D28: =D25-D27 -> 3276.2411 | F28: =F25-F27 -> 12240.124 | H28: =H25-H27 -> 0 | J28: =J25-J27 -> 0 | L28: =L25-L27 -> 27455.265 | N28: =N25-N27 -> 0
C30: Convertible debt outstanding | D30: 983449 | F30: 2277749 | H30: 0 | J30: 0 | L30: 0 | N30: 0
C31: Conversion ratio | D31: 4.5955 | F31: 6.3492 | H31: 3.5396 | J31: 0 | L31: 0 | N31: 0
C32: Conversion price | D32: =D30/D33 -> 217.60418 | F32: =F30/F33 -> 157.50016 | H32: 0 | J32: 0 | L32: 0 | N32: 0
C33: Common shares convertible into | D33: =D30*D31/1000 -> 4519.4399 | F33: =F30*F31/1000 -> 14461.884 | H33: 0 | J33: 0 | L33: 0 | N33: 0
C34: Dilution from convertible debt | D34: =IF(D32<D12,D33,0) -> 0 | F34: =IF(F32<F12,F33,0) -> 14461.884 | H34: =IF(H32<H12,H33,0) -> 0 | J34: =IF(J32<J12,J33,0) -> 0 | L34: =IF(L32<L12,L33,0) -> 0 | N34: =IF(N32<N12,N33,0) -> 0
C36: Convertible preferred par value | D36: 0 | F36: 0 | H36: 0 | J36: 0 | L36: 4954000 | N36: 0
C37: Preferred shares oustanding | D37: 0 | F37: 0 | H37: 0 | J37: 0 | L37: 50000 | N37: 0
C38: Conversion ratio | D38: 0 | F38: 0 | H38: 0 | J38: 0 | L38: 499.8126 | N38: 0
C39: Common shares convertible into | D39: 0 | F39: 0 | H39: 0 | J39: 0 | L39: =L37*L38 -> 24990630 | N39: 0
C40: Conversion price | D40: 0 | F40: 0 | H40: 0 | J40: 0 | L40: 0 | N40: 0
C41: Dilution from preferred stock | D41: 0 | F41: 0 | H41: 0 | J41: 0 | L41: 0 | N41: 0
C43: Fully Diluted Shares Outstanding | D43: =D21+D28+D34 -> 372552.73 | F43: =F21+F28+F34 -> 392941.01 | H43: =H21+H28+H34 -> 54211.536 | J43: =J21+J28+J34 -> 945000 | L43: =L21+L28+L34 -> 3023501.3 | N43: =N21+N28+N34 -> 838000
B46: x | C46: Balance Sheet Data
C48: Cash | D48: 401305 | F48: 1941657 | H48: 882242 | J48: 7327000 | L48: 38455000 | N48: 4158000
C49: Investments | D49: 4073531 | F49: 1411448 | H49: 958214 | J49: 2238000 | L49: 677000 | N49: 378000
C50: Cash & Cash Equivalents | D50: =SUM(D48:D49) -> 4474836 | F50: =SUM(F48:F49) -> 3353105 | H50: =SUM(H48:H49) -> 1840456 | J50: =SUM(J48:J49) -> 9565000 | L50: =SUM(L48:L49) -> 39132000 | N50: =SUM(N48:N49) -> 4536000
C51: Accounts Receivable | D51: 741262 | F51: 938145 | H51: 419146 | J51: 14339000 | L51: 10719000 | N51: 2116000
C52: Prepaid expenses & other current assets | D52: 90160 | F52: 164319 | H52: 100611 | J52: 2243000 | L52: 5023000 | N52: 621000
C53: Goodwill & Intangibles | D53: 545536 | F53: 1431540 | H53: 326677 | J53: 64756000 | L53: 65915000 | N53: 8180000
C54: Operating lease assets | D54: 214674 | F54: 254641 | H54: 200821 | J54: 2003000 | L54: 20817000 | N54: 368000
C55: Equity Method Investments | J55: 7591000
C56: PP&E, Net | D56: 338093 | F56: 265844 | H56: 141869 | J56: 3120000 | L56: 83617000 | N56: 485000
C57: Other assets | D57: 36553 | F57: 403686 | H57: 165602 | J57: 3628000 | L57: 8657000 | N57: 427000
C58: Accounts payable, acrrued liabilities, & other current liabilities | F58: 919484 | H58: 191625 | J58: 8253000 | L58: 11414000 | N58: 1199000
C60: Notes Payable | D60: 0 | F60: 0 | H60: 0 | J60: 0 | L60: 9887000 | N60: 0
C61: Current Portion of Long-Term Debt | D61: 0 | F61: 0 | H61: 0 | J61: 4000000 | L61: 0 | N61: 0
C62: Other Short-Term Debt | D62: 0 | F62: 0 | H62: 0 | J62: 0 | L62: 0 | N62: 0
C63: Total Short-Term Debt | D63: =SUM(D60:D62) -> 0 | F63: =SUM(F60:F62) -> 0 | H63: =SUM(H60:H62) -> 0 | J63: =SUM(J60:J62) -> 4000000 | L63: =SUM(L60:L62) -> 9887000 | N63: =SUM(N60:N62) -> 0
C64: Long-Term Debt | D64: =IF(D34>0,0,D30) -> 983449 | F64: =IF(F34>0,0,F30) -> 0 | H64: 0 | J64: 10439000 | L64: 0 | N64: 0
C65: Other Long-Term Debt | D65: 0 | F65: 0 | H65: 0 | J65: 0 | L65: 124718000 | N65: 0
C66: Total Long-Term Debt | D66: =SUM(D64:D65) -> 983449 | F66: =SUM(F64:F65) -> 0 | H66: =SUM(H64:H65) -> 0 | J66: =SUM(J64:J65) -> 10439000 | L66: =SUM(L64:L65) -> 124718000 | N66: =SUM(N64:N65) -> 0
C68: Minority Interests | D68: 0 | F68: 0 | H68: 0 | J68: 0 | L68: 556000 | N68: 0
C69: Preferred Stock | D69: 0 | F69: 0 | H69: 0 | J69: 0 | L69: 4954000 | N69: 0
C70: Total Shareholders' Equity | D70: 3732206 | F70: 2132933 | H70: 2066244 | J70: 59142000 | L70: 39051000 | N70: 9393000
B73: x | C73: Market Valuation Summary
C75: Price Per Share | D75: =D12 -> 127.16 | F75: =F12 -> 177.25 | H75: =H12 -> 257.63 | J75: =J12 -> 199.28 | L75: =L12 -> 159.16 | N75: =N12 -> 168.13
C76: Fully Diluted Shares Outstanding | D76: =D43 -> 372552.73 | F76: =F43 -> 392941.01 | H76: =H43 -> 54211.536 | J76: =J43 -> 945000 | L76: =L43 -> 3023501.3 | N76: =N43 -> 838000
C77: Market Value of Equity | D77: =D75*D76 -> 47373805 | F77: =F75*F76 -> 69648794 | H77: =H75*H76 -> 13966518 | J77: =J75*J76 -> 188319600 | L77: =L75*L76 -> 4.8122046e+08 | N77: =N75*N76 -> 140892940
C79: Gross Debt | D79: =D63+D66 -> 983449 | F79: =F63+F66 -> 0 | H79: =H63+H66 -> 0 | J79: =J63+J66 -> 14439000 | L79: =L63+L66 -> 134605000 | N79: =N63+N66 -> 0
C80: Minority Interest | D80: =D68 -> 0 | F80: =F68 -> 0 | H80: =H68 -> 0 | J80: =J68 -> 0 | L80: =L68 -> 556000 | N80: =N68 -> 0
C81: Preferred Stock | D81: =D69 -> 0 | F81: =F69 -> 0 | H81: =H69 -> 0 | J81: =J69 -> 0 | L81: =L69 -> 4954000 | N81: =N69 -> 0
C82: Operating Lease Liabilities | D82: 295556 | F82: 407866 | H82: 262305 | J82: 2737000 | L82: 21310000 | N82: 372000
C83: Cash & Cash Equivalents | D83: =-D50 -> -4474836 | F83: =-F50 -> -3353105 | H83: =-H50 -> -1840456 | J83: =-J50 -> -9565000 | L83: =-L50 -> -39132000 | N83: =-N50 -> -4536000
C84: Net Debt | D84: =SUM(D79:D83) -> -3195831 | F84: =SUM(F79:F83) -> -2945239 | H84: =SUM(H79:H83) -> -1578151 | J84: =SUM(J79:J83) -> 7611000 | L84: =SUM(L79:L83) -> 122293000 | N84: =SUM(N79:N83) -> -4164000
C86: Enterprise Value | D86: =D77+D84 -> 44177974 | F86: =F77+F84 -> 66703555 | H86: =H77+H84 -> 12388367 | J86: =J77+J84 -> 195930600 | L86: =L77+L84 -> 6.0351346e+08 | N86: =N77+N84 -> 136728940
B89: x | C89: Income Statement Data
C91: Latest Fiscal Year
C92: Revenue | D92: 3427158 | F92: 3626396 | H92: 3131266 | J92: 41525000 | L92: 57399000 | N92: 9221500
C93: COGS (enter as -) | D93: -686957 | F93: -1214673 | H93: -508487 | J93: -9270000 | L93: 0 | N93: -2451600
C94: Gross Profit | D94: =SUM(D92:D93) -> 2740201 | F94: =SUM(F92:F93) -> 2411723 | H94: =SUM(H92:H93) -> 2622779 | J94: =SUM(J92:J93) -> 32255000 | L94: =SUM(L92:L93) -> 57399000 | N94: =SUM(N92:N93) -> 6769900
C95: Operating Expenses | D95: -2784574 | F95: -3867733 | H95: -2615400 | J95: -23924000 | L95: -39721000 | N95: -5527000
C96: Operating Income (EBIT) | D96: =SUM(D94:D95) -> -44373 | F96: =SUM(F94:F95) -> -1456010 | H96: =SUM(H94:H95) -> 7379 | J96: =SUM(J94:J95) -> 8331000 | L96: =SUM(L94:L95) -> 17678000 | N96: =SUM(N94:N95) -> 1242900
C97: Non-operating (expense) / benefit | D97: 171394 | F97: 170911 | H97: 62084 | J97: 1189000 | L97: -3518000 | N97: =-3000+355800 -> 352800
C98: Pre-tax Income (EBT) | D98: =SUM(D96:D97) -> 127021 | F98: =SUM(F96:F97) -> -1285099 | H98: =SUM(H96:H97) -> 69463 | J98: =SUM(J96:J97) -> 9520000 | L98: =SUM(L96:L97) -> 14160000 | N98: =SUM(N96:N97) -> 1595700
C99: Tax (expense) / benefit | D99: -19280 | F99: 4113 | H99: -23552 | J99: -2063000 | L99: -1717000 | N99: -461800
C100: Net Income | D100: =SUM(D98:D99) -> 107741 | F100: =SUM(F98:F99) -> -1280986 | H100: =SUM(H98:H99) -> 45911 | J100: =SUM(J98:J99) -> 7457000 | L100: =SUM(L98:L99) -> 12443000 | N100: =SUM(N98:N99) -> 1133900
C101: Diluted Weighted Avg. Shares | D101: 363472 | F101: 332707 | H101: 53194 | J101: 956000 | L101: 2866000 | N101: 709300
C102: Depreciation & Amortization | D102: 55756 | F102: 182508 | H102: 136295 | J102: 3631000 | L102: 6174000 | N102: 343400
C104: EBITDA | D104: =D96+D102 -> 11383 | F104: =F96+F102 -> -1273502 | H104: =H96+H102 -> 143674 | J104: =J96+J102 -> 11962000 | L104: =L96+L102 -> 23852000 | N104: =N96+N102 -> 1586300
C105: EPS | D105: =D100/D101 -> 0.29642173 | F105: =F100/F101 -> -3.8501925 | H105: =H100/H101 -> 0.86308606 | J105: =J100/J101 -> 7.8002092 | L105: =L100/L101 -> 4.3415911 | N105: =N100/N101 -> 1.5986184
C107: Calculated Tax Rate | D107: =-(IFERROR(D99/D98,0)) -> 0.15178593 | F107: =-(IFERROR(F99/F98,0)) -> 0.0032005316 | H107: =-(IFERROR(H99/H98,0)) -> 0.3390582 | J107: =-(IFERROR(J99/J98,0)) -> 0.21670168 | L107: =-(IFERROR(L99/L98,0)) -> 0.12125706 | N107: =-(IFERROR(N99/N98,0)) -> 0.28940277
C109: Non-GAAP Operating Adjustments | D109: 812417 | F109: 1924883 | H109: 574522 | J109: 5825000 | L109: 7355000 | N109: 1409000
C110: Non-GAAP Non-Operating Adjustments | D110: 5602 | F110: 8298 | H110: 1000 | J110: 0 | L110: 0 | N110: 1100
C111: Tax Effect on Non-GAAP Adjustments | D111: -179178 | F111: -138193 | H111: -105445 | J111: -1313000 | L111: -2514000 | N111: -199500
C113: Adjusted EBITDA | D113: =D114+D102 -> 823800 | F113: =F114+F102 -> 651381 | H113: =H114+H102 -> 718196 | J113: =J114+J102 -> 17787000 | L113: =L114+L102 -> 31207000 | N113: =N114+N102 -> 2995300
C114: Adjusted EBIT | D114: =D96+D109 -> 768044 | F114: =F96+F109 -> 468873 | H114: =H96+H109 -> 581901 | J114: =J96+J109 -> 14156000 | L114: =L96+L109 -> 25033000 | N114: =N96+N109 -> 2651900
C115: Adjusted Net Income | D115: =D100+SUM(D109:D111) -> 746582 | F115: =F100+SUM(F109:F111) -> 514002 | H115: =H100+SUM(H109:H111) -> 515988 | J115: =J100+SUM(J109:J111) -> 11969000 | L115: =L100+SUM(L109:L111) -> 17284000 | N115: =N100+SUM(N109:N111) -> 2344500
C116: Adjusted EPS | D116: =D115/D101 -> 2.0540289 | F116: =F115/F101 -> 1.5449089 | H116: =H115/H101 -> 9.7001166 | J116: =J115/J101 -> 12.519874 | L116: =L115/L101 -> 6.0307048 | N116: =N115/N101 -> 3.3053715
C118: Latest Fiscal Quarters
C119: Revenue | D119: 0 | F119: 3399952 | H119: 0 | J119: 0 | L119: 48173000 | N119: 5068000
C120: COGS (enter as -) | D120: 0 | F120: -1111474 | H120: 0 | J120: 0 | L120: 0 | N120: -1323000
C121: Gross Profit | D121: 0 | F121: =SUM(F119:F120) -> 2288478 | H121: 0 | J121: 0 | L121: =SUM(L119:L120) -> 48173000 | N121: =SUM(N119:N120) -> 3745000
C122: Operating Expenses | D122: 0 | F122: -3405484 | H122: 0 | J122: 0 | L122: -33700000 | N122: -3039000
C123: Operating Income (EBIT) | D123: 0 | F123: =SUM(F121:F122) -> -1117006 | H123: 0 | J123: 0 | L123: =SUM(L121:L122) -> 14473000 | N123: =SUM(N121:N122) -> 706000
C124: Non-operating (expense) / benefit | D124: 0 | F124: 106994 | H124: 0 | J124: 0 | L124: =-3160000+2872000 -> -288000 | N124: 255000
C125: Pre-tax Income (EBT) | D125: 0 | F125: =SUM(F123:F124) -> -1010012 | H125: 0 | J125: 0 | L125: =SUM(L123:L124) -> 14185000 | N125: =SUM(N123:N124) -> 961000
C126: Tax (expense) / benefit | D126: 0 | F126: -9473 | H126: 0 | J126: 0 | L126: -1402000 | N126: -195000
C127: Net Income | D127: 0 | F127: =SUM(F125:F126) -> -1019485 | H127: 0 | J127: 0 | L127: =SUM(L125:L126) -> 12783000 | N127: =SUM(N125:N126) -> 766000
C128: Diluted Weighted Avg. Shares | D128: 0 | F128: 335875 | H128: 0 | J128: 0 | L128: 2914000 | N128: 713000
C129: Depreciation & Amortization | D129: 0 | F129: 161519 | H129: 0 | J129: 0 | L129: 6447000 | N129: 180000
...

Sheet Operating Metrics
C2: Comparable Company Operating Metrics
C3: $USD Thousand except per share data
J5: Revenue | O5: CAGR | Q5: Adjusted EBIT | V5: CAGR | X5: Adjusted EBIT Margin | AC5: Adjusted EBITDA | AH5: CAGR | AJ5: Adjusted EBITDA Margin | AO5: Adjusted Net Income | AT5: CAGR | AV5: Adjusted Net Income Margin
C6: Ticker | D6: Company | E6: Enterprise Value | F6: Market Capitalization | G6: Price | H6: Net Debt/ LTM EBITDA | J6: 0 | K6: LTM | L6: 1 | M6: 2 | O6: FY0-FY2 | Q6: 0 | R6: LTM | S6: 1 | T6: 2 | V6: FY0-FY2 | X6: 0 | Y6: LTM | Z6: 1 | AA6: 2 | AC6: 0 | AD6: LTM | AE6: 1 | AF6: 2 | AH6: FY0-FY2 | AJ6: 0 | AK6: LTM | AL6: 1 | AM6: 2 | AO6: 0 | AP6: LTM | AQ6: 1 | AR6: 2 | AT6: FY0-FY2 | AV6: 0 | AW6: LTM | AX6: 1 | AY6: 2
C7: NASDAQ: DDOG | D7: =_xlfn.XLOOKUP(C7,Inputs!$D$10:$N$10,Inputs!$D$11:$N$11) -> Datadog | E7: =_xlfn.XLOOKUP(C7,Inputs!$D$10:$N$10,Inputs!$D$86:$N$86) -> 44177974 | F7: =_xlfn.XLOOKUP(C7,Inputs!$D$10:$N$10,Inputs!$D$77:$N$77) -> 47373805 | G7: =_xlfn.XLOOKUP(C7,Inputs!$D$10:$N$10,Inputs!$D$12:$N$12) -> 127.16 | H7: =_xlfn.XLOOKUP(C7,Inputs!$D$10:$N$10,Inputs!$D$84:$N$84)/'Operating Metrics'!AD7 -> -3.8793773 | J7: =_xlfn.XLOOKUP(C7,Inputs!$D$10:$N$10,Inputs!$D$184:$N$184) -> 3427158 | K7: =_xlfn.XLOOKUP(C7,Inputs!$D$10:$N$10,Inputs!$D$173:$N$173) -> 3427158 | L7: =_xlfn.XLOOKUP(C7,Inputs!$D$10:$N$10,Inputs!$D$185:$N$185) -> 4121580 | M7: =_xlfn.XLOOKUP(C7,Inputs!$D$10:$N$10,Inputs!$D$186:$N$186) -> 4930010 | O7: =(M7/J7)^(1/($M$6-$J$6))-1 -> 0.19938009 | Q7: =_xlfn.XLOOKUP(C7,Inputs!$D$10:$N$10,Inputs!$D$200:$N$200) -> 768044 | R7: =_xlfn.XLOOKUP(C7,Inputs!$D$10:$N$10,Inputs!$D$175:$N$175) -> 768044 | S7: =_xlfn.XLOOKUP(C7,Inputs!$D$10:$N$10,Inputs!$D$201:$N$201) -> 879310 | T7: =_xlfn.XLOOKUP(C7,Inputs!$D$10:$N$10,Inputs!$D$202:$N$202) -> 1113080 | V7: =(T7/Q7)^(1/($T$6-$Q$6))-1 -> 0.2038438 | X7: =Q7/J7 -> 0.22410522 | Y7: =R7/K7 -> 0.22410522 | Z7: =S7/L7 -> 0.21334294 | AA7: =T7/M7 -> 0.22577642 | AC7: =_xlfn.XLOOKUP(C7,Inputs!$D$10:$N$10,Inputs!$D$192:$N$192) -> 823800 | AD7: =_xlfn.XLOOKUP(C7,Inputs!$D$10:$N$10,Inputs!$D$174:$N$174) -> 823800 | AE7: =_xlfn.XLOOKUP(C7,Inputs!$D$10:$N$10,Inputs!$D$193:$N$193) -> 987200 | AF7: =_xlfn.XLOOKUP(C7,Inputs!$D$10:$N$10,Inputs!$D$194:$N$194) -> 1221230 | AH7: =(AF7/AC7)^(1/($AF$6-$AC$6))-1 -> 0.2175529 | AJ7: =AC7/J7 -> 0.24037409 | AK7: =AD7/K7 -> 0.24037409 | AL7: =AE7/L7 -> 0.2395198 | AM7: =AF7/M7 -> 0.24771349 | AO7: =_xlfn.XLOOKUP(C7,Inputs!$D$10:$N$10,Inputs!$D$208:$N$208) -> 746582 | AP7: =_xlfn.XLOOKUP(C7,Inputs!$D$10:$N$10,Inputs!$D$176:$N$176) -> 746582 | AQ7: =_xlfn.XLOOKUP(C7,Inputs!$D$10:$N$10,Inputs!$D$209:$N$209) -> 797830 | AR7: =_xlfn.XLOOKUP(C7,Inputs!$D$10:$N$10,Inputs!$D$210:$N$210) -> 1019470 | AT7: =(AR7/AO7)^(1/($AR$6-$AO$6))-1 -> 0.16855314 | AV7: =AO7/J7 -> 0.21784289 | AW7: =AP7/K7 -> 0.21784289 | AX7: =AQ7/L7 -> 0.19357382 | AY7: =AR7/M7 -> 0.20678863
C8: NYSE: SNOW | D8: =_xlfn.XLOOKUP(C8,Inputs!$D$10:$N$10,Inputs!$D$11:$N$11) -> Snowflake | E8: =_xlfn.XLOOKUP(C8,Inputs!$D$10:$N$10,Inputs!$D$86:$N$86) -> 66703555 | F8: =_xlfn.XLOOKUP(C8,Inputs!$D$10:$N$10,Inputs!$D$77:$N$77) -> 69648794 | G8: =_xlfn.XLOOKUP(C8,Inputs!$D$10:$N$10,Inputs!$D$12:$N$12) -> 177.25 | H8: =_xlfn.XLOOKUP(C8,Inputs!$D$10:$N$10,Inputs!$D$84:$N$84)/'Operating Metrics'!AD8 -> -3.3011454 | J8: =_xlfn.XLOOKUP(C8,Inputs!$D$10:$N$10,Inputs!$D$184:$N$184) -> 3626396 | K8: =_xlfn.XLOOKUP(C8,Inputs!$D$10:$N$10,Inputs!$D$173:$N$173) -> 4386722 | L8: =_xlfn.XLOOKUP(C8,Inputs!$D$10:$N$10,Inputs!$D$185:$N$185) -> 4683950 | M8: =_xlfn.XLOOKUP(C8,Inputs!$D$10:$N$10,Inputs!$D$186:$N$186) -> 5917810 | O8: =(M8/J8)^(1/($M$6-$J$6))-1 -> 0.27744701 | Q8: =_xlfn.XLOOKUP(C8,Inputs!$D$10:$N$10,Inputs!$D$200:$N$200) -> 468873 | R8: =_xlfn.XLOOKUP(C8,Inputs!$D$10:$N$10,Inputs!$D$175:$N$175) -> 680538 | S8: =_xlfn.XLOOKUP(C8,Inputs!$D$10:$N$10,Inputs!$D$201:$N$201) -> 489720 | T8: =_xlfn.XLOOKUP(C8,Inputs!$D$10:$N$10,Inputs!$D$202:$N$202) -> 739500 | V8: =(T8/Q8)^(1/($T$6-$Q$6))-1 -> 0.25586072 | X8: =Q8/J8 -> 0.12929448 | Y8: =R8/K8 -> 0.15513589 | Z8: =S8/L8 -> 0.10455278 | AA8: =T8/M8 -> 0.12496177 | AC8: =_xlfn.XLOOKUP(C8,Inputs!$D$10:$N$10,Inputs!$D$192:$N$192) -> 651381 | AD8: =_xlfn.XLOOKUP(C8,Inputs!$D$10:$N$10,Inputs!$D$174:$N$174) -> 892187 | AE8: =_xlfn.XLOOKUP(C8,Inputs!$D$10:$N$10,Inputs!$D$193:$N$193) -> 710160 | AF8: =_xlfn.XLOOKUP(C8,Inputs!$D$10:$N$10,Inputs!$D$194:$N$194) -> 909340 | AH8: =(AF8/AC8)^(1/($AF$6-$AC$6))-1 -> 0.18153232 | AJ8: =AC8/J8 -> 0.17962214 | AK8: =AD8/K8 -> 0.20338353 | AL8: =AE8/L8 -> 0.15161562 | AM8: =AF8/M8 -> 0.15366157 | AO8: =_xlfn.XLOOKUP(C8,Inputs!$D$10:$N$10,Inputs!$D$208:$N$208) -> 514002 | AP8: =_xlfn.XLOOKUP(C8,Inputs!$D$10:$N$10,Inputs!$D$176:$N$176) -> 657078 | AQ8: =_xlfn.XLOOKUP(C8,Inputs!$D$10:$N$10,Inputs!$D$209:$N$209) -> 670010 | AR8: =_xlfn.XLOOKUP(C8,Inputs!$D$10:$N$10,Inputs!$D$210:$N$210) -> 926220 | AT8: =(AR8/AO8)^(1/($AR$6-$AO$6))-1 -> 0.34237753 | AV8: =AO8/J8 -> 0.14173907 | AW8: =AP8/K8 -> 0.14978793 | AX8: =AQ8/L8 -> 0.1430438 | AY8: =AR8/M8 -> 0.15651398
C9: NYSE: HUBS | D9: =_xlfn.XLOOKUP(C9,Inputs!$D$10:$N$10,Inputs!$D$11:$N$11) -> Hubspot | E9: =_xlfn.XLOOKUP(C9,Inputs!$D$10:$N$10,Inputs!$D$86:$N$86) -> 12388367 | F9: =_xlfn.XLOOKUP(C9,Inputs!$D$10:$N$10,Inputs!$D$77:$N$77) -> 13966518 | G9: =_xlfn.XLOOKUP(C9,Inputs!$D$10:$N$10,Inputs!$D$12:$N$12) -> 257.63 | H9: =_xlfn.XLOOKUP(C9,Inputs!$D$10:$N$10,Inputs!$D$84:$N$84)/'Operating Metrics'!AD9 -> -2.1973821 | J9: =_xlfn.XLOOKUP(C9,Inputs!$D$10:$N$10,Inputs!$D$184:$N$184) -> 3131266 | K9: =_xlfn.XLOOKUP(C9,Inputs!$D$10:$N$10,Inputs!$D$173:$N$173) -> 3131266 | L9: =_xlfn.XLOOKUP(C9,Inputs!$D$10:$N$10,Inputs!$D$185:$N$185) -> 3696350 | M9: =_xlfn.XLOOKUP(C9,Inputs!$D$10:$N$10,Inputs!$D$186:$N$186) -> 4286170 | O9: =(M9/J9)^(1/($M$6-$J$6))-1 -> 0.16996997 | Q9: =_xlfn.XLOOKUP(C9,Inputs!$D$10:$N$10,Inputs!$D$200:$N$200) -> 581901 | R9: =_xlfn.XLOOKUP(C9,Inputs!$D$10:$N$10,Inputs!$D$175:$N$175) -> 581901 | S9: =_xlfn.XLOOKUP(C9,Inputs!$D$10:$N$10,Inputs!$D$201:$N$201) -> 740300 | T9: =_xlfn.XLOOKUP(C9,Inputs!$D$10:$N$10,Inputs!$D$202:$N$202) -> 907850 | V9: =(T9/Q9)^(1/($T$6-$Q$6))-1 -> 0.24905769 | X9: =Q9/J9 -> 0.1858357 | Y9: =R9/K9 -> 0.1858357 | Z9: =S9/L9 -> 0.20027865 | AA9: =T9/M9 -> 0.21180914 | AC9: =_xlfn.XLOOKUP(C9,Inputs!$D$10:$N$10,Inputs!$D$192:$N$192) -> 718196 | AD9: =_xlfn.XLOOKUP(C9,Inputs!$D$10:$N$10,Inputs!$D$174:$N$174) -> 718196 | AE9: =_xlfn.XLOOKUP(C9,Inputs!$D$10:$N$10,Inputs!$D$193:$N$193) -> 877440 | AF9: =_xlfn.XLOOKUP(C9,Inputs!$D$10:$N$10,Inputs!$D$194:$N$194) -> 1067570 | AH9: =(AF9/AC9)^(1/($AF$6-$AC$6))-1 -> 0.21920487 | AJ9: =AC9/J9 -> 0.22936282 | AK9: =AD9/K9 -> 0.22936282 | AL9: =AE9/L9 -> 0.23738012 | AM9: =AF9/M9 -> 0.24907318 | AO9: =_xlfn.XLOOKUP(C9,Inputs!$D$10:$N$10,Inputs!$D$208:$N$208) -> 515988 | AP9: =_xlfn.XLOOKUP(C9,Inputs!$D$10:$N$10,Inputs!$D$176:$N$176) -> 515988 | AQ9: =_xlfn.XLOOKUP(C9,Inputs!$D$10:$N$10,Inputs!$D$209:$N$209) -> 646520 | AR9: =_xlfn.XLOOKUP(C9,Inputs!$D$10:$N$10,Inputs!$D$210:$N$210) -> 793660 | AT9: =(AR9/AO9)^(1/($AR$6-$AO$6))-1 -> 0.24021633 | AV9: =AO9/J9 -> 0.16478574 | AW9: =AP9/K9 -> 0.16478574 | AX9: =AQ9/L9 -> 0.17490768 | AY9: =AR9/M9 -> 0.18516764
C10: NYSE: CRM | D10: =_xlfn.XLOOKUP(C10,Inputs!$D$10:$N$10,Inputs!$D$11:$N$11) -> Salesforce | E10: =_xlfn.XLOOKUP(C10,Inputs!$D$10:$N$10,Inputs!$D$86:$N$86) -> 195930600 | F10: =_xlfn.XLOOKUP(C10,Inputs!$D$10:$N$10,Inputs!$D$77:$N$77) -> 188319600 | G10: =_xlfn.XLOOKUP(C10,Inputs!$D$10:$N$10,Inputs!$D$12:$N$12) -> 199.28 | H10: =_xlfn.XLOOKUP(C10,Inputs!$D$10:$N$10,Inputs!$D$84:$N$84)/'Operating Metrics'!AD10 -> 0.42789678 | J10: =_xlfn.XLOOKUP(C10,Inputs!$D$10:$N$10,Inputs!$D$184:$N$184) -> 41525000 | K10: =_xlfn.XLOOKUP(C10,Inputs!$D$10:$N$10,Inputs!$D$173:$N$173) -> 41525000 | L10: =_xlfn.XLOOKUP(C10,Inputs!$D$10:$N$10,Inputs!$D$185:$N$185) -> 46128890 | M10: =_xlfn.XLOOKUP(C10,Inputs!$D$10:$N$10,Inputs!$D$186:$N$186) -> 50529780 | O10: =(M10/J10)^(1/($M$6-$J$6))-1 -> 0.10311016 | Q10: =_xlfn.XLOOKUP(C10,Inputs!$D$10:$N$10,Inputs!$D$200:$N$200) -> 14156000 | R10: =_xlfn.XLOOKUP(C10,Inputs!$D$10:$N$10,Inputs!$D$175:$N$175) -> 14156000 | S10: =_xlfn.XLOOKUP(C10,Inputs!$D$10:$N$10,Inputs!$D$201:$N$201) -> 15874340 | T10: =_xlfn.XLOOKUP(C10,Inputs!$D$10:$N$10,Inputs!$D$202:$N$202) -> 17848180 | V10: =(T10/Q10)^(1/($T$6-$Q$6))-1 -> 0.12286279 | X10: =Q10/J10 -> 0.34090307 | Y10: =R10/K10 -> 0.34090307 | Z10: =S10/L10 -> 0.34413011 | AA10: =T10/M10 -> 0.35322101 | AC10: =_xlfn.XLOOKUP(C10,Inputs!$D$10:$N$10,Inputs!$D$192:$N$192) -> 17787000 | AD10: =_xlfn.XLOOKUP(C10,Inputs!$D$10:$N$10,Inputs!$D$174:$N$174) -> 17787000 | AE10: =_xlfn.XLOOKUP(C10,Inputs!$D$10:$N$10,Inputs!$D$193:$N$193) -> 18191960 | AF10: =_xlfn.XLOOKUP(C10,Inputs!$D$10:$N$10,Inputs!$D$194:$N$194) -> 19354770 | AH10: =(AF10/AC10)^(1/($AF$6-$AC$6))-1 -> 0.043140134 | AJ10: =AC10/J10 -> 0.42834437 | AK10: =AD10/K10 -> 0.42834437 | AL10: =AE10/L10 -> 0.39437238 | AM10: =AF10/M10 -> 0.38303689 | AO10: =_xlfn.XLOOKUP(C10,Inputs!$D$10:$N$10,Inputs!$D$208:$N$208) -> 11969000 | AP10: =_xlfn.XLOOKUP(C10,Inputs!$D$10:$N$10,Inputs!$D$176:$N$176) -> 11969000 | AQ10: =_xlfn.XLOOKUP(C10,Inputs!$D$10:$N$10,Inputs!$D$209:$N$209) -> 12360630 | AR10: =_xlfn.XLOOKUP(C10,Inputs!$D$10:$N$10,Inputs!$D$210:$N$210) -> 13906060 | AT10: =(AR10/AO10)^(1/($AR$6-$AO$6))-1 -> 0.077886707 | AV10: =AO10/J10 -> 0.288236 | AW10: =AP10/K10 -> 0.288236 | AX10: =AQ10/L10 -> 0.26795854 | AY10: =AR10/M10 -> 0.27520524
C11: NYSE: ORCL | D11: =_xlfn.XLOOKUP(C11,Inputs!$D$10:$N$10,Inputs!$D$11:$N$11) -> Oracle | E11: =_xlfn.XLOOKUP(C11,Inputs!$D$10:$N$10,Inputs!$D$86:$N$86) -> 6.0351346e+08 | F11: =_xlfn.XLOOKUP(C11,Inputs!$D$10:$N$10,Inputs!$D$77:$N$77) -> 4.8122046e+08 | G11: =_xlfn.XLOOKUP(C11,Inputs!$D$10:$N$10,Inputs!$D$12:$N$12) -> 159.16 | H11: =_xlfn.XLOOKUP(C11,Inputs!$D$10:$N$10,Inputs!$D$84:$N$84)/'Operating Metrics'!AD11 -> 3.4435152 | J11: =_xlfn.XLOOKUP(C11,Inputs!$D$10:$N$10,Inputs!$D$184:$N$184) -> 57399000 | K11: =_xlfn.XLOOKUP(C11,Inputs!$D$10:$N$10,Inputs!$D$173:$N$173) -> 64076000 | L11: =_xlfn.XLOOKUP(C11,Inputs!$D$10:$N$10,Inputs!$D$185:$N$185) -> 67119090 | M11: =_xlfn.XLOOKUP(C11,Inputs!$D$10:$N$10,Inputs!$D$186:$N$186) -> 88996530 | O11: =(M11/J11)^(1/($M$6-$J$6))-1 -> 0.24518641 | Q11: =_xlfn.XLOOKUP(C11,Inputs!$D$10:$N$10,Inputs!$D$200:$N$200) -> 25033000 | R11: =_xlfn.XLOOKUP(C11,Inputs!$D$10:$N$10,Inputs!$D$175:$N$175) -> 27371000 | S11: =_xlfn.XLOOKUP(C11,Inputs!$D$10:$N$10,Inputs!$D$201:$N$201) -> 28536000 | T11: =_xlfn.XLOOKUP(C11,Inputs!$D$10:$N$10,Inputs!$D$202:$N$202) -> 34665560 | V11: =(T11/Q11)^(1/($T$6-$Q$6))-1 -> 0.17677291 | X11: =Q11/J11 -> 0.43612258 | Y11: =R11/K11 -> 0.42716462 | Z11: =S11/L11 -> 0.42515475 | AA11: =T11/M11 -> 0.38951586 | AC11: =_xlfn.XLOOKUP(C11,Inputs!$D$10:$N$10,Inputs!$D$192:$N$192) -> 31207000 | AD11: =_xlfn.XLOOKUP(C11,Inputs!$D$10:$N$10,Inputs!$D$174:$N$174) -> 35514000 | AE11: =_xlfn.XLOOKUP(C11,Inputs!$D$10:$N$10,Inputs!$D$193:$N$193) -> 36359120 | AF11: =_xlfn.XLOOKUP(C11,Inputs!$D$10:$N$10,Inputs!$D$194:$N$194) -> 45937920 | AH11: =(AF11/AC11)^(1/($AF$6-$AC$6))-1 -> 0.21327613 | AJ11: =AC11/J11 -> 0.54368543 | AK11: =AD11/K11 -> 0.55424808 | AL11: =AE11/L11 -> 0.54171056 | AM11: =AF11/M11 -> 0.51617653 | AO11: =_xlfn.XLOOKUP(C11,Inputs!$D$10:$N$10,Inputs!$D$208:$N$208) -> 17284000 | AP11: =_xlfn.XLOOKUP(C11,Inputs!$D$10:$N$10,Inputs!$D$176:$N$176) -> 20984000 | AQ11: =_xlfn.XLOOKUP(C11,Inputs!$D$10:$N$10,Inputs!$D$209:$N$209) -> 21860860 | AR11: =_xlfn.XLOOKUP(C11,Inputs!$D$10:$N$10,Inputs!$D$210:$N$210) -> 23799820 | AT11: =(AR11/AO11)^(1/($AR$6-$AO$6))-1 -> 0.17345032 | AV11: =AO11/J11 -> 0.30112023 | AW11: =AP11/K11 -> 0.32748611 | AX11: =AQ11/L11 -> 0.32570257 | AY11: =AR11/M11 -> 0.26742413
C12: NASDAQ: PANW | D12: =_xlfn.XLOOKUP(C12,Inputs!$D$10:$N$10,Inputs!$D$11:$N$11) -> Palo Alto Networks | E12: =_xlfn.XLOOKUP(C12,Inputs!$D$10:$N$10,Inputs!$D$86:$N$86) -> 136728940 | F12: =_xlfn.XLOOKUP(C12,Inputs!$D$10:$N$10,Inputs!$D$77:$N$77) -> 140892940 | G12: =_xlfn.XLOOKUP(C12,Inputs!$D$10:$N$10,Inputs!$D$12:$N$12) -> 168.13 | H12: =_xlfn.XLOOKUP(C12,Inputs!$D$10:$N$10,Inputs!$D$84:$N$84)/'Operating Metrics'!AD12 -> -1.2702093 | J12: =_xlfn.XLOOKUP(C12,Inputs!$D$10:$N$10,Inputs!$D$184:$N$184) -> 9221500 | K12: =_xlfn.XLOOKUP(C12,Inputs!$D$10:$N$10,Inputs!$D$173:$N$173) -> 9893300 | L12: =_xlfn.XLOOKUP(C12,Inputs!$D$10:$N$10,Inputs!$D$185:$N$185) -> 11294170 | M12: =_xlfn.XLOOKUP(C12,Inputs!$D$10:$N$10,Inputs!$D$186:$N$186) -> 13571780 | O12: =(M12/J12)^(1/($M$6-$J$6))-1 -> 0.21315871 | Q12: =_xlfn.XLOOKUP(C12,Inputs!$D$10:$N$10,Inputs!$D$200:$N$200) -> 2651900 | R12: =_xlfn.XLOOKUP(C12,Inputs!$D$10:$N$10,Inputs!$D$175:$N$175) -> 2926300 | S12: =_xlfn.XLOOKUP(C12,Inputs!$D$10:$N$10,Inputs!$D$201:$N$201) -> 3244140 | T12: =_xlfn.XLOOKUP(C12,Inputs!$D$10:$N$10,Inputs!$D$202:$N$202) -> 3988560 | V12: =(T12/Q12)^(1/($T$6-$Q$6))-1 -> 0.22639252 | X12: =Q12/J12 -> 0.28757794 | Y12: =R12/K12 -> 0.29578604 | Z12: =S12/L12 -> 0.28724023 | AA12: =T12/M12 -> 0.29388628 | AC12: =_xlfn.XLOOKUP(C12,Inputs!$D$10:$N$10,Inputs!$D$192:$N$192) -> 2995300 | AD12: =_xlfn.XLOOKUP(C12,Inputs!$D$10:$N$10,Inputs!$D$174:$N$174) -> 3278200 | AE12: =_xlfn.XLOOKUP(C12,Inputs!$D$10:$N$10,Inputs!$D$193:$N$193) -> 3498640 | AF12: =_xlfn.XLOOKUP(C12,Inputs!$D$10:$N$10,Inputs!$D$194:$N$194) -> 4212200 | AH12: =(AF12/AC12)^(1/($AF$6-$AC$6))-1 -> 0.18586248 | AJ12: =AC12/J12 -> 0.324817 | AK12: =AD12/K12 -> 0.33135556 | AL12: =AE12/L12 -> 0.30977398 | AM12: =AF12/M12 -> 0.31036459 | AO12: =_xlfn.XLOOKUP(C12,Inputs!$D$10:$N$10,Inputs!$D$208:$N$208) -> 2344500 | AP12: =_xlfn.XLOOKUP(C12,Inputs!$D$10:$N$10,Inputs!$D$176:$N$176) -> 2627900 | AQ12: =_xlfn.XLOOKUP(C12,Inputs!$D$10:$N$10,Inputs!$D$209:$N$209) -> 2836720 | AR12: =_xlfn.XLOOKUP(C12,Inputs!$D$10:$N$10,Inputs!$D$210:$N$210) -> 3355350 | AT12: =(AR12/AO12)^(1/($AR$6-$AO$6))-1 -> 0.19631017 | AV12: =AO12/J12 -> 0.2542428 | AW12: =AP12/K12 -> 0.26562421 | AX12: =AQ12/L12 -> 0.25116675 | AY12: =AR12/M12 -> 0.24722991
C14: Mean | H14: =AVERAGE(H7:H12) -> -1.1294503 | O14: =AVERAGE(O7:O12) -> 0.20137539 | V14: =AVERAGE(V7:V12) -> 0.2057984 | AH14: =AVERAGE(AH7:AH12) -> 0.17676147 | AT14: =AVERAGE(AT7:AT12) -> 0.19979903
C15: Median | H15: =MEDIAN(H7:H12) -> -1.7337957 | O15: =MEDIAN(O7:O12) -> 0.2062694 | V15: =MEDIAN(V7:V12) -> 0.21511816 | AH15: =MEDIAN(AH7:AH12) -> 0.1995693 | AT15: =MEDIAN(AT7:AT12) -> 0.18488025
C16: Min | H16: =MIN(H7:H12) -> -3.8793773 | O16: =MIN(O7:O12) -> 0.10311016 | V16: =MIN(V7:V12) -> 0.12286279 | AH16: =MIN(AH7:AH12) -> 0.043140134 | AT16: =MIN(AT7:AT12) -> 0.077886707
C17: Max | H17: =MAX(H7:H12) -> 3.4435152 | O17: =MAX(O7:O12) -> 0.27744701 | V17: =MAX(V7:V12) -> 0.25586072 | AH17: =MAX(AH7:AH12) -> 0.21920487 | AT17: =MAX(AT7:AT12) -> 0.34237753

Sheet Valuation
C2: Comparable Company Valuation
C3: $USD Thousand except per share data
H5: EV/Revenue | L5: EV/EBIT | P5: EV/EBITDA | T5: Price/Earnings
C6: Ticker | D6: Company | E6: Enterprise Value | F6: Market Capitalization | G6: Price | H6: LTM | I6: FY1 | J6: FY2 | L6: LTM | M6: FY1 | N6: FY2 | P6: LTM | Q6: FY1 | R6: FY2 | T6: LTM | U6: FY1 | V6: FY2
C7: NASDAQ: DDOG | D7: =_xlfn.XLOOKUP(C7,Inputs!$D$10:$N$10,Inputs!$D$11:$N$11) -> Datadog | E7: ='Operating Metrics'!E7 -> 44177974 | F7: ='Operating Metrics'!F7 -> 47373805 | G7: ='Operating Metrics'!G7 -> 127.16 | H7: =E7/'Operating Metrics'!K7 -> 12.890556 | I7: =F7/'Operating Metrics'!L7 -> 11.494088 | J7: =E7/'Operating Metrics'!M7 -> 8.9610312 | L7: =$E7/'Operating Metrics'!R7 -> 57.520108 | M7: =$E7/'Operating Metrics'!S7 -> 50.241637 | N7: =$E7/'Operating Metrics'!T7 -> 39.689846 | P7: =$E7/'Operating Metrics'!AD7 -> 53.627062 | Q7: =$E7/'Operating Metrics'!AE7 -> 44.750784 | R7: =$E7/'Operating Metrics'!AF7 -> 36.174982 | T7: =$F7/'Operating Metrics'!AP7 -> 63.454255 | U7: =$F7/'Operating Metrics'!AQ7 -> 59.378319 | V7: =$F7/'Operating Metrics'!AR7 -> 46.469052
C8: NYSE: SNOW | D8: =_xlfn.XLOOKUP(C8,Inputs!$D$10:$N$10,Inputs!$D$11:$N$11) -> Snowflake | E8: ='Operating Metrics'!E8 -> 66703555 | F8: ='Operating Metrics'!F8 -> 69648794 | G8: ='Operating Metrics'!G8 -> 177.25 | H8: =E8/'Operating Metrics'!K8 -> 15.205786 | I8: =F8/'Operating Metrics'!L8 -> 14.869671 | J8: =E8/'Operating Metrics'!M8 -> 11.271662 | L8: =$E8/'Operating Metrics'!R8 -> 98.015915 | M8: =$E8/'Operating Metrics'!S8 -> 136.20754 | N8: =$E8/'Operating Metrics'!T8 -> 90.200885 | P8: =$E8/'Operating Metrics'!AD8 -> 74.764096 | Q8: =$E8/'Operating Metrics'!AE8 -> 93.927502 | R8: =$E8/'Operating Metrics'!AF8 -> 73.353811 | T8: =$F8/'Operating Metrics'!AP8 -> 105.99776 | U8: =$F8/'Operating Metrics'!AQ8 -> 103.95187 | V8: =$F8/'Operating Metrics'!AR8 -> 75.196815
C9: NYSE: HUBS | D9: =_xlfn.XLOOKUP(C9,Inputs!$D$10:$N$10,Inputs!$D$11:$N$11) -> Hubspot | E9: ='Operating Metrics'!E9 -> 12388367 | F9: ='Operating Metrics'!F9 -> 13966518 | G9: ='Operating Metrics'!G9 -> 257.63 | H9: =E9/'Operating Metrics'!K9 -> 3.9563445 | I9: =F9/'Operating Metrics'!L9 -> 3.778462 | J9: =E9/'Operating Metrics'!M9 -> 2.8903116 | L9: =$E9/'Operating Metrics'!R9 -> 21.289475 | M9: =$E9/'Operating Metrics'!S9 -> 16.734252 | N9: =$E9/'Operating Metrics'!T9 -> 13.64583 | P9: =$E9/'Operating Metrics'!AD9 -> 17.249284 | Q9: =$E9/'Operating Metrics'!AE9 -> 14.118763 | R9: =$E9/'Operating Metrics'!AF9 -> 11.604267 | T9: =$F9/'Operating Metrics'!AP9 -> 27.067525 | U9: =$F9/'Operating Metrics'!AQ9 -> 21.602608 | V9: =$F9/'Operating Metrics'!AR9 -> 17.597609
C10: NYSE: CRM | D10: =_xlfn.XLOOKUP(C10,Inputs!$D$10:$N$10,Inputs!$D$11:$N$11) -> Salesforce | E10: ='Operating Metrics'!E10 -> 195930600 | F10: ='Operating Metrics'!F10 -> 188319600 | G10: ='Operating Metrics'!G10 -> 199.28 | H10: =E10/'Operating Metrics'!K10 -> 4.7183769 | I10: =F10/'Operating Metrics'!L10 -> 4.0824655 | J10: =E10/'Operating Metrics'!M10 -> 3.8775273 | L10: =$E10/'Operating Metrics'!R10 -> 13.840817 | M10: =$E10/'Operating Metrics'!S10 -> 12.342598 | N10: =$E10/'Operating Metrics'!T10 -> 10.977623 | P10: =$E10/'Operating Metrics'!AD10 -> 11.015382 | Q10: =$E10/'Operating Metrics'!AE10 -> 10.770175 | R10: =$E10/'Operating Metrics'!AF10 -> 10.123117 | T10: =$F10/'Operating Metrics'!AP10 -> 15.733946 | U10: =$F10/'Operating Metrics'!AQ10 -> 15.235437 | V10: =$F10/'Operating Metrics'!AR10 -> 13.542269
C11: NYSE: ORCL | D11: =_xlfn.XLOOKUP(C11,Inputs!$D$10:$N$10,Inputs!$D$11:$N$11) -> Oracle | E11: ='Operating Metrics'!E11 -> 6.0351346e+08 | F11: ='Operating Metrics'!F11 -> 4.8122046e+08 | G11: ='Operating Metrics'!G11 -> 159.16 | H11: =E11/'Operating Metrics'!K11 -> 9.4187131 | I11: =F11/'Operating Metrics'!L11 -> 7.1696512 | J11: =E11/'Operating Metrics'!M11 -> 6.7813145 | L11: =$E11/'Operating Metrics'!R11 -> 22.049376 | M11: =$E11/'Operating Metrics'!S11 -> 21.149196 | N11: =$E11/'Operating Metrics'!T11 -> 17.409598 | P11: =$E11/'Operating Metrics'!AD11 -> 16.993677 | Q11: =$E11/'Operating Metrics'!AE11 -> 16.598682 | R11: =$E11/'Operating Metrics'!AF11 -> 13.137588 | T11: =$F11/'Operating Metrics'!AP11 -> 22.932733 | U11: =$F11/'Operating Metrics'!AQ11 -> 22.012879 | V11: =$F11/'Operating Metrics'!AR11 -> 20.2195
C12: NASDAQ: PANW | D12: =_xlfn.XLOOKUP(C12,Inputs!$D$10:$N$10,Inputs!$D$11:$N$11) -> Palo Alto Networks | E12: ='Operating Metrics'!E12 -> 136728940 | F12: ='Operating Metrics'!F12 -> 140892940 | G12: ='Operating Metrics'!G12 -> 168.13 | H12: =E12/'Operating Metrics'!K12 -> 13.820357 | I12: =F12/'Operating Metrics'!L12 -> 12.474838 | J12: =E12/'Operating Metrics'!M12 -> 10.074503 | L12: =$E12/'Operating Metrics'!R12 -> 46.72417 | M12: =$E12/'Operating Metrics'!S12 -> 42.146436 | N12: =$E12/'Operating Metrics'!T12 -> 34.280277 | P12: =$E12/'Operating Metrics'!AD12 -> 41.708541 | Q12: =$E12/'Operating Metrics'!AE12 -> 39.080597 | R12: =$E12/'Operating Metrics'!AF12 -> 32.46022 | T12: =$F12/'Operating Metrics'!AP12 -> 53.61427 | U12: =$F12/'Operating Metrics'!AQ12 -> 49.667553 | V12: =$F12/'Operating Metrics'!AR12 -> 41.990535
C14: Mean | H14: =AVERAGE(H7:H12) -> 10.001689 | I14: =AVERAGE(I7:I12) -> 8.9781959 | J14: =AVERAGE(J7:J12) -> 7.3093916 | L14: =AVERAGE(L7:L12) -> 43.239977 | M14: =AVERAGE(M7:M12) -> 46.470276 | N14: =AVERAGE(N7:N12) -> 34.367343 | P14: =AVERAGE(P7:P12) -> 35.893007 | Q14: =AVERAGE(Q7:Q12) -> 36.541084 | R14: =AVERAGE(R7:R12) -> 29.475664 | T14: =AVERAGE(T7:T12) -> 48.133414 | U14: =AVERAGE(U7:U12) -> 45.308111 | V14: =AVERAGE(V7:V12) -> 35.835963
C15: Median | H15: =MEDIAN(H7:H12) -> 11.154635 | I15: =MEDIAN(I7:I12) -> 9.3318697 | J15: =MEDIAN(J7:J12) -> 7.8711729 | L15: =MEDIAN(L7:L12) -> 34.386773 | M15: =MEDIAN(M7:M12) -> 31.647816 | N15: =MEDIAN(N7:N12) -> 25.844937 | P15: =MEDIAN(P7:P12) -> 29.478913 | Q15: =MEDIAN(Q7:Q12) -> 27.839639 | R15: =MEDIAN(R7:R12) -> 22.798904 | T15: =MEDIAN(T7:T12) -> 40.340897 | U15: =MEDIAN(U7:U12) -> 35.840216 | V15: =MEDIAN(V7:V12) -> 31.105017
C16: Min | H16: =MIN(H7:H12) -> 3.9563445 | I16: =MIN(I7:I12) -> 3.778462 | J16: =MIN(J7:J12) -> 2.8903116 | L16: =MIN(L7:L12) -> 13.840817 | M16: =MIN(M7:M12) -> 12.342598 | N16: =MIN(N7:N12) -> 10.977623 | P16: =MIN(P7:P12) -> 11.015382 | Q16: =MIN(Q7:Q12) -> 10.770175 | R16: =MIN(R7:R12) -> 10.123117 | T16: =MIN(T7:T12) -> 15.733946 | U16: =MIN(U7:U12) -> 15.235437 | V16: =MIN(V7:V12) -> 13.542269
C17: Max | H17: =MAX(H7:H12) -> 15.205786 | I17: =MAX(I7:I12) -> 14.869671 | J17: =MAX(J7:J12) -> 11.271662 | L17: =MAX(L7:L12) -> 98.015915 | M17: =MAX(M7:M12) -> 136.20754 | N17: =MAX(N7:N12) -> 90.200885 | P17: =MAX(P7:P12) -> 74.764096 | Q17: =MAX(Q7:Q12) -> 93.927502 | R17: =MAX(R7:R12) -> 73.353811 | T17: =MAX(T7:T12) -> 105.99776 | U17: =MAX(U7:U12) -> 103.95187 | V17: =MAX(V7:V12) -> 75.196815
